Workbook

Sheet Faturado mensal
M1: =SUM(faturado[jan-25]) -> 3619127.4 | N1: =SUM(faturado[fev-25]) -> 4320391.3 | O1: =SUM(faturado[mar-25]) -> 3902344.3 | P1: =SUM(faturado[abr-25]) -> 3829344.8 | Q1: =SUM(faturado[mai-25]) -> 4132901.8 | R1: =SUM(faturado[jun-25]) -> 4141150.1 | S1: =SUM(faturado[jul-25]) -> 4286340.2 | T1: =SUM(faturado[ago-25]) -> 4032447.3 | U1: =SUM(faturado[set-25]) -> 5129442.6 | V1: =SUM(faturado[out-25]) -> 4946827.6 | W1: =SUM(faturado[nov-25]) -> 4434241.2 | X1: =SUM(faturado[dez-25]) -> 5035170.3 | Y1: =SUM(faturado[2025]) -> 55977647 | Z1: =SUM(faturado[jan-26]) -> 3634915.2 | AA1: =SUM(faturado[fev-26]) -> 4723958.9 | AB1: =SUM(faturado[mar-26]) -> 4291708.5 | AC1: =SUM(faturado[abr-26]) -> 4992439.9 | AD1: =SUM(faturado[mai-26]) -> 4845613.8 | AE1: =SUM(faturado[jun-26]) -> 3848780.6 | AF1: =SUM(faturado[jul-26]) -> 0 | AG1: =SUM(faturado[ago-26]) -> 0 | AH1: =SUM(faturado[set-26]) -> 0 | AI1: =SUM(faturado[out-26]) -> 0 | AJ1: =SUM(faturado[nov-26]) -> 0 | AK1: =SUM(faturado[dez-26]) -> 0 | AL1: =SUM(faturado[2026]) -> 26581067
A2: contrato | B2: pn_fornecedor | C2: descricao_fornecedor | D2: status_do_contrato | E2: departamento | F2: família | G2: gestão | H2: curva | I2: referencia_a | J2: descricao_condicao_de_pagamento | K2: depto_de_compras | L2: descricao_dpto_de_compras | M2: jan-25 | N2: fev-25 | O2: mar-25 | P2: abr-25 | Q2: mai-25 | R2: jun-25 | S2: jul-25 | T2: ago-25 | U2: set-25 | V2: out-25 | W2: nov-25 | X2: dez-25 | Y2: 2025 | Z2: jan-26 | AA2: fev-26 | AB2: mar-26 | AC2: abr-26 | AD2: mai-26 | AE2: jun-26 | AF2: jul-26 | AG2: ago-26 | AH2: set-26 | AI2: out-26 | AJ2: nov-26 | AK2: dez-26 | AL2: 2026
A3: CS0000647 | B3: 090030154 | C3: OPUS CONSULT TEC E EMPRESARIAL | D3: Concluído | G3: INDUSTRIAL SRS | H3: C | I3: OPUS CONSULT TEC E EMPRESARIAL | J3: 30 DIAS | K3: SRSFAB | L3: PRGM . COMPRAS - SRS - FABRICA | M3: =SUMIFS(#REF!,#REF!, $A3,#REF!, ">="&'Faturado mensal'!M$2,#REF!, "<"&EOMONTH('Faturado mensal'!M$2,0)) -> 0 | N3: =SUMIFS(#REF!,#REF!, $A3,#REF!, ">="&'Faturado mensal'!N$2,#REF!, "<"&EOMONTH('Faturado mensal'!N$2,0)) -> 0 | O3: =SUMIFS(#REF!,#REF!, $A3,#REF!, ">="&'Faturado mensal'!O$2,#REF!, "<"&EOMONTH('Faturado mensal'!O$2,0)) -> 0 | P3: =SUMIFS(#REF!,#REF!, $A3,#REF!, ">="&'Faturado mensal'!P$2,#REF!, "<"&EOMONTH('Faturado mensal'!P$2,0)) -> 0 | Q3: =SUMIFS(#REF!,#REF!, $A3,#REF!, ">="&'Faturado mensal'!Q$2,#REF!, "<"&EOMONTH('Faturado mensal'!Q$2,0)) -> 0 | R3: =SUMIFS(#REF!,#REF!, $A3,#REF!, ">="&'Faturado mensal'!R$2,#REF!, "<"&EOMONTH('Faturado mensal'!R$2,0)) -> 0 | S3: =SUMIFS(#REF!,#REF!, $A3,#REF!, ">="&'Faturado mensal'!S$2,#REF!, "<"&EOMONTH('Faturado mensal'!S$2,0)) -> 0 | T3: =SUMIFS(#REF!,#REF!, $A3,#REF!, ">="&'Faturado mensal'!T$2,#REF!, "<"&EOMONTH('Faturado mensal'!T$2,0)) -> 0 | ... X3: =SUMIFS(#REF!,#REF!, $A3,#REF!, ">="&'Faturado mensal'!X$2,#REF!, "<"&EOMONTH('Faturado mensal'!X$2,0)) -> 0 | Y3: =SUMIFS(#REF!,#REF!, $A3,#REF!, ">="&'Faturado mensal'!M$2,#REF!, "<"&EOMONTH('Faturado mensal'!M$2,12)) -> 0 | Z3: =SUMIFS(#REF!,#REF!, $A3,#REF!, ">="&'Faturado mensal'!Z$2,#REF!, "<"&EOMONTH('Faturado mensal'!Z$2,0)) -> 0 | AA3: =SUMIFS(#REF!,#REF!, $A3,#REF!, ">="&'Faturado mensal'!AA$2,#REF!, "<"&EOMONTH('Faturado mensal'!AA$2,0)) -> 0 | AB3: =SUMIFS(#REF!,#REF!, $A3,#REF!, ">="&'Faturado mensal'!AB$2,#REF!, "<"&EOMONTH('Faturado mensal'!AB$2,0)) -> 0 | AC3: =SUMIFS(#REF!,#REF!, $A3,#REF!, ">="&'Faturado mensal'!AC$2,#REF!, "<"&EOMONTH('Faturado mensal'!AC$2,0)) -> 0 | AD3: =SUMIFS(#REF!,#REF!, $A3,#REF!, ">="&'Faturado mensal'!AD$2,#REF!, "<"&EOMONTH('Faturado mensal'!AD$2,0)) -> 0 | AE3: =SUMIFS(#REF!,#REF!, $A3,#REF!, ">="&'Faturado mensal'!AE$2,#REF!, "<"&EOMONTH('Faturado mensal'!AE$2,0)) -> 0 | AF3: =SUMIFS(#REF!,#REF!, $A3,#REF!, ">="&'Faturado mensal'!AF$2,#REF!, "<"&EOMONTH('Faturado mensal'!AF$2,0)) -> 0 | AG3: =SUMIFS(#REF!,#REF!, $A3,#REF!, ">="&'Faturado mensal'!AG$2,#REF!, "<"&EOMONTH('Faturado mensal'!AG$2,0)) -> 0 | ... AK3: =SUMIFS(#REF!,#REF!, $A3,#REF!, ">="&'Faturado mensal'!AK$2,#REF!, "<"&EOMONTH('Faturado mensal'!AK$2,0)) -> 0 | AL3: =SUMIFS(#REF!,#REF!, $A3,#REF!, ">="&Z$2,#REF!, "<"&EOMONTH(AK$2,0)) -> 0
A4: CS0000649 | B4: 070006685 | C4: SERPRAM SERV PREST A M H LTDA | D4: Concluído | I4: SERPRAM SERV PREST A M H LTDA | J4: 30 DIAS | K4: SRSFAB | L4: PRGM . COMPRAS - SRS - FABRICA | M4: =SUMIFS(#REF!,#REF!, $A4,#REF!, ">="&'Faturado mensal'!M$2,#REF!, "<"&EOMONTH('Faturado mensal'!M$2,0)) -> 0 | N4: =SUMIFS(#REF!,#REF!, $A4,#REF!, ">="&'Faturado mensal'!N$2,#REF!, "<"&EOMONTH('Faturado mensal'!N$2,0)) -> 0 | O4: =SUMIFS(#REF!,#REF!, $A4,#REF!, ">="&'Faturado mensal'!O$2,#REF!, "<"&EOMONTH('Faturado mensal'!O$2,0)) -> 0 | P4: =SUMIFS(#REF!,#REF!, $A4,#REF!, ">="&'Faturado mensal'!P$2,#REF!, "<"&EOMONTH('Faturado mensal'!P$2,0)) -> 0 | Q4: =SUMIFS(#REF!,#REF!, $A4,#REF!, ">="&'Faturado mensal'!Q$2,#REF!, "<"&EOMONTH('Faturado mensal'!Q$2,0)) -> 0 | R4: =SUMIFS(#REF!,#REF!, $A4,#REF!, ">="&'Faturado mensal'!R$2,#REF!, "<"&EOMONTH('Faturado mensal'!R$2,0)) -> 0 | S4: =SUMIFS(#REF!,#REF!, $A4,#REF!, ">="&'Faturado mensal'!S$2,#REF!, "<"&EOMONTH('Faturado mensal'!S$2,0)) -> 0 | T4: =SUMIFS(#REF!,#REF!, $A4,#REF!, ">="&'Faturado mensal'!T$2,#REF!, "<"&EOMONTH('Faturado mensal'!T$2,0)) -> 0 | ... X4: =SUMIFS(#REF!,#REF!, $A4,#REF!, ">="&'Faturado mensal'!X$2,#REF!, "<"&EOMONTH('Faturado mensal'!X$2,0)) -> 0 | Y4: =SUMIFS(#REF!,#REF!, $A4,#REF!, ">="&'Faturado mensal'!M$2,#REF!, "<"&EOMONTH('Faturado mensal'!M$2,12)) -> 0 | Z4: =SUMIFS(#REF!,#REF!, $A4,#REF!, ">="&'Faturado mensal'!Z$2,#REF!, "<"&EOMONTH('Faturado mensal'!Z$2,0)) -> 0 | AA4: =SUMIFS(#REF!,#REF!, $A4,#REF!, ">="&'Faturado mensal'!AA$2,#REF!, "<"&EOMONTH('Faturado mensal'!AA$2,0)) -> 0 | AB4: =SUMIFS(#REF!,#REF!, $A4,#REF!, ">="&'Faturado mensal'!AB$2,#REF!, "<"&EOMONTH('Faturado mensal'!AB$2,0)) -> 0 | AC4: =SUMIFS(#REF!,#REF!, $A4,#REF!, ">="&'Faturado mensal'!AC$2,#REF!, "<"&EOMONTH('Faturado mensal'!AC$2,0)) -> 0 | AD4: =SUMIFS(#REF!,#REF!, $A4,#REF!, ">="&'Faturado mensal'!AD$2,#REF!, "<"&EOMONTH('Faturado mensal'!AD$2,0)) -> 0 | AE4: =SUMIFS(#REF!,#REF!, $A4,#REF!, ">="&'Faturado mensal'!AE$2,#REF!, "<"&EOMONTH('Faturado mensal'!AE$2,0)) -> 0 | AF4: =SUMIFS(#REF!,#REF!, $A4,#REF!, ">="&'Faturado mensal'!AF$2,#REF!, "<"&EOMONTH('Faturado mensal'!AF$2,0)) -> 0 | AG4: =SUMIFS(#REF!,#REF!, $A4,#REF!, ">="&'Faturado mensal'!AG$2,#REF!, "<"&EOMONTH('Faturado mensal'!AG$2,0)) -> 0 | ... AK4: =SUMIFS(#REF!,#REF!, $A4,#REF!, ">="&'Faturado mensal'!AK$2,#REF!, "<"&EOMONTH('Faturado mensal'!AK$2,0)) -> 0 | AL4: =SUMIFS(#REF!,#REF!, $A4,#REF!, ">="&Z$2,#REF!, "<"&EOMONTH(AK$2,0)) -> 0
A5: CS0000652 | B5: 070001769 | C5: METHODOS LABORATORIO, ANALISES CLIN | D5: Ativo | E5: RECURSOS HUMANOS | F5: SERVIÇOS PRESTADOS | G5: INDUSTRIAL SRS | H5: A | I5: METHODOS LABORATORIO, ANALISES | J5: 30 DIAS | K5: SRSADM | L5: COMPRAS - SRS - ADMINISTRAÇÃO | M5: =SUMIFS(#REF!,#REF!, $A5,#REF!, ">="&'Faturado mensal'!M$2,#REF!, "<"&EOMONTH('Faturado mensal'!M$2,0)) -> 0 | N5: =SUMIFS(#REF!,#REF!, $A5,#REF!, ">="&'Faturado mensal'!N$2,#REF!, "<"&EOMONTH('Faturado mensal'!N$2,0)) -> 241.23 | O5: =SUMIFS(#REF!,#REF!, $A5,#REF!, ">="&'Faturado mensal'!O$2,#REF!, "<"&EOMONTH('Faturado mensal'!O$2,0)) -> 122.56 | P5: =SUMIFS(#REF!,#REF!, $A5,#REF!, ">="&'Faturado mensal'!P$2,#REF!, "<"&EOMONTH('Faturado mensal'!P$2,0)) -> 0 | Q5: =SUMIFS(#REF!,#REF!, $A5,#REF!, ">="&'Faturado mensal'!Q$2,#REF!, "<"&EOMONTH('Faturado mensal'!Q$2,0)) -> 170.08 | R5: =SUMIFS(#REF!,#REF!, $A5,#REF!, ">="&'Faturado mensal'!R$2,#REF!, "<"&EOMONTH('Faturado mensal'!R$2,0)) -> 438.38 | S5: =SUMIFS(#REF!,#REF!, $A5,#REF!, ">="&'Faturado mensal'!S$2,#REF!, "<"&EOMONTH('Faturado mensal'!S$2,0)) -> 155.56 | T5: =SUMIFS(#REF!,#REF!, $A5,#REF!, ">="&'Faturado mensal'!T$2,#REF!, "<"&EOMONTH('Faturado mensal'!T$2,0)) -> 195.27 | ... X5: =SUMIFS(#REF!,#REF!, $A5,#REF!, ">="&'Faturado mensal'!X$2,#REF!, "<"&EOMONTH('Faturado mensal'!X$2,0)) -> 260.44 | Y5: =SUMIFS(#REF!,#REF!, $A5,#REF!, ">="&'Faturado mensal'!M$2,#REF!, "<"&EOMONTH('Faturado mensal'!M$2,12)) -> 2020.12 | Z5: =SUMIFS(#REF!,#REF!, $A5,#REF!, ">="&'Faturado mensal'!Z$2,#REF!, "<"&EOMONTH('Faturado mensal'!Z$2,0)) -> 0 | AA5: =SUMIFS(#REF!,#REF!, $A5,#REF!, ">="&'Faturado mensal'!AA$2,#REF!, "<"&EOMONTH('Faturado mensal'!AA$2,0)) -> 30.64 | AB5: =SUMIFS(#REF!,#REF!, $A5,#REF!, ">="&'Faturado mensal'!AB$2,#REF!, "<"&EOMONTH('Faturado mensal'!AB$2,0)) -> 0 | AC5: =SUMIFS(#REF!,#REF!, $A5,#REF!, ">="&'Faturado mensal'!AC$2,#REF!, "<"&EOMONTH('Faturado mensal'!AC$2,0)) -> 45.96 | AD5: =SUMIFS(#REF!,#REF!, $A5,#REF!, ">="&'Faturado mensal'!AD$2,#REF!, "<"&EOMONTH('Faturado mensal'!AD$2,0)) -> 173.86 | AE5: =SUMIFS(#REF!,#REF!, $A5,#REF!, ">="&'Faturado mensal'!AE$2,#REF!, "<"&EOMONTH('Faturado mensal'!AE$2,0)) -> 108.93 | AF5: =SUMIFS(#REF!,#REF!, $A5,#REF!, ">="&'Faturado mensal'!AF$2,#REF!, "<"&EOMONTH('Faturado mensal'!AF$2,0)) -> 0 | AG5: =SUMIFS(#REF!,#REF!, $A5,#REF!, ">="&'Faturado mensal'!AG$2,#REF!, "<"&EOMONTH('Faturado mensal'!AG$2,0)) -> 0 | ... AK5: =SUMIFS(#REF!,#REF!, $A5,#REF!, ">="&'Faturado mensal'!AK$2,#REF!, "<"&EOMONTH('Faturado mensal'!AK$2,0)) -> 0 | AL5: =SUMIFS(#REF!,#REF!, $A5,#REF!, ">="&Z$2,#REF!, "<"&EOMONTH(AK$2,0)) -> 359.39
A6: CS0000656 | B6: 090095495 | C6: SUL COM DE GAZ E ACESS LTDA ME | D6: Concluído | G6: INDUSTRIAL SRS | H6: B | I6: SUL COM DE GAZ E ACESS LTDA ME | J6: 30 DIAS | K6: SRSFAB | L6: PRGM . COMPRAS - SRS - FABRICA | M6: =SUMIFS(#REF!,#REF!, $A6,#REF!, ">="&'Faturado mensal'!M$2,#REF!, "<"&EOMONTH('Faturado mensal'!M$2,0)) -> 0 | N6: =SUMIFS(#REF!,#REF!, $A6,#REF!, ">="&'Faturado mensal'!N$2,#REF!, "<"&EOMONTH('Faturado mensal'!N$2,0)) -> 0 | O6: =SUMIFS(#REF!,#REF!, $A6,#REF!, ">="&'Faturado mensal'!O$2,#REF!, "<"&EOMONTH('Faturado mensal'!O$2,0)) -> 0 | P6: =SUMIFS(#REF!,#REF!, $A6,#REF!, ">="&'Faturado mensal'!P$2,#REF!, "<"&EOMONTH('Faturado mensal'!P$2,0)) -> 0 | Q6: =SUMIFS(#REF!,#REF!, $A6,#REF!, ">="&'Faturado mensal'!Q$2,#REF!, "<"&EOMONTH('Faturado mensal'!Q$2,0)) -> 0 | R6: =SUMIFS(#REF!,#REF!, $A6,#REF!, ">="&'Faturado mensal'!R$2,#REF!, "<"&EOMONTH('Faturado mensal'!R$2,0)) -> 0 | S6: =SUMIFS(#REF!,#REF!, $A6,#REF!, ">="&'Faturado mensal'!S$2,#REF!, "<"&EOMONTH('Faturado mensal'!S$2,0)) -> 0 | T6: =SUMIFS(#REF!,#REF!, $A6,#REF!, ">="&'Faturado mensal'!T$2,#REF!, "<"&EOMONTH('Faturado mensal'!T$2,0)) -> 0 | ... X6: =SUMIFS(#REF!,#REF!, $A6,#REF!, ">="&'Faturado mensal'!X$2,#REF!, "<"&EOMONTH('Faturado mensal'!X$2,0)) -> 0 | Y6: =SUMIFS(#REF!,#REF!, $A6,#REF!, ">="&'Faturado mensal'!M$2,#REF!, "<"&EOMONTH('Faturado mensal'!M$2,12)) -> 0 | Z6: =SUMIFS(#REF!,#REF!, $A6,#REF!, ">="&'Faturado mensal'!Z$2,#REF!, "<"&EOMONTH('Faturado mensal'!Z$2,0)) -> 0 | AA6: =SUMIFS(#REF!,#REF!, $A6,#REF!, ">="&'Faturado mensal'!AA$2,#REF!, "<"&EOMONTH('Faturado mensal'!AA$2,0)) -> 0 | AB6: =SUMIFS(#REF!,#REF!, $A6,#REF!, ">="&'Faturado mensal'!AB$2,#REF!, "<"&EOMONTH('Faturado mensal'!AB$2,0)) -> 0 | AC6: =SUMIFS(#REF!,#REF!, $A6,#REF!, ">="&'Faturado mensal'!AC$2,#REF!, "<"&EOMONTH('Faturado mensal'!AC$2,0)) -> 0 | AD6: =SUMIFS(#REF!,#REF!, $A6,#REF!, ">="&'Faturado mensal'!AD$2,#REF!, "<"&EOMONTH('Faturado mensal'!AD$2,0)) -> 0 | AE6: =SUMIFS(#REF!,#REF!, $A6,#REF!, ">="&'Faturado mensal'!AE$2,#REF!, "<"&EOMONTH('Faturado mensal'!AE$2,0)) -> 0 | AF6: =SUMIFS(#REF!,#REF!, $A6,#REF!, ">="&'Faturado mensal'!AF$2,#REF!, "<"&EOMONTH('Faturado mensal'!AF$2,0)) -> 0 | AG6: =SUMIFS(#REF!,#REF!, $A6,#REF!, ">="&'Faturado mensal'!AG$2,#REF!, "<"&EOMONTH('Faturado mensal'!AG$2,0)) -> 0 | ... AK6: =SUMIFS(#REF!,#REF!, $A6,#REF!, ">="&'Faturado mensal'!AK$2,#REF!, "<"&EOMONTH('Faturado mensal'!AK$2,0)) -> 0 | AL6: =SUMIFS(#REF!,#REF!, $A6,#REF!, ">="&Z$2,#REF!, "<"&EOMONTH(AK$2,0)) -> 0
A7: CS0000662 | B7: 090000133 | C7: EXTELLPP EQUIP.E EXTINT.LTDA | D7: Ativo | E7: QSMA | F7: SERVIÇOS PRESTADOS | G7: INDUSTRIAL VIES | H7: C | I7: EXTELLPP EQUIP.E EXTINT.LTDA | J7: 15 DIAS | K7: VIESFB | L7: PRGM .COMPRAS - VIES - FABRICA | M7: =SUMIFS(#REF!,#REF!, $A7,#REF!, ">="&'Faturado mensal'!M$2,#REF!, "<"&EOMONTH('Faturado mensal'!M$2,0)) -> 1000 | N7: =SUMIFS(#REF!,#REF!, $A7,#REF!, ">="&'Faturado mensal'!N$2,#REF!, "<"&EOMONTH('Faturado mensal'!N$2,0)) -> 1000 | O7: =SUMIFS(#REF!,#REF!, $A7,#REF!, ">="&'Faturado mensal'!O$2,#REF!, "<"&EOMONTH('Faturado mensal'!O$2,0)) -> 1000 | P7: =SUMIFS(#REF!,#REF!, $A7,#REF!, ">="&'Faturado mensal'!P$2,#REF!, "<"&EOMONTH('Faturado mensal'!P$2,0)) -> 1000 | Q7: =SUMIFS(#REF!,#REF!, $A7,#REF!, ">="&'Faturado mensal'!Q$2,#REF!, "<"&EOMONTH('Faturado mensal'!Q$2,0)) -> 1000 | R7: =SUMIFS(#REF!,#REF!, $A7,#REF!, ">="&'Faturado mensal'!R$2,#REF!, "<"&EOMONTH('Faturado mensal'!R$2,0)) -> 1000 | S7: =SUMIFS(#REF!,#REF!, $A7,#REF!, ">="&'Faturado mensal'!S$2,#REF!, "<"&EOMONTH('Faturado mensal'!S$2,0)) -> 1000 | T7: =SUMIFS(#REF!,#REF!, $A7,#REF!, ">="&'Faturado mensal'!T$2,#REF!, "<"&EOMONTH('Faturado mensal'!T$2,0)) -> 0 | ... X7: =SUMIFS(#REF!,#REF!, $A7,#REF!, ">="&'Faturado mensal'!X$2,#REF!, "<"&EOMONTH('Faturado mensal'!X$2,0)) -> 1000 | Y7: =SUMIFS(#REF!,#REF!, $A7,#REF!, ">="&'Faturado mensal'!M$2,#REF!, "<"&EOMONTH('Faturado mensal'!M$2,12)) -> 13000 | Z7: =SUMIFS(#REF!,#REF!, $A7,#REF!, ">="&'Faturado mensal'!Z$2,#REF!, "<"&EOMONTH('Faturado mensal'!Z$2,0)) -> 1000 | AA7: =SUMIFS(#REF!,#REF!, $A7,#REF!, ">="&'Faturado mensal'!AA$2,#REF!, "<"&EOMONTH('Faturado mensal'!AA$2,0)) -> 1000 | AB7: =SUMIFS(#REF!,#REF!, $A7,#REF!, ">="&'Faturado mensal'!AB$2,#REF!, "<"&EOMONTH('Faturado mensal'!AB$2,0)) -> 1000 | AC7: =SUMIFS(#REF!,#REF!, $A7,#REF!, ">="&'Faturado mensal'!AC$2,#REF!, "<"&EOMONTH('Faturado mensal'!AC$2,0)) -> 1000 | AD7: =SUMIFS(#REF!,#REF!, $A7,#REF!, ">="&'Faturado mensal'!AD$2,#REF!, "<"&EOMONTH('Faturado mensal'!AD$2,0)) -> 0 | AE7: =SUMIFS(#REF!,#REF!, $A7,#REF!, ">="&'Faturado mensal'!AE$2,#REF!, "<"&EOMONTH('Faturado mensal'!AE$2,0)) -> 2000 | AF7: =SUMIFS(#REF!,#REF!, $A7,#REF!, ">="&'Faturado mensal'!AF$2,#REF!, "<"&EOMONTH('Faturado mensal'!AF$2,0)) -> 0 | AG7: =SUMIFS(#REF!,#REF!, $A7,#REF!, ">="&'Faturado mensal'!AG$2,#REF!, "<"&EOMONTH('Faturado mensal'!AG$2,0)) -> 0 | ... AK7: =SUMIFS(#REF!,#REF!, $A7,#REF!, ">="&'Faturado mensal'!AK$2,#REF!, "<"&EOMONTH('Faturado mensal'!AK$2,0)) -> 0 | AL7: =SUMIFS(#REF!,#REF!, $A7,#REF!, ">="&Z$2,#REF!, "<"&EOMONTH(AK$2,0)) -> 6000
A8: CS0000663 | B8: 090005248 | C8: FORCA DELTA INT.CON.ASS.S.LTDA | D8: Concluído | I8: FORCA DELTA INT.CON.ASS.S.LTDA | J8: 30 DIAS | K8: VIESFB | L8: PRGM .COMPRAS - VIES - FABRICA | M8: =SUMIFS(#REF!,#REF!, $A8,#REF!, ">="&'Faturado mensal'!M$2,#REF!, "<"&EOMONTH('Faturado mensal'!M$2,0)) -> 0 | N8: =SUMIFS(#REF!,#REF!, $A8,#REF!, ">="&'Faturado mensal'!N$2,#REF!, "<"&EOMONTH('Faturado mensal'!N$2,0)) -> 0 | O8: =SUMIFS(#REF!,#REF!, $A8,#REF!, ">="&'Faturado mensal'!O$2,#REF!, "<"&EOMONTH('Faturado mensal'!O$2,0)) -> 0 | P8: =SUMIFS(#REF!,#REF!, $A8,#REF!, ">="&'Faturado mensal'!P$2,#REF!, "<"&EOMONTH('Faturado mensal'!P$2,0)) -> 0 | Q8: =SUMIFS(#REF!,#REF!, $A8,#REF!, ">="&'Faturado mensal'!Q$2,#REF!, "<"&EOMONTH('Faturado mensal'!Q$2,0)) -> 0 | R8: =SUMIFS(#REF!,#REF!, $A8,#REF!, ">="&'Faturado mensal'!R$2,#REF!, "<"&EOMONTH('Faturado mensal'!R$2,0)) -> 0 | S8: =SUMIFS(#REF!,#REF!, $A8,#REF!, ">="&'Faturado mensal'!S$2,#REF!, "<"&EOMONTH('Faturado mensal'!S$2,0)) -> 0 | T8: =SUMIFS(#REF!,#REF!, $A8,#REF!, ">="&'Faturado mensal'!T$2,#REF!, "<"&EOMONTH('Faturado mensal'!T$2,0)) -> 0 | ... X8: =SUMIFS(#REF!,#REF!, $A8,#REF!, ">="&'Faturado mensal'!X$2,#REF!, "<"&EOMONTH('Faturado mensal'!X$2,0)) -> 0 | Y8: =SUMIFS(#REF!,#REF!, $A8,#REF!, ">="&'Faturado mensal'!M$2,#REF!, "<"&EOMONTH('Faturado mensal'!M$2,12)) -> 0 | Z8: =SUMIFS(#REF!,#REF!, $A8,#REF!, ">="&'Faturado mensal'!Z$2,#REF!, "<"&EOMONTH('Faturado mensal'!Z$2,0)) -> 0 | AA8: =SUMIFS(#REF!,#REF!, $A8,#REF!, ">="&'Faturado mensal'!AA$2,#REF!, "<"&EOMONTH('Faturado mensal'!AA$2,0)) -> 0 | AB8: =SUMIFS(#REF!,#REF!, $A8,#REF!, ">="&'Faturado mensal'!AB$2,#REF!, "<"&EOMONTH('Faturado mensal'!AB$2,0)) -> 0 | AC8: =SUMIFS(#REF!,#REF!, $A8,#REF!, ">="&'Faturado mensal'!AC$2,#REF!, "<"&EOMONTH('Faturado mensal'!AC$2,0)) -> 0 | AD8: =SUMIFS(#REF!,#REF!, $A8,#REF!, ">="&'Faturado mensal'!AD$2,#REF!, "<"&EOMONTH('Faturado mensal'!AD$2,0)) -> 0 | AE8: =SUMIFS(#REF!,#REF!, $A8,#REF!, ">="&'Faturado mensal'!AE$2,#REF!, "<"&EOMONTH('Faturado mensal'!AE$2,0)) -> 0 | AF8: =SUMIFS(#REF!,#REF!, $A8,#REF!, ">="&'Faturado mensal'!AF$2,#REF!, "<"&EOMONTH('Faturado mensal'!AF$2,0)) -> 0 | AG8: =SUMIFS(#REF!,#REF!, $A8,#REF!, ">="&'Faturado mensal'!AG$2,#REF!, "<"&EOMONTH('Faturado mensal'!AG$2,0)) -> 0 | ... AK8: =SUMIFS(#REF!,#REF!, $A8,#REF!, ">="&'Faturado mensal'!AK$2,#REF!, "<"&EOMONTH('Faturado mensal'!AK$2,0)) -> 0 | AL8: =SUMIFS(#REF!,#REF!, $A8,#REF!, ">="&Z$2,#REF!, "<"&EOMONTH(AK$2,0)) -> 0
A9: CS0000666 | B9: 070075619 | C9: KOLETUS TRANS COLE RESID LTDA | D9: Ativo | E9: QSMA | F9: SERVIÇOS PRESTADOS | G9: INDUSTRIAL VIES | H9: A | I9: KOLETUS TRANS COLE RESID LTDA | J9: 30 DIAS | K9: VIESFB | L9: PRGM .COMPRAS - VIES - FABRICA | M9: =SUMIFS(#REF!,#REF!, $A9,#REF!, ">="&'Faturado mensal'!M$2,#REF!, "<"&EOMONTH('Faturado mensal'!M$2,0)) -> 28530.44 | N9: =SUMIFS(#REF!,#REF!, $A9,#REF!, ">="&'Faturado mensal'!N$2,#REF!, "<"&EOMONTH('Faturado mensal'!N$2,0)) -> 0 | O9: =SUMIFS(#REF!,#REF!, $A9,#REF!, ">="&'Faturado mensal'!O$2,#REF!, "<"&EOMONTH('Faturado mensal'!O$2,0)) -> 50133.85 | P9: =SUMIFS(#REF!,#REF!, $A9,#REF!, ">="&'Faturado mensal'!P$2,#REF!, "<"&EOMONTH('Faturado mensal'!P$2,0)) -> 0 | Q9: =SUMIFS(#REF!,#REF!, $A9,#REF!, ">="&'Faturado mensal'!Q$2,#REF!, "<"&EOMONTH('Faturado mensal'!Q$2,0)) -> 50998.86 | R9: =SUMIFS(#REF!,#REF!, $A9,#REF!, ">="&'Faturado mensal'!R$2,#REF!, "<"&EOMONTH('Faturado mensal'!R$2,0)) -> 0 | S9: =SUMIFS(#REF!,#REF!, $A9,#REF!, ">="&'Faturado mensal'!S$2,#REF!, "<"&EOMONTH('Faturado mensal'!S$2,0)) -> 28535.23 | T9: =SUMIFS(#REF!,#REF!, $A9,#REF!, ">="&'Faturado mensal'!T$2,#REF!, "<"&EOMONTH('Faturado mensal'!T$2,0)) -> 54722.23 | ... X9: =SUMIFS(#REF!,#REF!, $A9,#REF!, ">="&'Faturado mensal'!X$2,#REF!, "<"&EOMONTH('Faturado mensal'!X$2,0)) -> 49878.03 | Y9: =SUMIFS(#REF!,#REF!, $A9,#REF!, ">="&'Faturado mensal'!M$2,#REF!, "<"&EOMONTH('Faturado mensal'!M$2,12)) -> 332211.3 | Z9: =SUMIFS(#REF!,#REF!, $A9,#REF!, ">="&'Faturado mensal'!Z$2,#REF!, "<"&EOMONTH('Faturado mensal'!Z$2,0)) -> 17467.9 | AA9: =SUMIFS(#REF!,#REF!, $A9,#REF!, ">="&'Faturado mensal'!AA$2,#REF!, "<"&EOMONTH('Faturado mensal'!AA$2,0)) -> 20128.94 | AB9: =SUMIFS(#REF!,#REF!, $A9,#REF!, ">="&'Faturado mensal'!AB$2,#REF!, "<"&EOMONTH('Faturado mensal'!AB$2,0)) -> 15777.94 | AC9: =SUMIFS(#REF!,#REF!, $A9,#REF!, ">="&'Faturado mensal'!AC$2,#REF!, "<"&EOMONTH('Faturado mensal'!AC$2,0)) -> 17028.24 | AD9: =SUMIFS(#REF!,#REF!, $A9,#REF!, ">="&'Faturado mensal'!AD$2,#REF!, "<"&EOMONTH('Faturado mensal'!AD$2,0)) -> 16481.86 | AE9: =SUMIFS(#REF!,#REF!, $A9,#REF!, ">="&'Faturado mensal'!AE$2,#REF!, "<"&EOMONTH('Faturado mensal'!AE$2,0)) -> 0 | AF9: =SUMIFS(#REF!,#REF!, $A9,#REF!, ">="&'Faturado mensal'!AF$2,#REF!, "<"&EOMONTH('Faturado mensal'!AF$2,0)) -> 0 | AG9: =SUMIFS(#REF!,#REF!, $A9,#REF!, ">="&'Faturado mensal'!AG$2,#REF!, "<"&EOMONTH('Faturado mensal'!AG$2,0)) -> 0 | ... AK9: =SUMIFS(#REF!,#REF!, $A9,#REF!, ">="&'Faturado mensal'!AK$2,#REF!, "<"&EOMONTH('Faturado mensal'!AK$2,0)) -> 0 | AL9: =SUMIFS(#REF!,#REF!, $A9,#REF!, ">="&Z$2,#REF!, "<"&EOMONTH(AK$2,0)) -> 86884.88
A10: CS0000667 | B10: 070001498 | C10: RENAN V. B. SILVA CONSULTORIA E SER | D10: Ativo | E10: MANUFATURA VIES | F10: TERCEIROS | G10: INDUSTRIAL VIES | H10: C | I10: RENAN V. B. SILVA CONSULTORIA | J10: 30 DIAS | K10: VIESFB | L10: PRGM .COMPRAS - VIES - FABRICA | M10: =SUMIFS(#REF!,#REF!, $A10,#REF!, ">="&'Faturado mensal'!M$2,#REF!, "<"&EOMONTH('Faturado mensal'!M$2,0)) -> 22365 | N10: =SUMIFS(#REF!,#REF!, $A10,#REF!, ">="&'Faturado mensal'!N$2,#REF!, "<"&EOMONTH('Faturado mensal'!N$2,0)) -> 0 | O10: =SUMIFS(#REF!,#REF!, $A10,#REF!, ">="&'Faturado mensal'!O$2,#REF!, "<"&EOMONTH('Faturado mensal'!O$2,0)) -> 3420 | P10: =SUMIFS(#REF!,#REF!, $A10,#REF!, ">="&'Faturado mensal'!P$2,#REF!, "<"&EOMONTH('Faturado mensal'!P$2,0)) -> 0 | Q10: =SUMIFS(#REF!,#REF!, $A10,#REF!, ">="&'Faturado mensal'!Q$2,#REF!, "<"&EOMONTH('Faturado mensal'!Q$2,0)) -> 5200 | R10: =SUMIFS(#REF!,#REF!, $A10,#REF!, ">="&'Faturado mensal'!R$2,#REF!, "<"&EOMONTH('Faturado mensal'!R$2,0)) -> 0 | S10: =SUMIFS(#REF!,#REF!, $A10,#REF!, ">="&'Faturado mensal'!S$2,#REF!, "<"&EOMONTH('Faturado mensal'!S$2,0)) -> 0 | T10: =SUMIFS(#REF!,#REF!, $A10,#REF!, ">="&'Faturado mensal'!T$2,#REF!, "<"&EOMONTH('Faturado mensal'!T$2,0)) -> 5400 | ... X10: =SUMIFS(#REF!,#REF!, $A10,#REF!, ">="&'Faturado mensal'!X$2,#REF!, "<"&EOMONTH('Faturado mensal'!X$2,0)) -> 0 | Y10: =SUMIFS(#REF!,#REF!, $A10,#REF!, ">="&'Faturado mensal'!M$2,#REF!, "<"&EOMONTH('Faturado mensal'!M$2,12)) -> 36385 | Z10: =SUMIFS(#REF!,#REF!, $A10,#REF!, ">="&'Faturado mensal'!Z$2,#REF!, "<"&EOMONTH('Faturado mensal'!Z$2,0)) -> 0 | AA10: =SUMIFS(#REF!,#REF!, $A10,#REF!, ">="&'Faturado mensal'!AA$2,#REF!, "<"&EOMONTH('Faturado mensal'!AA$2,0)) -> 0 | AB10: =SUMIFS(#REF!,#REF!, $A10,#REF!, ">="&'Faturado mensal'!AB$2,#REF!, "<"&EOMONTH('Faturado mensal'!AB$2,0)) -> 800 | AC10: =SUMIFS(#REF!,#REF!, $A10,#REF!, ">="&'Faturado mensal'!AC$2,#REF!, "<"&EOMONTH('Faturado mensal'!AC$2,0)) -> 0 | AD10: =SUMIFS(#REF!,#REF!, $A10,#REF!, ">="&'Faturado mensal'!AD$2,#REF!, "<"&EOMONTH('Faturado mensal'!AD$2,0)) -> 0 | AE10: =SUMIFS(#REF!,#REF!, $A10,#REF!, ">="&'Faturado mensal'!AE$2,#REF!, "<"&EOMONTH('Faturado mensal'!AE$2,0)) -> 0 | AF10: =SUMIFS(#REF!,#REF!, $A10,#REF!, ">="&'Faturado mensal'!AF$2,#REF!, "<"&EOMONTH('Faturado mensal'!AF$2,0)) -> 0 | AG10: =SUMIFS(#REF!,#REF!, $A10,#REF!, ">="&'Faturado mensal'!AG$2,#REF!, "<"&EOMONTH('Faturado mensal'!AG$2,0)) -> 0 | ... AK10: =SUMIFS(#REF!,#REF!, $A10,#REF!, ">="&'Faturado mensal'!AK$2,#REF!, "<"&EOMONTH('Faturado mensal'!AK$2,0)) -> 0 | AL10: =SUMIFS(#REF!,#REF!, $A10,#REF!, ">="&Z$2,#REF!, "<"&EOMONTH(AK$2,0)) -> 800
A11: CS0000669 | B11: 090095563 | C11: AEJ PAULISTA SERVICOS LTDA ME | D11: Concluído | I11: AEJ PAULISTA SERVICOS LTDA ME | J11: 30 DIAS | K11: VIESFB | L11: PRGM .COMPRAS - VIES - FABRICA | M11: =SUMIFS(#REF!,#REF!, $A11,#REF!, ">="&'Faturado mensal'!M$2,#REF!, "<"&EOMONTH('Faturado mensal'!M$2,0)) -> 0 | N11: =SUMIFS(#REF!,#REF!, $A11,#REF!, ">="&'Faturado mensal'!N$2,#REF!, "<"&EOMONTH('Faturado mensal'!N$2,0)) -> 0 | O11: =SUMIFS(#REF!,#REF!, $A11,#REF!, ">="&'Faturado mensal'!O$2,#REF!, "<"&EOMONTH('Faturado mensal'!O$2,0)) -> 0 | P11: =SUMIFS(#REF!,#REF!, $A11,#REF!, ">="&'Faturado mensal'!P$2,#REF!, "<"&EOMONTH('Faturado mensal'!P$2,0)) -> 0 | Q11: =SUMIFS(#REF!,#REF!, $A11,#REF!, ">="&'Faturado mensal'!Q$2,#REF!, "<"&EOMONTH('Faturado mensal'!Q$2,0)) -> 0 | R11: =SUMIFS(#REF!,#REF!, $A11,#REF!, ">="&'Faturado mensal'!R$2,#REF!, "<"&EOMONTH('Faturado mensal'!R$2,0)) -> 0 | S11: =SUMIFS(#REF!,#REF!, $A11,#REF!, ">="&'Faturado mensal'!S$2,#REF!, "<"&EOMONTH('Faturado mensal'!S$2,0)) -> 0 | T11: =SUMIFS(#REF!,#REF!, $A11,#REF!, ">="&'Faturado mensal'!T$2,#REF!, "<"&EOMONTH('Faturado mensal'!T$2,0)) -> 0 | ... X11: =SUMIFS(#REF!,#REF!, $A11,#REF!, ">="&'Faturado mensal'!X$2,#REF!, "<"&EOMONTH('Faturado mensal'!X$2,0)) -> 0 | Y11: =SUMIFS(#REF!,#REF!, $A11,#REF!, ">="&'Faturado mensal'!M$2,#REF!, "<"&EOMONTH('Faturado mensal'!M$2,12)) -> 0 | Z11: =SUMIFS(#REF!,#REF!, $A11,#REF!, ">="&'Faturado mensal'!Z$2,#REF!, "<"&EOMONTH('Faturado mensal'!Z$2,0)) -> 0 | AA11: =SUMIFS(#REF!,#REF!, $A11,#REF!, ">="&'Faturado mensal'!AA$2,#REF!, "<"&EOMONTH('Faturado mensal'!AA$2,0)) -> 0 | AB11: =SUMIFS(#REF!,#REF!, $A11,#REF!, ">="&'Faturado mensal'!AB$2,#REF!, "<"&EOMONTH('Faturado mensal'!AB$2,0)) -> 0 | AC11: =SUMIFS(#REF!,#REF!, $A11,#REF!, ">="&'Faturado mensal'!AC$2,#REF!, "<"&EOMONTH('Faturado mensal'!AC$2,0)) -> 0 | AD11: =SUMIFS(#REF!,#REF!, $A11,#REF!, ">="&'Faturado mensal'!AD$2,#REF!, "<"&EOMONTH('Faturado mensal'!AD$2,0)) -> 0 | AE11: =SUMIFS(#REF!,#REF!, $A11,#REF!, ">="&'Faturado mensal'!AE$2,#REF!, "<"&EOMONTH('Faturado mensal'!AE$2,0)) -> 0 | AF11: =SUMIFS(#REF!,#REF!, $A11,#REF!, ">="&'Faturado mensal'!AF$2,#REF!, "<"&EOMONTH('Faturado mensal'!AF$2,0)) -> 0 | AG11: =SUMIFS(#REF!,#REF!, $A11,#REF!, ">="&'Faturado mensal'!AG$2,#REF!, "<"&EOMONTH('Faturado mensal'!AG$2,0)) -> 0 | ... AK11: =SUMIFS(#REF!,#REF!, $A11,#REF!, ">="&'Faturado mensal'!AK$2,#REF!, "<"&EOMONTH('Faturado mensal'!AK$2,0)) -> 0 | AL11: =SUMIFS(#REF!,#REF!, $A11,#REF!, ">="&Z$2,#REF!, "<"&EOMONTH(AK$2,0)) -> 0
A12: CS0000676 | B12: 070065548 | C12: TUV SUD SFDK LABORATORIO DE ANALISE | D12: Ativo | E12: QSMA | F12: SERVIÇOS PRESTADOS | G12: INDUSTRIAL SRS | H12: B | I12: TUV SUD SFDK LABORATORIO DE AN | J12: 30 DIAS | K12: SRSFAB | L12: PRGM . COMPRAS - SRS - FABRICA | M12: =SUMIFS(#REF!,#REF!, $A12,#REF!, ">="&'Faturado mensal'!M$2,#REF!, "<"&EOMONTH('Faturado mensal'!M$2,0)) -> 0 | N12: =SUMIFS(#REF!,#REF!, $A12,#REF!, ">="&'Faturado mensal'!N$2,#REF!, "<"&EOMONTH('Faturado mensal'!N$2,0)) -> 0 | O12: =SUMIFS(#REF!,#REF!, $A12,#REF!, ">="&'Faturado mensal'!O$2,#REF!, "<"&EOMONTH('Faturado mensal'!O$2,0)) -> 0 | P12: =SUMIFS(#REF!,#REF!, $A12,#REF!, ">="&'Faturado mensal'!P$2,#REF!, "<"&EOMONTH('Faturado mensal'!P$2,0)) -> 0 | Q12: =SUMIFS(#REF!,#REF!, $A12,#REF!, ">="&'Faturado mensal'!Q$2,#REF!, "<"&EOMONTH('Faturado mensal'!Q$2,0)) -> 0 | R12: =SUMIFS(#REF!,#REF!, $A12,#REF!, ">="&'Faturado mensal'!R$2,#REF!, "<"&EOMONTH('Faturado mensal'!R$2,0)) -> 0 | S12: =SUMIFS(#REF!,#REF!, $A12,#REF!, ">="&'Faturado mensal'!S$2,#REF!, "<"&EOMONTH('Faturado mensal'!S$2,0)) -> 0 | T12: =SUMIFS(#REF!,#REF!, $A12,#REF!, ">="&'Faturado mensal'!T$2,#REF!, "<"&EOMONTH('Faturado mensal'!T$2,0)) -> 0 | ... X12: =SUMIFS(#REF!,#REF!, $A12,#REF!, ">="&'Faturado mensal'!X$2,#REF!, "<"&EOMONTH('Faturado mensal'!X$2,0)) -> 0 | Y12: =SUMIFS(#REF!,#REF!, $A12,#REF!, ">="&'Faturado mensal'!M$2,#REF!, "<"&EOMONTH('Faturado mensal'!M$2,12)) -> 20128.7 | Z12: =SUMIFS(#REF!,#REF!, $A12,#REF!, ">="&'Faturado mensal'!Z$2,#REF!, "<"&EOMONTH('Faturado mensal'!Z$2,0)) -> 1250.01 | AA12: =SUMIFS(#REF!,#REF!, $A12,#REF!, ">="&'Faturado mensal'!AA$2,#REF!, "<"&EOMONTH('Faturado mensal'!AA$2,0)) -> 0 | AB12: =SUMIFS(#REF!,#REF!, $A12,#REF!, ">="&'Faturado mensal'!AB$2,#REF!, "<"&EOMONTH('Faturado mensal'!AB$2,0)) -> 0 | AC12: =SUMIFS(#REF!,#REF!, $A12,#REF!, ">="&'Faturado mensal'!AC$2,#REF!, "<"&EOMONTH('Faturado mensal'!AC$2,0)) -> 0 | AD12: =SUMIFS(#REF!,#REF!, $A12,#REF!, ">="&'Faturado mensal'!AD$2,#REF!, "<"&EOMONTH('Faturado mensal'!AD$2,0)) -> 0 | AE12: =SUMIFS(#REF!,#REF!, $A12,#REF!, ">="&'Faturado mensal'!AE$2,#REF!, "<"&EOMONTH('Faturado mensal'!AE$2,0)) -> 0 | AF12: =SUMIFS(#REF!,#REF!, $A12,#REF!, ">="&'Faturado mensal'!AF$2,#REF!, "<"&EOMONTH('Faturado mensal'!AF$2,0)) -> 0 | AG12: =SUMIFS(#REF!,#REF!, $A12,#REF!, ">="&'Faturado mensal'!AG$2,#REF!, "<"&EOMONTH('Faturado mensal'!AG$2,0)) -> 0 | ... AK12: =SUMIFS(#REF!,#REF!, $A12,#REF!, ">="&'Faturado mensal'!AK$2,#REF!, "<"&EOMONTH('Faturado mensal'!AK$2,0)) -> 0 | AL12: =SUMIFS(#REF!,#REF!, $A12,#REF!, ">="&Z$2,#REF!, "<"&EOMONTH(AK$2,0)) -> 1250.01
A13: CS0000677 | B13: 070001699 | C13: WELLIMAR GONCALVES DE MEIRA 7296884 | D13: Concluído | I13: WELLIMAR GONCALVES DE MEIRA 72 | J13: 30 DIAS | K13: SRSFAB | L13: PRGM . COMPRAS - SRS - FABRICA | M13: =SUMIFS(#REF!,#REF!, $A13,#REF!, ">="&'Faturado mensal'!M$2,#REF!, "<"&EOMONTH('Faturado mensal'!M$2,0)) -> 0 | N13: =SUMIFS(#REF!,#REF!, $A13,#REF!, ">="&'Faturado mensal'!N$2,#REF!, "<"&EOMONTH('Faturado mensal'!N$2,0)) -> 0 | O13: =SUMIFS(#REF!,#REF!, $A13,#REF!, ">="&'Faturado mensal'!O$2,#REF!, "<"&EOMONTH('Faturado mensal'!O$2,0)) -> 0 | P13: =SUMIFS(#REF!,#REF!, $A13,#REF!, ">="&'Faturado mensal'!P$2,#REF!, "<"&EOMONTH('Faturado mensal'!P$2,0)) -> 0 | Q13: =SUMIFS(#REF!,#REF!, $A13,#REF!, ">="&'Faturado mensal'!Q$2,#REF!, "<"&EOMONTH('Faturado mensal'!Q$2,0)) -> 0 | R13: =SUMIFS(#REF!,#REF!, $A13,#REF!, ">="&'Faturado mensal'!R$2,#REF!, "<"&EOMONTH('Faturado mensal'!R$2,0)) -> 0 | S13: =SUMIFS(#REF!,#REF!, $A13,#REF!, ">="&'Faturado mensal'!S$2,#REF!, "<"&EOMONTH('Faturado mensal'!S$2,0)) -> 0 | T13: =SUMIFS(#REF!,#REF!, $A13,#REF!, ">="&'Faturado mensal'!T$2,#REF!, "<"&EOMONTH('Faturado mensal'!T$2,0)) -> 0 | ... X13: =SUMIFS(#REF!,#REF!, $A13,#REF!, ">="&'Faturado mensal'!X$2,#REF!, "<"&EOMONTH('Faturado mensal'!X$2,0)) -> 0 | Y13: =SUMIFS(#REF!,#REF!, $A13,#REF!, ">="&'Faturado mensal'!M$2,#REF!, "<"&EOMONTH('Faturado mensal'!M$2,12)) -> 0 | Z13: =SUMIFS(#REF!,#REF!, $A13,#REF!, ">="&'Faturado mensal'!Z$2,#REF!, "<"&EOMONTH('Faturado mensal'!Z$2,0)) -> 0 | AA13: =SUMIFS(#REF!,#REF!, $A13,#REF!, ">="&'Faturado mensal'!AA$2,#REF!, "<"&EOMONTH('Faturado mensal'!AA$2,0)) -> 0 | AB13: =SUMIFS(#REF!,#REF!, $A13,#REF!, ">="&'Faturado mensal'!AB$2,#REF!, "<"&EOMONTH('Faturado mensal'!AB$2,0)) -> 0 | AC13: =SUMIFS(#REF!,#REF!, $A13,#REF!, ">="&'Faturado mensal'!AC$2,#REF!, "<"&EOMONTH('Faturado mensal'!AC$2,0)) -> 0 | AD13: =SUMIFS(#REF!,#REF!, $A13,#REF!, ">="&'Faturado mensal'!AD$2,#REF!, "<"&EOMONTH('Faturado mensal'!AD$2,0)) -> 0 | AE13: =SUMIFS(#REF!,#REF!, $A13,#REF!, ">="&'Faturado mensal'!AE$2,#REF!, "<"&EOMONTH('Faturado mensal'!AE$2,0)) -> 0 | AF13: =SUMIFS(#REF!,#REF!, $A13,#REF!, ">="&'Faturado mensal'!AF$2,#REF!, "<"&EOMONTH('Faturado mensal'!AF$2,0)) -> 0 | AG13: =SUMIFS(#REF!,#REF!, $A13,#REF!, ">="&'Faturado mensal'!AG$2,#REF!, "<"&EOMONTH('Faturado mensal'!AG$2,0)) -> 0 | ... AK13: =SUMIFS(#REF!,#REF!, $A13,#REF!, ">="&'Faturado mensal'!AK$2,#REF!, "<"&EOMONTH('Faturado mensal'!AK$2,0)) -> 0 | AL13: =SUMIFS(#REF!,#REF!, $A13,#REF!, ">="&Z$2,#REF!, "<"&EOMONTH(AK$2,0)) -> 0
A14: CS0000678 | B14: 070001703 | C14: SERI.E DESIGN LTDA. | D14: Concluído | G14: INDUSTRIAL SRS | H14: B | I14: SERI.E DESIGN LTDA. | J14: 30 DIAS | K14: SRSFAB | L14: PRGM . COMPRAS - SRS - FABRICA | M14: =SUMIFS(#REF!,#REF!, $A14,#REF!, ">="&'Faturado mensal'!M$2,#REF!, "<"&EOMONTH('Faturado mensal'!M$2,0)) -> 0 | N14: =SUMIFS(#REF!,#REF!, $A14,#REF!, ">="&'Faturado mensal'!N$2,#REF!, "<"&EOMONTH('Faturado mensal'!N$2,0)) -> 0 | O14: =SUMIFS(#REF!,#REF!, $A14,#REF!, ">="&'Faturado mensal'!O$2,#REF!, "<"&EOMONTH('Faturado mensal'!O$2,0)) -> 0 | P14: =SUMIFS(#REF!,#REF!, $A14,#REF!, ">="&'Faturado mensal'!P$2,#REF!, "<"&EOMONTH('Faturado mensal'!P$2,0)) -> 0 | Q14: =SUMIFS(#REF!,#REF!, $A14,#REF!, ">="&'Faturado mensal'!Q$2,#REF!, "<"&EOMONTH('Faturado mensal'!Q$2,0)) -> 0 | R14: =SUMIFS(#REF!,#REF!, $A14,#REF!, ">="&'Faturado mensal'!R$2,#REF!, "<"&EOMONTH('Faturado mensal'!R$2,0)) -> 0 | S14: =SUMIFS(#REF!,#REF!, $A14,#REF!, ">="&'Faturado mensal'!S$2,#REF!, "<"&EOMONTH('Faturado mensal'!S$2,0)) -> 0 | T14: =SUMIFS(#REF!,#REF!, $A14,#REF!, ">="&'Faturado mensal'!T$2,#REF!, "<"&EOMONTH('Faturado mensal'!T$2,0)) -> 0 | ... X14: =SUMIFS(#REF!,#REF!, $A14,#REF!, ">="&'Faturado mensal'!X$2,#REF!, "<"&EOMONTH('Faturado mensal'!X$2,0)) -> 0 | Y14: =SUMIFS(#REF!,#REF!, $A14,#REF!, ">="&'Faturado mensal'!M$2,#REF!, "<"&EOMONTH('Faturado mensal'!M$2,12)) -> 0 | Z14: =SUMIFS(#REF!,#REF!, $A14,#REF!, ">="&'Faturado mensal'!Z$2,#REF!, "<"&EOMONTH('Faturado mensal'!Z$2,0)) -> 0 | AA14: =SUMIFS(#REF!,#REF!, $A14,#REF!, ">="&'Faturado mensal'!AA$2,#REF!, "<"&EOMONTH('Faturado mensal'!AA$2,0)) -> 0 | AB14: =SUMIFS(#REF!,#REF!, $A14,#REF!, ">="&'Faturado mensal'!AB$2,#REF!, "<"&EOMONTH('Faturado mensal'!AB$2,0)) -> 0 | AC14: =SUMIFS(#REF!,#REF!, $A14,#REF!, ">="&'Faturado mensal'!AC$2,#REF!, "<"&EOMONTH('Faturado mensal'!AC$2,0)) -> 0 | AD14: =SUMIFS(#REF!,#REF!, $A14,#REF!, ">="&'Faturado mensal'!AD$2,#REF!, "<"&EOMONTH('Faturado mensal'!AD$2,0)) -> 0 | AE14: =SUMIFS(#REF!,#REF!, $A14,#REF!, ">="&'Faturado mensal'!AE$2,#REF!, "<"&EOMONTH('Faturado mensal'!AE$2,0)) -> 0 | AF14: =SUMIFS(#REF!,#REF!, $A14,#REF!, ">="&'Faturado mensal'!AF$2,#REF!, "<"&EOMONTH('Faturado mensal'!AF$2,0)) -> 0 | AG14: =SUMIFS(#REF!,#REF!, $A14,#REF!, ">="&'Faturado mensal'!AG$2,#REF!, "<"&EOMONTH('Faturado mensal'!AG$2,0)) -> 0 | ... AK14: =SUMIFS(#REF!,#REF!, $A14,#REF!, ">="&'Faturado mensal'!AK$2,#REF!, "<"&EOMONTH('Faturado mensal'!AK$2,0)) -> 0 | AL14: =SUMIFS(#REF!,#REF!, $A14,#REF!, ">="&Z$2,#REF!, "<"&EOMONTH(AK$2,0)) -> 0
A15: CS0000681 | B15: 070000685 | C15: AMPRO LABOR. E ENGa. S/C LTDA | D15: Ativo | E15: QSMA | F15: SERVIÇOS PRESTADOS | G15: INDUSTRIAL SRS | H15: B | I15: AMPRO LABOR. E ENGa. S/C LTDA | J15: 30 DIAS | K15: SRSFAB | L15: PRGM . COMPRAS - SRS - FABRICA | M15: =SUMIFS(#REF!,#REF!, $A15,#REF!, ">="&'Faturado mensal'!M$2,#REF!, "<"&EOMONTH('Faturado mensal'!M$2,0)) -> 0 | N15: =SUMIFS(#REF!,#REF!, $A15,#REF!, ">="&'Faturado mensal'!N$2,#REF!, "<"&EOMONTH('Faturado mensal'!N$2,0)) -> 0 | O15: =SUMIFS(#REF!,#REF!, $A15,#REF!, ">="&'Faturado mensal'!O$2,#REF!, "<"&EOMONTH('Faturado mensal'!O$2,0)) -> 1261 | P15: =SUMIFS(#REF!,#REF!, $A15,#REF!, ">="&'Faturado mensal'!P$2,#REF!, "<"&EOMONTH('Faturado mensal'!P$2,0)) -> 0 | Q15: =SUMIFS(#REF!,#REF!, $A15,#REF!, ">="&'Faturado mensal'!Q$2,#REF!, "<"&EOMONTH('Faturado mensal'!Q$2,0)) -> 0 | R15: =SUMIFS(#REF!,#REF!, $A15,#REF!, ">="&'Faturado mensal'!R$2,#REF!, "<"&EOMONTH('Faturado mensal'!R$2,0)) -> 1261 | S15: =SUMIFS(#REF!,#REF!, $A15,#REF!, ">="&'Faturado mensal'!S$2,#REF!, "<"&EOMONTH('Faturado mensal'!S$2,0)) -> 0 | T15: =SUMIFS(#REF!,#REF!, $A15,#REF!, ">="&'Faturado mensal'!T$2,#REF!, "<"&EOMONTH('Faturado mensal'!T$2,0)) -> 756 | ... X15: =SUMIFS(#REF!,#REF!, $A15,#REF!, ">="&'Faturado mensal'!X$2,#REF!, "<"&EOMONTH('Faturado mensal'!X$2,0)) -> 1305 | Y15: =SUMIFS(#REF!,#REF!, $A15,#REF!, ">="&'Faturado mensal'!M$2,#REF!, "<"&EOMONTH('Faturado mensal'!M$2,12)) -> 6148 | Z15: =SUMIFS(#REF!,#REF!, $A15,#REF!, ">="&'Faturado mensal'!Z$2,#REF!, "<"&EOMONTH('Faturado mensal'!Z$2,0)) -> 0 | AA15: =SUMIFS(#REF!,#REF!, $A15,#REF!, ">="&'Faturado mensal'!AA$2,#REF!, "<"&EOMONTH('Faturado mensal'!AA$2,0)) -> 0 | AB15: =SUMIFS(#REF!,#REF!, $A15,#REF!, ">="&'Faturado mensal'!AB$2,#REF!, "<"&EOMONTH('Faturado mensal'!AB$2,0)) -> 1305 | AC15: =SUMIFS(#REF!,#REF!, $A15,#REF!, ">="&'Faturado mensal'!AC$2,#REF!, "<"&EOMONTH('Faturado mensal'!AC$2,0)) -> 0 | AD15: =SUMIFS(#REF!,#REF!, $A15,#REF!, ">="&'Faturado mensal'!AD$2,#REF!, "<"&EOMONTH('Faturado mensal'!AD$2,0)) -> 0 | AE15: =SUMIFS(#REF!,#REF!, $A15,#REF!, ">="&'Faturado mensal'!AE$2,#REF!, "<"&EOMONTH('Faturado mensal'!AE$2,0)) -> 1305 | AF15: =SUMIFS(#REF!,#REF!, $A15,#REF!, ">="&'Faturado mensal'!AF$2,#REF!, "<"&EOMONTH('Faturado mensal'!AF$2,0)) -> 0 | AG15: =SUMIFS(#REF!,#REF!, $A15,#REF!, ">="&'Faturado mensal'!AG$2,#REF!, "<"&EOMONTH('Faturado mensal'!AG$2,0)) -> 0 | ... AK15: =SUMIFS(#REF!,#REF!, $A15,#REF!, ">="&'Faturado mensal'!AK$2,#REF!, "<"&EOMONTH('Faturado mensal'!AK$2,0)) -> 0 | AL15: =SUMIFS(#REF!,#REF!, $A15,#REF!, ">="&Z$2,#REF!, "<"&EOMONTH(AK$2,0)) -> 2610
A16: CS0000682 | B16: 090010126 | C16: H M CONSULTORIA LTDA | D16: Concluído | I16: H M CONSULTORIA LTDA | J16: 30 DIAS | K16: SRSFAB | L16: PRGM . COMPRAS - SRS - FABRICA | M16: =SUMIFS(#REF!,#REF!, $A16,#REF!, ">="&'Faturado mensal'!M$2,#REF!, "<"&EOMONTH('Faturado mensal'!M$2,0)) -> 0 | N16: =SUMIFS(#REF!,#REF!, $A16,#REF!, ">="&'Faturado mensal'!N$2,#REF!, "<"&EOMONTH('Faturado mensal'!N$2,0)) -> 0 | O16: =SUMIFS(#REF!,#REF!, $A16,#REF!, ">="&'Faturado mensal'!O$2,#REF!, "<"&EOMONTH('Faturado mensal'!O$2,0)) -> 0 | P16: =SUMIFS(#REF!,#REF!, $A16,#REF!, ">="&'Faturado mensal'!P$2,#REF!, "<"&EOMONTH('Faturado mensal'!P$2,0)) -> 0 | Q16: =SUMIFS(#REF!,#REF!, $A16,#REF!, ">="&'Faturado mensal'!Q$2,#REF!, "<"&EOMONTH('Faturado mensal'!Q$2,0)) -> 0 | R16: =SUMIFS(#REF!,#REF!, $A16,#REF!, ">="&'Faturado mensal'!R$2,#REF!, "<"&EOMONTH('Faturado mensal'!R$2,0)) -> 0 | S16: =SUMIFS(#REF!,#REF!, $A16,#REF!, ">="&'Faturado mensal'!S$2,#REF!, "<"&EOMONTH('Faturado mensal'!S$2,0)) -> 0 | T16: =SUMIFS(#REF!,#REF!, $A16,#REF!, ">="&'Faturado mensal'!T$2,#REF!, "<"&EOMONTH('Faturado mensal'!T$2,0)) -> 0 | ... X16: =SUMIFS(#REF!,#REF!, $A16,#REF!, ">="&'Faturado mensal'!X$2,#REF!, "<"&EOMONTH('Faturado mensal'!X$2,0)) -> 0 | Y16: =SUMIFS(#REF!,#REF!, $A16,#REF!, ">="&'Faturado mensal'!M$2,#REF!, "<"&EOMONTH('Faturado mensal'!M$2,12)) -> 0 | Z16: =SUMIFS(#REF!,#REF!, $A16,#REF!, ">="&'Faturado mensal'!Z$2,#REF!, "<"&EOMONTH('Faturado mensal'!Z$2,0)) -> 0 | AA16: =SUMIFS(#REF!,#REF!, $A16,#REF!, ">="&'Faturado mensal'!AA$2,#REF!, "<"&EOMONTH('Faturado mensal'!AA$2,0)) -> 0 | AB16: =SUMIFS(#REF!,#REF!, $A16,#REF!, ">="&'Faturado mensal'!AB$2,#REF!, "<"&EOMONTH('Faturado mensal'!AB$2,0)) -> 0 | AC16: =SUMIFS(#REF!,#REF!, $A16,#REF!, ">="&'Faturado mensal'!AC$2,#REF!, "<"&EOMONTH('Faturado mensal'!AC$2,0)) -> 0 | AD16: =SUMIFS(#REF!,#REF!, $A16,#REF!, ">="&'Faturado mensal'!AD$2,#REF!, "<"&EOMONTH('Faturado mensal'!AD$2,0)) -> 0 | AE16: =SUMIFS(#REF!,#REF!, $A16,#REF!, ">="&'Faturado mensal'!AE$2,#REF!, "<"&EOMONTH('Faturado mensal'!AE$2,0)) -> 0 | AF16: =SUMIFS(#REF!,#REF!, $A16,#REF!, ">="&'Faturado mensal'!AF$2,#REF!, "<"&EOMONTH('Faturado mensal'!AF$2,0)) -> 0 | AG16: =SUMIFS(#REF!,#REF!, $A16,#REF!, ">="&'Faturado mensal'!AG$2,#REF!, "<"&EOMONTH('Faturado mensal'!AG$2,0)) -> 0 | ... AK16: =SUMIFS(#REF!,#REF!, $A16,#REF!, ">="&'Faturado mensal'!AK$2,#REF!, "<"&EOMONTH('Faturado mensal'!AK$2,0)) -> 0 | AL16: =SUMIFS(#REF!,#REF!, $A16,#REF!, ">="&Z$2,#REF!, "<"&EOMONTH(AK$2,0)) -> 0
A17: CS0000683 | B17: 070076376 | C17: PAULO YOCHIKASU UEMATSU | D17: Concluído | G17: INDUSTRIAL SRS | H17: Indef | I17: PAULO YOCHIKASU UEMATSU | J17: 30 DIAS | K17: SRSFAB | L17: PRGM . COMPRAS - SRS - FABRICA | M17: =SUMIFS(#REF!,#REF!, $A17,#REF!, ">="&'Faturado mensal'!M$2,#REF!, "<"&EOMONTH('Faturado mensal'!M$2,0)) -> 0 | N17: =SUMIFS(#REF!,#REF!, $A17,#REF!, ">="&'Faturado mensal'!N$2,#REF!, "<"&EOMONTH('Faturado mensal'!N$2,0)) -> 0 | O17: =SUMIFS(#REF!,#REF!, $A17,#REF!, ">="&'Faturado mensal'!O$2,#REF!, "<"&EOMONTH('Faturado mensal'!O$2,0)) -> 0 | P17: =SUMIFS(#REF!,#REF!, $A17,#REF!, ">="&'Faturado mensal'!P$2,#REF!, "<"&EOMONTH('Faturado mensal'!P$2,0)) -> 0 | Q17: =SUMIFS(#REF!,#REF!, $A17,#REF!, ">="&'Faturado mensal'!Q$2,#REF!, "<"&EOMONTH('Faturado mensal'!Q$2,0)) -> 0 | R17: =SUMIFS(#REF!,#REF!, $A17,#REF!, ">="&'Faturado mensal'!R$2,#REF!, "<"&EOMONTH('Faturado mensal'!R$2,0)) -> 0 | S17: =SUMIFS(#REF!,#REF!, $A17,#REF!, ">="&'Faturado mensal'!S$2,#REF!, "<"&EOMONTH('Faturado mensal'!S$2,0)) -> 0 | T17: =SUMIFS(#REF!,#REF!, $A17,#REF!, ">="&'Faturado mensal'!T$2,#REF!, "<"&EOMONTH('Faturado mensal'!T$2,0)) -> 0 | ... X17: =SUMIFS(#REF!,#REF!, $A17,#REF!, ">="&'Faturado mensal'!X$2,#REF!, "<"&EOMONTH('Faturado mensal'!X$2,0)) -> 0 | Y17: =SUMIFS(#REF!,#REF!, $A17,#REF!, ">="&'Faturado mensal'!M$2,#REF!, "<"&EOMONTH('Faturado mensal'!M$2,12)) -> 0 | Z17: =SUMIFS(#REF!,#REF!, $A17,#REF!, ">="&'Faturado mensal'!Z$2,#REF!, "<"&EOMONTH('Faturado mensal'!Z$2,0)) -> 0 | AA17: =SUMIFS(#REF!,#REF!, $A17,#REF!, ">="&'Faturado mensal'!AA$2,#REF!, "<"&EOMONTH('Faturado mensal'!AA$2,0)) -> 0 | AB17: =SUMIFS(#REF!,#REF!, $A17,#REF!, ">="&'Faturado mensal'!AB$2,#REF!, "<"&EOMONTH('Faturado mensal'!AB$2,0)) -> 0 | AC17: =SUMIFS(#REF!,#REF!, $A17,#REF!, ">="&'Faturado mensal'!AC$2,#REF!, "<"&EOMONTH('Faturado mensal'!AC$2,0)) -> 0 | AD17: =SUMIFS(#REF!,#REF!, $A17,#REF!, ">="&'Faturado mensal'!AD$2,#REF!, "<"&EOMONTH('Faturado mensal'!AD$2,0)) -> 0 | AE17: =SUMIFS(#REF!,#REF!, $A17,#REF!, ">="&'Faturado mensal'!AE$2,#REF!, "<"&EOMONTH('Faturado mensal'!AE$2,0)) -> 0 | AF17: =SUMIFS(#REF!,#REF!, $A17,#REF!, ">="&'Faturado mensal'!AF$2,#REF!, "<"&EOMONTH('Faturado mensal'!AF$2,0)) -> 0 | AG17: =SUMIFS(#REF!,#REF!, $A17,#REF!, ">="&'Faturado mensal'!AG$2,#REF!, "<"&EOMONTH('Faturado mensal'!AG$2,0)) -> 0 | ... AK17: =SUMIFS(#REF!,#REF!, $A17,#REF!, ">="&'Faturado mensal'!AK$2,#REF!, "<"&EOMONTH('Faturado mensal'!AK$2,0)) -> 0 | AL17: =SUMIFS(#REF!,#REF!, $A17,#REF!, ">="&Z$2,#REF!, "<"&EOMONTH(AK$2,0)) -> 0
A18: CS0000685 | B18: 070075837 | C18: GS CONTROLE V. P. URBANAS LTDA | D18: Concluído | E18: QSMA | F18: MANUTENÇÃO EDIFÍCIOS / INSTALAÇÕES | G18: INDUSTRIAL VIES | H18: B | I18: GS CONTROLE V. P. URBANAS LTDA | J18: 30 DIAS | K18: VIESFB | L18: PRGM .COMPRAS - VIES - FABRICA | M18: =SUMIFS(#REF!,#REF!, $A18,#REF!, ">="&'Faturado mensal'!M$2,#REF!, "<"&EOMONTH('Faturado mensal'!M$2,0)) -> 0 | N18: =SUMIFS(#REF!,#REF!, $A18,#REF!, ">="&'Faturado mensal'!N$2,#REF!, "<"&EOMONTH('Faturado mensal'!N$2,0)) -> 0 | O18: =SUMIFS(#REF!,#REF!, $A18,#REF!, ">="&'Faturado mensal'!O$2,#REF!, "<"&EOMONTH('Faturado mensal'!O$2,0)) -> 0 | P18: =SUMIFS(#REF!,#REF!, $A18,#REF!, ">="&'Faturado mensal'!P$2,#REF!, "<"&EOMONTH('Faturado mensal'!P$2,0)) -> 0 | Q18: =SUMIFS(#REF!,#REF!, $A18,#REF!, ">="&'Faturado mensal'!Q$2,#REF!, "<"&EOMONTH('Faturado mensal'!Q$2,0)) -> 0 | R18: =SUMIFS(#REF!,#REF!, $A18,#REF!, ">="&'Faturado mensal'!R$2,#REF!, "<"&EOMONTH('Faturado mensal'!R$2,0)) -> 0 | S18: =SUMIFS(#REF!,#REF!, $A18,#REF!, ">="&'Faturado mensal'!S$2,#REF!, "<"&EOMONTH('Faturado mensal'!S$2,0)) -> 0 | T18: =SUMIFS(#REF!,#REF!, $A18,#REF!, ">="&'Faturado mensal'!T$2,#REF!, "<"&EOMONTH('Faturado mensal'!T$2,0)) -> 0 | ... X18: =SUMIFS(#REF!,#REF!, $A18,#REF!, ">="&'Faturado mensal'!X$2,#REF!, "<"&EOMONTH('Faturado mensal'!X$2,0)) -> 0 | Y18: =SUMIFS(#REF!,#REF!, $A18,#REF!, ">="&'Faturado mensal'!M$2,#REF!, "<"&EOMONTH('Faturado mensal'!M$2,12)) -> 0 | Z18: =SUMIFS(#REF!,#REF!, $A18,#REF!, ">="&'Faturado mensal'!Z$2,#REF!, "<"&EOMONTH('Faturado mensal'!Z$2,0)) -> 0 | AA18: =SUMIFS(#REF!,#REF!, $A18,#REF!, ">="&'Faturado mensal'!AA$2,#REF!, "<"&EOMONTH('Faturado mensal'!AA$2,0)) -> 0 | AB18: =SUMIFS(#REF!,#REF!, $A18,#REF!, ">="&'Faturado mensal'!AB$2,#REF!, "<"&EOMONTH('Faturado mensal'!AB$2,0)) -> 0 | AC18: =SUMIFS(#REF!,#REF!, $A18,#REF!, ">="&'Faturado mensal'!AC$2,#REF!, "<"&EOMONTH('Faturado mensal'!AC$2,0)) -> 0 | AD18: =SUMIFS(#REF!,#REF!, $A18,#REF!, ">="&'Faturado mensal'!AD$2,#REF!, "<"&EOMONTH('Faturado mensal'!AD$2,0)) -> 0 | AE18: =SUMIFS(#REF!,#REF!, $A18,#REF!, ">="&'Faturado mensal'!AE$2,#REF!, "<"&EOMONTH('Faturado mensal'!AE$2,0)) -> 0 | AF18: =SUMIFS(#REF!,#REF!, $A18,#REF!, ">="&'Faturado mensal'!AF$2,#REF!, "<"&EOMONTH('Faturado mensal'!AF$2,0)) -> 0 | AG18: =SUMIFS(#REF!,#REF!, $A18,#REF!, ">="&'Faturado mensal'!AG$2,#REF!, "<"&EOMONTH('Faturado mensal'!AG$2,0)) -> 0 | ... AK18: =SUMIFS(#REF!,#REF!, $A18,#REF!, ">="&'Faturado mensal'!AK$2,#REF!, "<"&EOMONTH('Faturado mensal'!AK$2,0)) -> 0 | AL18: =SUMIFS(#REF!,#REF!, $A18,#REF!, ">="&Z$2,#REF!, "<"&EOMONTH(AK$2,0)) -> 0
A19: CS0000686 | B19: 070075837 | C19: GS CONTROLE V. P. URBANAS LTDA | D19: Ativo | E19: QSMA | F19: MANUTENÇÃO EDIFÍCIOS / INSTALAÇÕES | G19: INDUSTRIAL VIES | H19: B | I19: GS CONTROLE V. P. URBANAS LTDA | J19: 30 DIAS | K19: VIESFB | L19: PRGM .COMPRAS - VIES - FABRICA | M19: =SUMIFS(#REF!,#REF!, $A19,#REF!, ">="&'Faturado mensal'!M$2,#REF!, "<"&EOMONTH('Faturado mensal'!M$2,0)) -> 283.62 | N19: =SUMIFS(#REF!,#REF!, $A19,#REF!, ">="&'Faturado mensal'!N$2,#REF!, "<"&EOMONTH('Faturado mensal'!N$2,0)) -> 0 | O19: =SUMIFS(#REF!,#REF!, $A19,#REF!, ">="&'Faturado mensal'!O$2,#REF!, "<"&EOMONTH('Faturado mensal'!O$2,0)) -> 0 | P19: =SUMIFS(#REF!,#REF!, $A19,#REF!, ">="&'Faturado mensal'!P$2,#REF!, "<"&EOMONTH('Faturado mensal'!P$2,0)) -> 283.62 | Q19: =SUMIFS(#REF!,#REF!, $A19,#REF!, ">="&'Faturado mensal'!Q$2,#REF!, "<"&EOMONTH('Faturado mensal'!Q$2,0)) -> 0 | R19: =SUMIFS(#REF!,#REF!, $A19,#REF!, ">="&'Faturado mensal'!R$2,#REF!, "<"&EOMONTH('Faturado mensal'!R$2,0)) -> 1828.63 | S19: =SUMIFS(#REF!,#REF!, $A19,#REF!, ">="&'Faturado mensal'!S$2,#REF!, "<"&EOMONTH('Faturado mensal'!S$2,0)) -> 1000 | T19: =SUMIFS(#REF!,#REF!, $A19,#REF!, ">="&'Faturado mensal'!T$2,#REF!, "<"&EOMONTH('Faturado mensal'!T$2,0)) -> 0 | ... X19: =SUMIFS(#REF!,#REF!, $A19,#REF!, ">="&'Faturado mensal'!X$2,#REF!, "<"&EOMONTH('Faturado mensal'!X$2,0)) -> 4458.63 | Y19: =SUMIFS(#REF!,#REF!, $A19,#REF!, ">="&'Faturado mensal'!M$2,#REF!, "<"&EOMONTH('Faturado mensal'!M$2,12)) -> 10169.5 | Z19: =SUMIFS(#REF!,#REF!, $A19,#REF!, ">="&'Faturado mensal'!Z$2,#REF!, "<"&EOMONTH('Faturado mensal'!Z$2,0)) -> 0 | AA19: =SUMIFS(#REF!,#REF!, $A19,#REF!, ">="&'Faturado mensal'!AA$2,#REF!, "<"&EOMONTH('Faturado mensal'!AA$2,0)) -> 2630 | AB19: =SUMIFS(#REF!,#REF!, $A19,#REF!, ">="&'Faturado mensal'!AB$2,#REF!, "<"&EOMONTH('Faturado mensal'!AB$2,0)) -> 1315 | AC19: =SUMIFS(#REF!,#REF!, $A19,#REF!, ">="&'Faturado mensal'!AC$2,#REF!, "<"&EOMONTH('Faturado mensal'!AC$2,0)) -> 0 | AD19: =SUMIFS(#REF!,#REF!, $A19,#REF!, ">="&'Faturado mensal'!AD$2,#REF!, "<"&EOMONTH('Faturado mensal'!AD$2,0)) -> 1315 | AE19: =SUMIFS(#REF!,#REF!, $A19,#REF!, ">="&'Faturado mensal'!AE$2,#REF!, "<"&EOMONTH('Faturado mensal'!AE$2,0)) -> 1315 | AF19: =SUMIFS(#REF!,#REF!, $A19,#REF!, ">="&'Faturado mensal'!AF$2,#REF!, "<"&EOMONTH('Faturado mensal'!AF$2,0)) -> 0 | AG19: =SUMIFS(#REF!,#REF!, $A19,#REF!, ">="&'Faturado mensal'!AG$2,#REF!, "<"&EOMONTH('Faturado mensal'!AG$2,0)) -> 0 | ... AK19: =SUMIFS(#REF!,#REF!, $A19,#REF!, ">="&'Faturado mensal'!AK$2,#REF!, "<"&EOMONTH('Faturado mensal'!AK$2,0)) -> 0 | AL19: =SUMIFS(#REF!,#REF!, $A19,#REF!, ">="&Z$2,#REF!, "<"&EOMONTH(AK$2,0)) -> 6575
A20: CS0000687 | B20: 070065603 | C20: TECMES E SERVICOS PRO INF LTDA | D20: Ativo | E20: ENGENHARIA PRODUTO | F20: SERVIÇOS PRESTADOS | G20: ENGENHARIA PRODUTO | H20: B | I20: TECMES E SERVICOS PRO INF LTDA | J20: 30 DIAS | K20: VIESFB | L20: PRGM .COMPRAS - VIES - FABRICA | M20: =SUMIFS(#REF!,#REF!, $A20,#REF!, ">="&'Faturado mensal'!M$2,#REF!, "<"&EOMONTH('Faturado mensal'!M$2,0)) -> 476.36 | N20: =SUMIFS(#REF!,#REF!, $A20,#REF!, ">="&'Faturado mensal'!N$2,#REF!, "<"&EOMONTH('Faturado mensal'!N$2,0)) -> 476.36 | O20: =SUMIFS(#REF!,#REF!, $A20,#REF!, ">="&'Faturado mensal'!O$2,#REF!, "<"&EOMONTH('Faturado mensal'!O$2,0)) -> 476.36 | P20: =SUMIFS(#REF!,#REF!, $A20,#REF!, ">="&'Faturado mensal'!P$2,#REF!, "<"&EOMONTH('Faturado mensal'!P$2,0)) -> 476.36 | Q20: =SUMIFS(#REF!,#REF!, $A20,#REF!, ">="&'Faturado mensal'!Q$2,#REF!, "<"&EOMONTH('Faturado mensal'!Q$2,0)) -> 476.36 | R20: =SUMIFS(#REF!,#REF!, $A20,#REF!, ">="&'Faturado mensal'!R$2,#REF!, "<"&EOMONTH('Faturado mensal'!R$2,0)) -> 476.36 | S20: =SUMIFS(#REF!,#REF!, $A20,#REF!, ">="&'Faturado mensal'!S$2,#REF!, "<"&EOMONTH('Faturado mensal'!S$2,0)) -> 476.36 | T20: =SUMIFS(#REF!,#REF!, $A20,#REF!, ">="&'Faturado mensal'!T$2,#REF!, "<"&EOMONTH('Faturado mensal'!T$2,0)) -> 476.36 | ... X20: =SUMIFS(#REF!,#REF!, $A20,#REF!, ">="&'Faturado mensal'!X$2,#REF!, "<"&EOMONTH('Faturado mensal'!X$2,0)) -> 476.36 | Y20: =SUMIFS(#REF!,#REF!, $A20,#REF!, ">="&'Faturado mensal'!M$2,#REF!, "<"&EOMONTH('Faturado mensal'!M$2,12)) -> 6192.68 | Z20: =SUMIFS(#REF!,#REF!, $A20,#REF!, ">="&'Faturado mensal'!Z$2,#REF!, "<"&EOMONTH('Faturado mensal'!Z$2,0)) -> 476.36 | AA20: =SUMIFS(#REF!,#REF!, $A20,#REF!, ">="&'Faturado mensal'!AA$2,#REF!, "<"&EOMONTH('Faturado mensal'!AA$2,0)) -> 476.36 | AB20: =SUMIFS(#REF!,#REF!, $A20,#REF!, ">="&'Faturado mensal'!AB$2,#REF!, "<"&EOMONTH('Faturado mensal'!AB$2,0)) -> 476.36 | AC20: =SUMIFS(#REF!,#REF!, $A20,#REF!, ">="&'Faturado mensal'!AC$2,#REF!, "<"&EOMONTH('Faturado mensal'!AC$2,0)) -> 476.36 | AD20: =SUMIFS(#REF!,#REF!, $A20,#REF!, ">="&'Faturado mensal'!AD$2,#REF!, "<"&EOMONTH('Faturado mensal'!AD$2,0)) -> 476.36 | AE20: =SUMIFS(#REF!,#REF!, $A20,#REF!, ">="&'Faturado mensal'!AE$2,#REF!, "<"&EOMONTH('Faturado mensal'!AE$2,0)) -> 476.36 | AF20: =SUMIFS(#REF!,#REF!, $A20,#REF!, ">="&'Faturado mensal'!AF$2,#REF!, "<"&EOMONTH('Faturado mensal'!AF$2,0)) -> 0 | AG20: =SUMIFS(#REF!,#REF!, $A20,#REF!, ">="&'Faturado mensal'!AG$2,#REF!, "<"&EOMONTH('Faturado mensal'!AG$2,0)) -> 0 | ... AK20: =SUMIFS(#REF!,#REF!, $A20,#REF!, ">="&'Faturado mensal'!AK$2,#REF!, "<"&EOMONTH('Faturado mensal'!AK$2,0)) -> 0 | AL20: =SUMIFS(#REF!,#REF!, $A20,#REF!, ">="&Z$2,#REF!, "<"&EOMONTH(AK$2,0)) -> 2858.16
A21: CS0000692 | B21: 070020209 | C21: AUDAX EXTINTORES COM.MAT.SEG.L | D21: Concluído | I21: AUDAX EXTINTORES COM.MAT.SEG.L | J21: 30 DIAS | K21: VIESFB | L21: PRGM .COMPRAS - VIES - FABRICA | M21: =SUMIFS(#REF!,#REF!, $A21,#REF!, ">="&'Faturado mensal'!M$2,#REF!, "<"&EOMONTH('Faturado mensal'!M$2,0)) -> 0 | N21: =SUMIFS(#REF!,#REF!, $A21,#REF!, ">="&'Faturado mensal'!N$2,#REF!, "<"&EOMONTH('Faturado mensal'!N$2,0)) -> 0 | O21: =SUMIFS(#REF!,#REF!, $A21,#REF!, ">="&'Faturado mensal'!O$2,#REF!, "<"&EOMONTH('Faturado mensal'!O$2,0)) -> 0 | P21: =SUMIFS(#REF!,#REF!, $A21,#REF!, ">="&'Faturado mensal'!P$2,#REF!, "<"&EOMONTH('Faturado mensal'!P$2,0)) -> 0 | Q21: =SUMIFS(#REF!,#REF!, $A21,#REF!, ">="&'Faturado mensal'!Q$2,#REF!, "<"&EOMONTH('Faturado mensal'!Q$2,0)) -> 0 | R21: =SUMIFS(#REF!,#REF!, $A21,#REF!, ">="&'Faturado mensal'!R$2,#REF!, "<"&EOMONTH('Faturado mensal'!R$2,0)) -> 0 | S21: =SUMIFS(#REF!,#REF!, $A21,#REF!, ">="&'Faturado mensal'!S$2,#REF!, "<"&EOMONTH('Faturado mensal'!S$2,0)) -> 0 | T21: =SUMIFS(#REF!,#REF!, $A21,#REF!, ">="&'Faturado mensal'!T$2,#REF!, "<"&EOMONTH('Faturado mensal'!T$2,0)) -> 0 | ... X21: =SUMIFS(#REF!,#REF!, $A21,#REF!, ">="&'Faturado mensal'!X$2,#REF!, "<"&EOMONTH('Faturado mensal'!X$2,0)) -> 0 | Y21: =SUMIFS(#REF!,#REF!, $A21,#REF!, ">="&'Faturado mensal'!M$2,#REF!, "<"&EOMONTH('Faturado mensal'!M$2,12)) -> 0 | Z21: =SUMIFS(#REF!,#REF!, $A21,#REF!, ">="&'Faturado mensal'!Z$2,#REF!, "<"&EOMONTH('Faturado mensal'!Z$2,0)) -> 0 | AA21: =SUMIFS(#REF!,#REF!, $A21,#REF!, ">="&'Faturado mensal'!AA$2,#REF!, "<"&EOMONTH('Faturado mensal'!AA$2,0)) -> 0 | AB21: =SUMIFS(#REF!,#REF!, $A21,#REF!, ">="&'Faturado mensal'!AB$2,#REF!, "<"&EOMONTH('Faturado mensal'!AB$2,0)) -> 0 | AC21: =SUMIFS(#REF!,#REF!, $A21,#REF!, ">="&'Faturado mensal'!AC$2,#REF!, "<"&EOMONTH('Faturado mensal'!AC$2,0)) -> 0 | AD21: =SUMIFS(#REF!,#REF!, $A21,#REF!, ">="&'Faturado mensal'!AD$2,#REF!, "<"&EOMONTH('Faturado mensal'!AD$2,0)) -> 0 | AE21: =SUMIFS(#REF!,#REF!, $A21,#REF!, ">="&'Faturado mensal'!AE$2,#REF!, "<"&EOMONTH('Faturado mensal'!AE$2,0)) -> 0 | AF21: =SUMIFS(#REF!,#REF!, $A21,#REF!, ">="&'Faturado mensal'!AF$2,#REF!, "<"&EOMONTH('Faturado mensal'!AF$2,0)) -> 0 | AG21: =SUMIFS(#REF!,#REF!, $A21,#REF!, ">="&'Faturado mensal'!AG$2,#REF!, "<"&EOMONTH('Faturado mensal'!AG$2,0)) -> 0 | ... AK21: =SUMIFS(#REF!,#REF!, $A21,#REF!, ">="&'Faturado mensal'!AK$2,#REF!, "<"&EOMONTH('Faturado mensal'!AK$2,0)) -> 0 | AL21: =SUMIFS(#REF!,#REF!, $A21,#REF!, ">="&Z$2,#REF!, "<"&EOMONTH(AK$2,0)) -> 0
A22: CS0000693 | B22: 090010056 | C22: VERZANI & SANDRINI ADM.MO LTDA | D22: Concluído | I22: VERZANI & SANDRINI ADM.MO LTDA | J22: 30 DIAS | K22: VIESFB | L22: PRGM .COMPRAS - VIES - FABRICA | M22: =SUMIFS(#REF!,#REF!, $A22,#REF!, ">="&'Faturado mensal'!M$2,#REF!, "<"&EOMONTH('Faturado mensal'!M$2,0)) -> 0 | N22: =SUMIFS(#REF!,#REF!, $A22,#REF!, ">="&'Faturado mensal'!N$2,#REF!, "<"&EOMONTH('Faturado mensal'!N$2,0)) -> 0 | O22: =SUMIFS(#REF!,#REF!, $A22,#REF!, ">="&'Faturado mensal'!O$2,#REF!, "<"&EOMONTH('Faturado mensal'!O$2,0)) -> 0 | P22: =SUMIFS(#REF!,#REF!, $A22,#REF!, ">="&'Faturado mensal'!P$2,#REF!, "<"&EOMONTH('Faturado mensal'!P$2,0)) -> 0 | Q22: =SUMIFS(#REF!,#REF!, $A22,#REF!, ">="&'Faturado mensal'!Q$2,#REF!, "<"&EOMONTH('Faturado mensal'!Q$2,0)) -> 0 | R22: =SUMIFS(#REF!,#REF!, $A22,#REF!, ">="&'Faturado mensal'!R$2,#REF!, "<"&EOMONTH('Faturado mensal'!R$2,0)) -> 0 | S22: =SUMIFS(#REF!,#REF!, $A22,#REF!, ">="&'Faturado mensal'!S$2,#REF!, "<"&EOMONTH('Faturado mensal'!S$2,0)) -> 0 | T22: =SUMIFS(#REF!,#REF!, $A22,#REF!, ">="&'Faturado mensal'!T$2,#REF!, "<"&EOMONTH('Faturado mensal'!T$2,0)) -> 0 | ... X22: =SUMIFS(#REF!,#REF!, $A22,#REF!, ">="&'Faturado mensal'!X$2,#REF!, "<"&EOMONTH('Faturado mensal'!X$2,0)) -> 0 | Y22: =SUMIFS(#REF!,#REF!, $A22,#REF!, ">="&'Faturado mensal'!M$2,#REF!, "<"&EOMONTH('Faturado mensal'!M$2,12)) -> 0 | Z22: =SUMIFS(#REF!,#REF!, $A22,#REF!, ">="&'Faturado mensal'!Z$2,#REF!, "<"&EOMONTH('Faturado mensal'!Z$2,0)) -> 0 | AA22: =SUMIFS(#REF!,#REF!, $A22,#REF!, ">="&'Faturado mensal'!AA$2,#REF!, "<"&EOMONTH('Faturado mensal'!AA$2,0)) -> 0 | AB22: =SUMIFS(#REF!,#REF!, $A22,#REF!, ">="&'Faturado mensal'!AB$2,#REF!, "<"&EOMONTH('Faturado mensal'!AB$2,0)) -> 0 | AC22: =SUMIFS(#REF!,#REF!, $A22,#REF!, ">="&'Faturado mensal'!AC$2,#REF!, "<"&EOMONTH('Faturado mensal'!AC$2,0)) -> 0 | AD22: =SUMIFS(#REF!,#REF!, $A22,#REF!, ">="&'Faturado mensal'!AD$2,#REF!, "<"&EOMONTH('Faturado mensal'!AD$2,0)) -> 0 | AE22: =SUMIFS(#REF!,#REF!, $A22,#REF!, ">="&'Faturado mensal'!AE$2,#REF!, "<"&EOMONTH('Faturado mensal'!AE$2,0)) -> 0 | AF22: =SUMIFS(#REF!,#REF!, $A22,#REF!, ">="&'Faturado mensal'!AF$2,#REF!, "<"&EOMONTH('Faturado mensal'!AF$2,0)) -> 0 | AG22: =SUMIFS(#REF!,#REF!, $A22,#REF!, ">="&'Faturado mensal'!AG$2,#REF!, "<"&EOMONTH('Faturado mensal'!AG$2,0)) -> 0 | ... AK22: =SUMIFS(#REF!,#REF!, $A22,#REF!, ">="&'Faturado mensal'!AK$2,#REF!, "<"&EOMONTH('Faturado mensal'!AK$2,0)) -> 0 | AL22: =SUMIFS(#REF!,#REF!, $A22,#REF!, ">="&Z$2,#REF!, "<"&EOMONTH(AK$2,0)) -> 0
A23: CS0000696 | B23: 090003565 | C23: IMIGRANTES EMPREEND. PART.LTDA | D23: Ativo | E23: CONSELHO | F23: SERVIÇOS PRESTADOS | G23: ADMINISTRATIVO | H23: C | I23: IMIGRANTES EMPREEND. PART.LTDA | J23: 30 DIAS | K23: 333ADM | L23: COMPRAS - 333 - ADMINISTRAÇÃO | M23: =SUMIFS(#REF!,#REF!, $A23,#REF!, ">="&'Faturado mensal'!M$2,#REF!, "<"&EOMONTH('Faturado mensal'!M$2,0)) -> 81089.2 | N23: =SUMIFS(#REF!,#REF!, $A23,#REF!, ">="&'Faturado mensal'!N$2,#REF!, "<"&EOMONTH('Faturado mensal'!N$2,0)) -> 81786.34 | O23: =SUMIFS(#REF!,#REF!, $A23,#REF!, ">="&'Faturado mensal'!O$2,#REF!, "<"&EOMONTH('Faturado mensal'!O$2,0)) -> 79690.48 | P23: =SUMIFS(#REF!,#REF!, $A23,#REF!, ">="&'Faturado mensal'!P$2,#REF!, "<"&EOMONTH('Faturado mensal'!P$2,0)) -> 91130.89 | Q23: =SUMIFS(#REF!,#REF!, $A23,#REF!, ">="&'Faturado mensal'!Q$2,#REF!, "<"&EOMONTH('Faturado mensal'!Q$2,0)) -> 83578.77 | R23: =SUMIFS(#REF!,#REF!, $A23,#REF!, ">="&'Faturado mensal'!R$2,#REF!, "<"&EOMONTH('Faturado mensal'!R$2,0)) -> 82283.88 | S23: =SUMIFS(#REF!,#REF!, $A23,#REF!, ">="&'Faturado mensal'!S$2,#REF!, "<"&EOMONTH('Faturado mensal'!S$2,0)) -> 78146.75 | T23: =SUMIFS(#REF!,#REF!, $A23,#REF!, ">="&'Faturado mensal'!T$2,#REF!, "<"&EOMONTH('Faturado mensal'!T$2,0)) -> 93690.94 | ... X23: =SUMIFS(#REF!,#REF!, $A23,#REF!, ">="&'Faturado mensal'!X$2,#REF!, "<"&EOMONTH('Faturado mensal'!X$2,0)) -> 125650.73 | Y23: =SUMIFS(#REF!,#REF!, $A23,#REF!, ">="&'Faturado mensal'!M$2,#REF!, "<"&EOMONTH('Faturado mensal'!M$2,12)) -> 1234291.7 | Z23: =SUMIFS(#REF!,#REF!, $A23,#REF!, ">="&'Faturado mensal'!Z$2,#REF!, "<"&EOMONTH('Faturado mensal'!Z$2,0)) -> 146093.96 | AA23: =SUMIFS(#REF!,#REF!, $A23,#REF!, ">="&'Faturado mensal'!AA$2,#REF!, "<"&EOMONTH('Faturado mensal'!AA$2,0)) -> 77365.62 | AB23: =SUMIFS(#REF!,#REF!, $A23,#REF!, ">="&'Faturado mensal'!AB$2,#REF!, "<"&EOMONTH('Faturado mensal'!AB$2,0)) -> 126650.56 | AC23: =SUMIFS(#REF!,#REF!, $A23,#REF!, ">="&'Faturado mensal'!AC$2,#REF!, "<"&EOMONTH('Faturado mensal'!AC$2,0)) -> 145954.6 | AD23: =SUMIFS(#REF!,#REF!, $A23,#REF!, ">="&'Faturado mensal'!AD$2,#REF!, "<"&EOMONTH('Faturado mensal'!AD$2,0)) -> 121054.8 | AE23: =SUMIFS(#REF!,#REF!, $A23,#REF!, ">="&'Faturado mensal'!AE$2,#REF!, "<"&EOMONTH('Faturado mensal'!AE$2,0)) -> 104715.95 | AF23: =SUMIFS(#REF!,#REF!, $A23,#REF!, ">="&'Faturado mensal'!AF$2,#REF!, "<"&EOMONTH('Faturado mensal'!AF$2,0)) -> 0 | AG23: =SUMIFS(#REF!,#REF!, $A23,#REF!, ">="&'Faturado mensal'!AG$2,#REF!, "<"&EOMONTH('Faturado mensal'!AG$2,0)) -> 0 | ... AK23: =SUMIFS(#REF!,#REF!, $A23,#REF!, ">="&'Faturado mensal'!AK$2,#REF!, "<"&EOMONTH('Faturado mensal'!AK$2,0)) -> 0 | AL23: =SUMIFS(#REF!,#REF!, $A23,#REF!, ">="&Z$2,#REF!, "<"&EOMONTH(AK$2,0)) -> 724763.49
A24: CS0000698 | B24: 070001585 | C24: TELOS CONSULTORIA EMPRESARIAL LTDA | D24: Concluído | I24: TELOS CONSULTORIA EMPRESARIAL | J24: 30 DIAS | K24: COFAB | L24: PRGM . COMPRAS - CO - FABRICA | M24: =SUMIFS(#REF!,#REF!, $A24,#REF!, ">="&'Faturado mensal'!M$2,#REF!, "<"&EOMONTH('Faturado mensal'!M$2,0)) -> 0 | N24: =SUMIFS(#REF!,#REF!, $A24,#REF!, ">="&'Faturado mensal'!N$2,#REF!, "<"&EOMONTH('Faturado mensal'!N$2,0)) -> 0 | O24: =SUMIFS(#REF!,#REF!, $A24,#REF!, ">="&'Faturado mensal'!O$2,#REF!, "<"&EOMONTH('Faturado mensal'!O$2,0)) -> 0 | P24: =SUMIFS(#REF!,#REF!, $A24,#REF!, ">="&'Faturado mensal'!P$2,#REF!, "<"&EOMONTH('Faturado mensal'!P$2,0)) -> 0 | Q24: =SUMIFS(#REF!,#REF!, $A24,#REF!, ">="&'Faturado mensal'!Q$2,#REF!, "<"&EOMONTH('Faturado mensal'!Q$2,0)) -> 0 | R24: =SUMIFS(#REF!,#REF!, $A24,#REF!, ">="&'Faturado mensal'!R$2,#REF!, "<"&EOMONTH('Faturado mensal'!R$2,0)) -> 0 | S24: =SUMIFS(#REF!,#REF!, $A24,#REF!, ">="&'Faturado mensal'!S$2,#REF!, "<"&EOMONTH('Faturado mensal'!S$2,0)) -> 0 | T24: =SUMIFS(#REF!,#REF!, $A24,#REF!, ">="&'Faturado mensal'!T$2,#REF!, "<"&EOMONTH('Faturado mensal'!T$2,0)) -> 0 | ... X24: =SUMIFS(#REF!,#REF!, $A24,#REF!, ">="&'Faturado mensal'!X$2,#REF!, "<"&EOMONTH('Faturado mensal'!X$2,0)) -> 0 | Y24: =SUMIFS(#REF!,#REF!, $A24,#REF!, ">="&'Faturado mensal'!M$2,#REF!, "<"&EOMONTH('Faturado mensal'!M$2,12)) -> 0 | Z24: =SUMIFS(#REF!,#REF!, $A24,#REF!, ">="&'Faturado mensal'!Z$2,#REF!, "<"&EOMONTH('Faturado mensal'!Z$2,0)) -> 0 | AA24: =SUMIFS(#REF!,#REF!, $A24,#REF!, ">="&'Faturado mensal'!AA$2,#REF!, "<"&EOMONTH('Faturado mensal'!AA$2,0)) -> 0 | AB24: =SUMIFS(#REF!,#REF!, $A24,#REF!, ">="&'Faturado mensal'!AB$2,#REF!, "<"&EOMONTH('Faturado mensal'!AB$2,0)) -> 0 | AC24: =SUMIFS(#REF!,#REF!, $A24,#REF!, ">="&'Faturado mensal'!AC$2,#REF!, "<"&EOMONTH('Faturado mensal'!AC$2,0)) -> 0 | AD24: =SUMIFS(#REF!,#REF!, $A24,#REF!, ">="&'Faturado mensal'!AD$2,#REF!, "<"&EOMONTH('Faturado mensal'!AD$2,0)) -> 0 | AE24: =SUMIFS(#REF!,#REF!, $A24,#REF!, ">="&'Faturado mensal'!AE$2,#REF!, "<"&EOMONTH('Faturado mensal'!AE$2,0)) -> 0 | AF24: =SUMIFS(#REF!,#REF!, $A24,#REF!, ">="&'Faturado mensal'!AF$2,#REF!, "<"&EOMONTH('Faturado mensal'!AF$2,0)) -> 0 | AG24: =SUMIFS(#REF!,#REF!, $A24,#REF!, ">="&'Faturado mensal'!AG$2,#REF!, "<"&EOMONTH('Faturado mensal'!AG$2,0)) -> 0 | ... AK24: =SUMIFS(#REF!,#REF!, $A24,#REF!, ">="&'Faturado mensal'!AK$2,#REF!, "<"&EOMONTH('Faturado mensal'!AK$2,0)) -> 0 | AL24: =SUMIFS(#REF!,#REF!, $A24,#REF!, ">="&Z$2,#REF!, "<"&EOMONTH(AK$2,0)) -> 0
A25: CS0000700 | B25: 090001789 | C25: INST. DA QUALIDADE AUTOMOT.IQA | D25: Ativo | E25: QSMA | F25: SERVIÇOS PRESTADOS | G25: INDUSTRIAL SRS | H25: B | I25: INST. DA QUALIDADE AUTOMOT.IQA | J25: 30 DIAS | K25: SRSFAB | L25: PRGM . COMPRAS - SRS - FABRICA | M25: =SUMIFS(#REF!,#REF!, $A25,#REF!, ">="&'Faturado mensal'!M$2,#REF!, "<"&EOMONTH('Faturado mensal'!M$2,0)) -> 0 | N25: =SUMIFS(#REF!,#REF!, $A25,#REF!, ">="&'Faturado mensal'!N$2,#REF!, "<"&EOMONTH('Faturado mensal'!N$2,0)) -> 0 | O25: =SUMIFS(#REF!,#REF!, $A25,#REF!, ">="&'Faturado mensal'!O$2,#REF!, "<"&EOMONTH('Faturado mensal'!O$2,0)) -> 0 | P25: =SUMIFS(#REF!,#REF!, $A25,#REF!, ">="&'Faturado mensal'!P$2,#REF!, "<"&EOMONTH('Faturado mensal'!P$2,0)) -> 0 | Q25: =SUMIFS(#REF!,#REF!, $A25,#REF!, ">="&'Faturado mensal'!Q$2,#REF!, "<"&EOMONTH('Faturado mensal'!Q$2,0)) -> 0 | R25: =SUMIFS(#REF!,#REF!, $A25,#REF!, ">="&'Faturado mensal'!R$2,#REF!, "<"&EOMONTH('Faturado mensal'!R$2,0)) -> 14793 | S25: =SUMIFS(#REF!,#REF!, $A25,#REF!, ">="&'Faturado mensal'!S$2,#REF!, "<"&EOMONTH('Faturado mensal'!S$2,0)) -> 0 | T25: =SUMIFS(#REF!,#REF!, $A25,#REF!, ">="&'Faturado mensal'!T$2,#REF!, "<"&EOMONTH('Faturado mensal'!T$2,0)) -> 0 | ... X25: =SUMIFS(#REF!,#REF!, $A25,#REF!, ">="&'Faturado mensal'!X$2,#REF!, "<"&EOMONTH('Faturado mensal'!X$2,0)) -> 0 | Y25: =SUMIFS(#REF!,#REF!, $A25,#REF!, ">="&'Faturado mensal'!M$2,#REF!, "<"&EOMONTH('Faturado mensal'!M$2,12)) -> 14793 | Z25: =SUMIFS(#REF!,#REF!, $A25,#REF!, ">="&'Faturado mensal'!Z$2,#REF!, "<"&EOMONTH('Faturado mensal'!Z$2,0)) -> 0 | AA25: =SUMIFS(#REF!,#REF!, $A25,#REF!, ">="&'Faturado mensal'!AA$2,#REF!, "<"&EOMONTH('Faturado mensal'!AA$2,0)) -> 0 | AB25: =SUMIFS(#REF!,#REF!, $A25,#REF!, ">="&'Faturado mensal'!AB$2,#REF!, "<"&EOMONTH('Faturado mensal'!AB$2,0)) -> 0 | AC25: =SUMIFS(#REF!,#REF!, $A25,#REF!, ">="&'Faturado mensal'!AC$2,#REF!, "<"&EOMONTH('Faturado mensal'!AC$2,0)) -> 0 | AD25: =SUMIFS(#REF!,#REF!, $A25,#REF!, ">="&'Faturado mensal'!AD$2,#REF!, "<"&EOMONTH('Faturado mensal'!AD$2,0)) -> 0 | AE25: =SUMIFS(#REF!,#REF!, $A25,#REF!, ">="&'Faturado mensal'!AE$2,#REF!, "<"&EOMONTH('Faturado mensal'!AE$2,0)) -> 0 | AF25: =SUMIFS(#REF!,#REF!, $A25,#REF!, ">="&'Faturado mensal'!AF$2,#REF!, "<"&EOMONTH('Faturado mensal'!AF$2,0)) -> 0 | AG25: =SUMIFS(#REF!,#REF!, $A25,#REF!, ">="&'Faturado mensal'!AG$2,#REF!, "<"&EOMONTH('Faturado mensal'!AG$2,0)) -> 0 | ... AK25: =SUMIFS(#REF!,#REF!, $A25,#REF!, ">="&'Faturado mensal'!AK$2,#REF!, "<"&EOMONTH('Faturado mensal'!AK$2,0)) -> 0 | AL25: =SUMIFS(#REF!,#REF!, $A25,#REF!, ">="&Z$2,#REF!, "<"&EOMONTH(AK$2,0)) -> 36550
A26: CS0000702 | B26: 070075837 | C26: GS CONTROLE V. P. URBANAS LTDA | D26: Ativo | E26: QSMA | F26: SERVIÇOS PRESTADOS | G26: INDUSTRIAL SRS | H26: B | I26: GS CONTROLE V. P. URBANAS LTDA | J26: 30 DIAS | K26: SRSFAB | L26: PRGM . COMPRAS - SRS - FABRICA | M26: =SUMIFS(#REF!,#REF!, $A26,#REF!, ">="&'Faturado mensal'!M$2,#REF!, "<"&EOMONTH('Faturado mensal'!M$2,0)) -> 0 | N26: =SUMIFS(#REF!,#REF!, $A26,#REF!, ">="&'Faturado mensal'!N$2,#REF!, "<"&EOMONTH('Faturado mensal'!N$2,0)) -> 0 | O26: =SUMIFS(#REF!,#REF!, $A26,#REF!, ">="&'Faturado mensal'!O$2,#REF!, "<"&EOMONTH('Faturado mensal'!O$2,0)) -> 0 | P26: =SUMIFS(#REF!,#REF!, $A26,#REF!, ">="&'Faturado mensal'!P$2,#REF!, "<"&EOMONTH('Faturado mensal'!P$2,0)) -> 0 | Q26: =SUMIFS(#REF!,#REF!, $A26,#REF!, ">="&'Faturado mensal'!Q$2,#REF!, "<"&EOMONTH('Faturado mensal'!Q$2,0)) -> 4491.99 | R26: =SUMIFS(#REF!,#REF!, $A26,#REF!, ">="&'Faturado mensal'!R$2,#REF!, "<"&EOMONTH('Faturado mensal'!R$2,0)) -> 0 | S26: =SUMIFS(#REF!,#REF!, $A26,#REF!, ">="&'Faturado mensal'!S$2,#REF!, "<"&EOMONTH('Faturado mensal'!S$2,0)) -> 0 | T26: =SUMIFS(#REF!,#REF!, $A26,#REF!, ">="&'Faturado mensal'!T$2,#REF!, "<"&EOMONTH('Faturado mensal'!T$2,0)) -> 0 | ... X26: =SUMIFS(#REF!,#REF!, $A26,#REF!, ">="&'Faturado mensal'!X$2,#REF!, "<"&EOMONTH('Faturado mensal'!X$2,0)) -> 4664.04 | Y26: =SUMIFS(#REF!,#REF!, $A26,#REF!, ">="&'Faturado mensal'!M$2,#REF!, "<"&EOMONTH('Faturado mensal'!M$2,12)) -> 9156.03 | Z26: =SUMIFS(#REF!,#REF!, $A26,#REF!, ">="&'Faturado mensal'!Z$2,#REF!, "<"&EOMONTH('Faturado mensal'!Z$2,0)) -> 0 | AA26: =SUMIFS(#REF!,#REF!, $A26,#REF!, ">="&'Faturado mensal'!AA$2,#REF!, "<"&EOMONTH('Faturado mensal'!AA$2,0)) -> 0 | AB26: =SUMIFS(#REF!,#REF!, $A26,#REF!, ">="&'Faturado mensal'!AB$2,#REF!, "<"&EOMONTH('Faturado mensal'!AB$2,0)) -> 0 | AC26: =SUMIFS(#REF!,#REF!, $A26,#REF!, ">="&'Faturado mensal'!AC$2,#REF!, "<"&EOMONTH('Faturado mensal'!AC$2,0)) -> 0 | AD26: =SUMIFS(#REF!,#REF!, $A26,#REF!, ">="&'Faturado mensal'!AD$2,#REF!, "<"&EOMONTH('Faturado mensal'!AD$2,0)) -> 0 | AE26: =SUMIFS(#REF!,#REF!, $A26,#REF!, ">="&'Faturado mensal'!AE$2,#REF!, "<"&EOMONTH('Faturado mensal'!AE$2,0)) -> 0 | AF26: =SUMIFS(#REF!,#REF!, $A26,#REF!, ">="&'Faturado mensal'!AF$2,#REF!, "<"&EOMONTH('Faturado mensal'!AF$2,0)) -> 0 | AG26: =SUMIFS(#REF!,#REF!, $A26,#REF!, ">="&'Faturado mensal'!AG$2,#REF!, "<"&EOMONTH('Faturado mensal'!AG$2,0)) -> 0 | ... AK26: =SUMIFS(#REF!,#REF!, $A26,#REF!, ">="&'Faturado mensal'!AK$2,#REF!, "<"&EOMONTH('Faturado mensal'!AK$2,0)) -> 0 | AL26: =SUMIFS(#REF!,#REF!, $A26,#REF!, ">="&Z$2,#REF!, "<"&EOMONTH(AK$2,0)) -> 0
A27: CS0000703 | B27: 070090174 | C27: OI S.A. - EM RECUPERACAO JUDICIAL | D27: Ativo | E27: TI | F27: SERVIÇOS TELEFONIA | G27: ADMINISTRATIVO | H27: C | I27: OI MOVEL S.A. | J27: 15 DIAS | K27: SRSADM | L27: COMPRAS - SRS - ADMINISTRAÇÃO | M27: =SUMIFS(#REF!,#REF!, $A27,#REF!, ">="&'Faturado mensal'!M$2,#REF!, "<"&EOMONTH('Faturado mensal'!M$2,0)) -> 0 | N27: =SUMIFS(#REF!,#REF!, $A27,#REF!, ">="&'Faturado mensal'!N$2,#REF!, "<"&EOMONTH('Faturado mensal'!N$2,0)) -> 0 | O27: =SUMIFS(#REF!,#REF!, $A27,#REF!, ">="&'Faturado mensal'!O$2,#REF!, "<"&EOMONTH('Faturado mensal'!O$2,0)) -> 0 | P27: =SUMIFS(#REF!,#REF!, $A27,#REF!, ">="&'Faturado mensal'!P$2,#REF!, "<"&EOMONTH('Faturado mensal'!P$2,0)) -> 0 | Q27: =SUMIFS(#REF!,#REF!, $A27,#REF!, ">="&'Faturado mensal'!Q$2,#REF!, "<"&EOMONTH('Faturado mensal'!Q$2,0)) -> 0 | R27: =SUMIFS(#REF!,#REF!, $A27,#REF!, ">="&'Faturado mensal'!R$2,#REF!, "<"&EOMONTH('Faturado mensal'!R$2,0)) -> 0 | S27: =SUMIFS(#REF!,#REF!, $A27,#REF!, ">="&'Faturado mensal'!S$2,#REF!, "<"&EOMONTH('Faturado mensal'!S$2,0)) -> 0 | T27: =SUMIFS(#REF!,#REF!, $A27,#REF!, ">="&'Faturado mensal'!T$2,#REF!, "<"&EOMONTH('Faturado mensal'!T$2,0)) -> 0 | ... X27: =SUMIFS(#REF!,#REF!, $A27,#REF!, ">="&'Faturado mensal'!X$2,#REF!, "<"&EOMONTH('Faturado mensal'!X$2,0)) -> 0 | Y27: =SUMIFS(#REF!,#REF!, $A27,#REF!, ">="&'Faturado mensal'!M$2,#REF!, "<"&EOMONTH('Faturado mensal'!M$2,12)) -> 0 | Z27: =SUMIFS(#REF!,#REF!, $A27,#REF!, ">="&'Faturado mensal'!Z$2,#REF!, "<"&EOMONTH('Faturado mensal'!Z$2,0)) -> 0 | AA27: =SUMIFS(#REF!,#REF!, $A27,#REF!, ">="&'Faturado mensal'!AA$2,#REF!, "<"&EOMONTH('Faturado mensal'!AA$2,0)) -> 0 | AB27: =SUMIFS(#REF!,#REF!, $A27,#REF!, ">="&'Faturado mensal'!AB$2,#REF!, "<"&EOMONTH('Faturado mensal'!AB$2,0)) -> 0 | AC27: =SUMIFS(#REF!,#REF!, $A27,#REF!, ">="&'Faturado mensal'!AC$2,#REF!, "<"&EOMONTH('Faturado mensal'!AC$2,0)) -> 488.2 | AD27: =SUMIFS(#REF!,#REF!, $A27,#REF!, ">="&'Faturado mensal'!AD$2,#REF!, "<"&EOMONTH('Faturado mensal'!AD$2,0)) -> 0 | AE27: =SUMIFS(#REF!,#REF!, $A27,#REF!, ">="&'Faturado mensal'!AE$2,#REF!, "<"&EOMONTH('Faturado mensal'!AE$2,0)) -> 0 | AF27: =SUMIFS(#REF!,#REF!, $A27,#REF!, ">="&'Faturado mensal'!AF$2,#REF!, "<"&EOMONTH('Faturado mensal'!AF$2,0)) -> 0 | AG27: =SUMIFS(#REF!,#REF!, $A27,#REF!, ">="&'Faturado mensal'!AG$2,#REF!, "<"&EOMONTH('Faturado mensal'!AG$2,0)) -> 0 | ... AK27: =SUMIFS(#REF!,#REF!, $A27,#REF!, ">="&'Faturado mensal'!AK$2,#REF!, "<"&EOMONTH('Faturado mensal'!AK$2,0)) -> 0 | AL27: =SUMIFS(#REF!,#REF!, $A27,#REF!, ">="&Z$2,#REF!, "<"&EOMONTH(AK$2,0)) -> 488.2
A28: CS0000708 | B28: 070075809 | C28: RUSSOMANO ADVOCACIA S/S | D28: Concluído | G28: ADMINISTRATIVO | H28: C | I28: RUSSOMANO ADVOCACIA S/S | J28: 30 DIAS | K28: VIESFB | L28: PRGM .COMPRAS - VIES - FABRICA | M28: =SUMIFS(#REF!,#REF!, $A28,#REF!, ">="&'Faturado mensal'!M$2,#REF!, "<"&EOMONTH('Faturado mensal'!M$2,0)) -> 0 | N28: =SUMIFS(#REF!,#REF!, $A28,#REF!, ">="&'Faturado mensal'!N$2,#REF!, "<"&EOMONTH('Faturado mensal'!N$2,0)) -> 0 | O28: =SUMIFS(#REF!,#REF!, $A28,#REF!, ">="&'Faturado mensal'!O$2,#REF!, "<"&EOMONTH('Faturado mensal'!O$2,0)) -> 0 | P28: =SUMIFS(#REF!,#REF!, $A28,#REF!, ">="&'Faturado mensal'!P$2,#REF!, "<"&EOMONTH('Faturado mensal'!P$2,0)) -> 0 | Q28: =SUMIFS(#REF!,#REF!, $A28,#REF!, ">="&'Faturado mensal'!Q$2,#REF!, "<"&EOMONTH('Faturado mensal'!Q$2,0)) -> 0 | R28: =SUMIFS(#REF!,#REF!, $A28,#REF!, ">="&'Faturado mensal'!R$2,#REF!, "<"&EOMONTH('Faturado mensal'!R$2,0)) -> 0 | S28: =SUMIFS(#REF!,#REF!, $A28,#REF!, ">="&'Faturado mensal'!S$2,#REF!, "<"&EOMONTH('Faturado mensal'!S$2,0)) -> 0 | T28: =SUMIFS(#REF!,#REF!, $A28,#REF!, ">="&'Faturado mensal'!T$2,#REF!, "<"&EOMONTH('Faturado mensal'!T$2,0)) -> 0 | ... X28: =SUMIFS(#REF!,#REF!, $A28,#REF!, ">="&'Faturado mensal'!X$2,#REF!, "<"&EOMONTH('Faturado mensal'!X$2,0)) -> 0 | Y28: =SUMIFS(#REF!,#REF!, $A28,#REF!, ">="&'Faturado mensal'!M$2,#REF!, "<"&EOMONTH('Faturado mensal'!M$2,12)) -> 0 | Z28: =SUMIFS(#REF!,#REF!, $A28,#REF!, ">="&'Faturado mensal'!Z$2,#REF!, "<"&EOMONTH('Faturado mensal'!Z$2,0)) -> 0 | AA28: =SUMIFS(#REF!,#REF!, $A28,#REF!, ">="&'Faturado mensal'!AA$2,#REF!, "<"&EOMONTH('Faturado mensal'!AA$2,0)) -> 0 | AB28: =SUMIFS(#REF!,#REF!, $A28,#REF!, ">="&'Faturado mensal'!AB$2,#REF!, "<"&EOMONTH('Faturado mensal'!AB$2,0)) -> 0 | AC28: =SUMIFS(#REF!,#REF!, $A28,#REF!, ">="&'Faturado mensal'!AC$2,#REF!, "<"&EOMONTH('Faturado mensal'!AC$2,0)) -> 0 | AD28: =SUMIFS(#REF!,#REF!, $A28,#REF!, ">="&'Faturado mensal'!AD$2,#REF!, "<"&EOMONTH('Faturado mensal'!AD$2,0)) -> 0 | AE28: =SUMIFS(#REF!,#REF!, $A28,#REF!, ">="&'Faturado mensal'!AE$2,#REF!, "<"&EOMONTH('Faturado mensal'!AE$2,0)) -> 0 | AF28: =SUMIFS(#REF!,#REF!, $A28,#REF!, ">="&'Faturado mensal'!AF$2,#REF!, "<"&EOMONTH('Faturado mensal'!AF$2,0)) -> 0 | AG28: =SUMIFS(#REF!,#REF!, $A28,#REF!, ">="&'Faturado mensal'!AG$2,#REF!, "<"&EOMONTH('Faturado mensal'!AG$2,0)) -> 0 | ... AK28: =SUMIFS(#REF!,#REF!, $A28,#REF!, ">="&'Faturado mensal'!AK$2,#REF!, "<"&EOMONTH('Faturado mensal'!AK$2,0)) -> 0 | AL28: =SUMIFS(#REF!,#REF!, $A28,#REF!, ">="&Z$2,#REF!, "<"&EOMONTH(AK$2,0)) -> 0
A29: CS0000712 | B29: 070076010 | C29: ADM AR CONDICIONADO LTDA EPP | D29: Ativo | E29: MANUFATURA VIES | F29: SERVIÇOS PRESTADOS | G29: INDUSTRIAL VIES | H29: C | I29: ADM AR CONDICIONADO LTDA EPP | J29: 30 DIAS | K29: VIESFB | L29: PRGM .COMPRAS - VIES - FABRICA | M29: =SUMIFS(#REF!,#REF!, $A29,#REF!, ">="&'Faturado mensal'!M$2,#REF!, "<"&EOMONTH('Faturado mensal'!M$2,0)) -> 4926.14 | N29: =SUMIFS(#REF!,#REF!, $A29,#REF!, ">="&'Faturado mensal'!N$2,#REF!, "<"&EOMONTH('Faturado mensal'!N$2,0)) -> 4926.14 | O29: =SUMIFS(#REF!,#REF!, $A29,#REF!, ">="&'Faturado mensal'!O$2,#REF!, "<"&EOMONTH('Faturado mensal'!O$2,0)) -> 4926.14 | P29: =SUMIFS(#REF!,#REF!, $A29,#REF!, ">="&'Faturado mensal'!P$2,#REF!, "<"&EOMONTH('Faturado mensal'!P$2,0)) -> 4926.14 | Q29: =SUMIFS(#REF!,#REF!, $A29,#REF!, ">="&'Faturado mensal'!Q$2,#REF!, "<"&EOMONTH('Faturado mensal'!Q$2,0)) -> 4926.14 | R29: =SUMIFS(#REF!,#REF!, $A29,#REF!, ">="&'Faturado mensal'!R$2,#REF!, "<"&EOMONTH('Faturado mensal'!R$2,0)) -> 4926.14 | S29: =SUMIFS(#REF!,#REF!, $A29,#REF!, ">="&'Faturado mensal'!S$2,#REF!, "<"&EOMONTH('Faturado mensal'!S$2,0)) -> 5271 | T29: =SUMIFS(#REF!,#REF!, $A29,#REF!, ">="&'Faturado mensal'!T$2,#REF!, "<"&EOMONTH('Faturado mensal'!T$2,0)) -> 5271 | ... X29: =SUMIFS(#REF!,#REF!, $A29,#REF!, ">="&'Faturado mensal'!X$2,#REF!, "<"&EOMONTH('Faturado mensal'!X$2,0)) -> 5271 | Y29: =SUMIFS(#REF!,#REF!, $A29,#REF!, ">="&'Faturado mensal'!M$2,#REF!, "<"&EOMONTH('Faturado mensal'!M$2,12)) -> 66453.84 | Z29: =SUMIFS(#REF!,#REF!, $A29,#REF!, ">="&'Faturado mensal'!Z$2,#REF!, "<"&EOMONTH('Faturado mensal'!Z$2,0)) -> 5271 | AA29: =SUMIFS(#REF!,#REF!, $A29,#REF!, ">="&'Faturado mensal'!AA$2,#REF!, "<"&EOMONTH('Faturado mensal'!AA$2,0)) -> 5271 | AB29: =SUMIFS(#REF!,#REF!, $A29,#REF!, ">="&'Faturado mensal'!AB$2,#REF!, "<"&EOMONTH('Faturado mensal'!AB$2,0)) -> 5271 | AC29: =SUMIFS(#REF!,#REF!, $A29,#REF!, ">="&'Faturado mensal'!AC$2,#REF!, "<"&EOMONTH('Faturado mensal'!AC$2,0)) -> 5271 | AD29: =SUMIFS(#REF!,#REF!, $A29,#REF!, ">="&'Faturado mensal'!AD$2,#REF!, "<"&EOMONTH('Faturado mensal'!AD$2,0)) -> 5271 | AE29: =SUMIFS(#REF!,#REF!, $A29,#REF!, ">="&'Faturado mensal'!AE$2,#REF!, "<"&EOMONTH('Faturado mensal'!AE$2,0)) -> 5271 | AF29: =SUMIFS(#REF!,#REF!, $A29,#REF!, ">="&'Faturado mensal'!AF$2,#REF!, "<"&EOMONTH('Faturado mensal'!AF$2,0)) -> 0 | AG29: =SUMIFS(#REF!,#REF!, $A29,#REF!, ">="&'Faturado mensal'!AG$2,#REF!, "<"&EOMONTH('Faturado mensal'!AG$2,0)) -> 0 | ... AK29: =SUMIFS(#REF!,#REF!, $A29,#REF!, ">="&'Faturado mensal'!AK$2,#REF!, "<"&EOMONTH('Faturado mensal'!AK$2,0)) -> 0 | AL29: =SUMIFS(#REF!,#REF!, $A29,#REF!, ">="&Z$2,#REF!, "<"&EOMONTH(AK$2,0)) -> 31626
A30: CS0000715 | B30: 090010398 | C30: WHIRLPOOL S.A | D30: Ativo | E30: REPOSIÇÃO | F30: LOCAÇÕES EQUIPAMENTOS / VEÍCULOS | G30: ADMINISTRATIVO | H30: C | I30: WHIRLPOOL S.A | J30: 30 DIAS | K30: 333FAB | L30: PRGM . COMPRAS - 333 - FABRICA | M30: =SUMIFS(#REF!,#REF!, $A30,#REF!, ">="&'Faturado mensal'!M$2,#REF!, "<"&EOMONTH('Faturado mensal'!M$2,0)) -> 75.08 | N30: =SUMIFS(#REF!,#REF!, $A30,#REF!, ">="&'Faturado mensal'!N$2,#REF!, "<"&EOMONTH('Faturado mensal'!N$2,0)) -> 75.08 | O30: =SUMIFS(#REF!,#REF!, $A30,#REF!, ">="&'Faturado mensal'!O$2,#REF!, "<"&EOMONTH('Faturado mensal'!O$2,0)) -> 75.08 | P30: =SUMIFS(#REF!,#REF!, $A30,#REF!, ">="&'Faturado mensal'!P$2,#REF!, "<"&EOMONTH('Faturado mensal'!P$2,0)) -> 75.08 | Q30: =SUMIFS(#REF!,#REF!, $A30,#REF!, ">="&'Faturado mensal'!Q$2,#REF!, "<"&EOMONTH('Faturado mensal'!Q$2,0)) -> 75.08 | R30: =SUMIFS(#REF!,#REF!, $A30,#REF!, ">="&'Faturado mensal'!R$2,#REF!, "<"&EOMONTH('Faturado mensal'!R$2,0)) -> 75.08 | S30: =SUMIFS(#REF!,#REF!, $A30,#REF!, ">="&'Faturado mensal'!S$2,#REF!, "<"&EOMONTH('Faturado mensal'!S$2,0)) -> 75.08 | T30: =SUMIFS(#REF!,#REF!, $A30,#REF!, ">="&'Faturado mensal'!T$2,#REF!, "<"&EOMONTH('Faturado mensal'!T$2,0)) -> 75.08 | ... X30: =SUMIFS(#REF!,#REF!, $A30,#REF!, ">="&'Faturado mensal'!X$2,#REF!, "<"&EOMONTH('Faturado mensal'!X$2,0)) -> 261.96 | Y30: =SUMIFS(#REF!,#REF!, $A30,#REF!, ">="&'Faturado mensal'!M$2,#REF!, "<"&EOMONTH('Faturado mensal'!M$2,12)) -> 1187.4 | Z30: =SUMIFS(#REF!,#REF!, $A30,#REF!, ">="&'Faturado mensal'!Z$2,#REF!, "<"&EOMONTH('Faturado mensal'!Z$2,0)) -> 87.32 | AA30: =SUMIFS(#REF!,#REF!, $A30,#REF!, ">="&'Faturado mensal'!AA$2,#REF!, "<"&EOMONTH('Faturado mensal'!AA$2,0)) -> 174.64 | AB30: =SUMIFS(#REF!,#REF!, $A30,#REF!, ">="&'Faturado mensal'!AB$2,#REF!, "<"&EOMONTH('Faturado mensal'!AB$2,0)) -> 0 | AC30: =SUMIFS(#REF!,#REF!, $A30,#REF!, ">="&'Faturado mensal'!AC$2,#REF!, "<"&EOMONTH('Faturado mensal'!AC$2,0)) -> 0 | AD30: =SUMIFS(#REF!,#REF!, $A30,#REF!, ">="&'Faturado mensal'!AD$2,#REF!, "<"&EOMONTH('Faturado mensal'!AD$2,0)) -> 0 | AE30: =SUMIFS(#REF!,#REF!, $A30,#REF!, ">="&'Faturado mensal'!AE$2,#REF!, "<"&EOMONTH('Faturado mensal'!AE$2,0)) -> 0 | AF30: =SUMIFS(#REF!,#REF!, $A30,#REF!, ">="&'Faturado mensal'!AF$2,#REF!, "<"&EOMONTH('Faturado mensal'!AF$2,0)) -> 0 | AG30: =SUMIFS(#REF!,#REF!, $A30,#REF!, ">="&'Faturado mensal'!AG$2,#REF!, "<"&EOMONTH('Faturado mensal'!AG$2,0)) -> 0 | ... AK30: =SUMIFS(#REF!,#REF!, $A30,#REF!, ">="&'Faturado mensal'!AK$2,#REF!, "<"&EOMONTH('Faturado mensal'!AK$2,0)) -> 0 | AL30: =SUMIFS(#REF!,#REF!, $A30,#REF!, ">="&Z$2,#REF!, "<"&EOMONTH(AK$2,0)) -> 261.96
A31: CS0000717 | B31: 070020105 | C31: AGIT SOLUCOES AMBIENTAIS LTDA | D31: Concluído | G31: INDUSTRIAL CO | H31: B | I31: AGIT SOLUCOES AMBIENTAIS LTDA | J31: 30 DIAS | K31: COFAB | L31: PRGM . COMPRAS - CO - FABRICA | M31: =SUMIFS(#REF!,#REF!, $A31,#REF!, ">="&'Faturado mensal'!M$2,#REF!, "<"&EOMONTH('Faturado mensal'!M$2,0)) -> 0 | N31: =SUMIFS(#REF!,#REF!, $A31,#REF!, ">="&'Faturado mensal'!N$2,#REF!, "<"&EOMONTH('Faturado mensal'!N$2,0)) -> 0 | O31: =SUMIFS(#REF!,#REF!, $A31,#REF!, ">="&'Faturado mensal'!O$2,#REF!, "<"&EOMONTH('Faturado mensal'!O$2,0)) -> 0 | P31: =SUMIFS(#REF!,#REF!, $A31,#REF!, ">="&'Faturado mensal'!P$2,#REF!, "<"&EOMONTH('Faturado mensal'!P$2,0)) -> 0 | Q31: =SUMIFS(#REF!,#REF!, $A31,#REF!, ">="&'Faturado mensal'!Q$2,#REF!, "<"&EOMONTH('Faturado mensal'!Q$2,0)) -> 0 | R31: =SUMIFS(#REF!,#REF!, $A31,#REF!, ">="&'Faturado mensal'!R$2,#REF!, "<"&EOMONTH('Faturado mensal'!R$2,0)) -> 0 | S31: =SUMIFS(#REF!,#REF!, $A31,#REF!, ">="&'Faturado mensal'!S$2,#REF!, "<"&EOMONTH('Faturado mensal'!S$2,0)) -> 0 | T31: =SUMIFS(#REF!,#REF!, $A31,#REF!, ">="&'Faturado mensal'!T$2,#REF!, "<"&EOMONTH('Faturado mensal'!T$2,0)) -> 0 | ... X31: =SUMIFS(#REF!,#REF!, $A31,#REF!, ">="&'Faturado mensal'!X$2,#REF!, "<"&EOMONTH('Faturado mensal'!X$2,0)) -> 0 | Y31: =SUMIFS(#REF!,#REF!, $A31,#REF!, ">="&'Faturado mensal'!M$2,#REF!, "<"&EOMONTH('Faturado mensal'!M$2,12)) -> 0 | Z31: =SUMIFS(#REF!,#REF!, $A31,#REF!, ">="&'Faturado mensal'!Z$2,#REF!, "<"&EOMONTH('Faturado mensal'!Z$2,0)) -> 0 | AA31: =SUMIFS(#REF!,#REF!, $A31,#REF!, ">="&'Faturado mensal'!AA$2,#REF!, "<"&EOMONTH('Faturado mensal'!AA$2,0)) -> 0 | AB31: =SUMIFS(#REF!,#REF!, $A31,#REF!, ">="&'Faturado mensal'!AB$2,#REF!, "<"&EOMONTH('Faturado mensal'!AB$2,0)) -> 0 | AC31: =SUMIFS(#REF!,#REF!, $A31,#REF!, ">="&'Faturado mensal'!AC$2,#REF!, "<"&EOMONTH('Faturado mensal'!AC$2,0)) -> 0 | AD31: =SUMIFS(#REF!,#REF!, $A31,#REF!, ">="&'Faturado mensal'!AD$2,#REF!, "<"&EOMONTH('Faturado mensal'!AD$2,0)) -> 0 | AE31: =SUMIFS(#REF!,#REF!, $A31,#REF!, ">="&'Faturado mensal'!AE$2,#REF!, "<"&EOMONTH('Faturado mensal'!AE$2,0)) -> 0 | AF31: =SUMIFS(#REF!,#REF!, $A31,#REF!, ">="&'Faturado mensal'!AF$2,#REF!, "<"&EOMONTH('Faturado mensal'!AF$2,0)) -> 0 | AG31: =SUMIFS(#REF!,#REF!, $A31,#REF!, ">="&'Faturado mensal'!AG$2,#REF!, "<"&EOMONTH('Faturado mensal'!AG$2,0)) -> 0 | ... AK31: =SUMIFS(#REF!,#REF!, $A31,#REF!, ">="&'Faturado mensal'!AK$2,#REF!, "<"&EOMONTH('Faturado mensal'!AK$2,0)) -> 0 | AL31: =SUMIFS(#REF!,#REF!, $A31,#REF!, ">="&Z$2,#REF!, "<"&EOMONTH(AK$2,0)) -> 0
A32: CS0000719 | B32: 070000629 | C32: EXCEL SERV. EM METROLOGIA LTDA | D32: Ativo | E32: QSMA | F32: SERVIÇOS PRESTADOS | G32: INDUSTRIAL CO | H32: C | I32: EXCEL SERV. EM METROLOGIA LTDA | J32: 30 DIAS | K32: COFAB | L32: PRGM . COMPRAS - CO - FABRICA | M32: =SUMIFS(#REF!,#REF!, $A32,#REF!, ">="&'Faturado mensal'!M$2,#REF!, "<"&EOMONTH('Faturado mensal'!M$2,0)) -> 0 | N32: =SUMIFS(#REF!,#REF!, $A32,#REF!, ">="&'Faturado mensal'!N$2,#REF!, "<"&EOMONTH('Faturado mensal'!N$2,0)) -> 9950.37 | O32: =SUMIFS(#REF!,#REF!, $A32,#REF!, ">="&'Faturado mensal'!O$2,#REF!, "<"&EOMONTH('Faturado mensal'!O$2,0)) -> 874.4 | P32: =SUMIFS(#REF!,#REF!, $A32,#REF!, ">="&'Faturado mensal'!P$2,#REF!, "<"&EOMONTH('Faturado mensal'!P$2,0)) -> 23.76 | Q32: =SUMIFS(#REF!,#REF!, $A32,#REF!, ">="&'Faturado mensal'!Q$2,#REF!, "<"&EOMONTH('Faturado mensal'!Q$2,0)) -> 0 | R32: =SUMIFS(#REF!,#REF!, $A32,#REF!, ">="&'Faturado mensal'!R$2,#REF!, "<"&EOMONTH('Faturado mensal'!R$2,0)) -> 0 | S32: =SUMIFS(#REF!,#REF!, $A32,#REF!, ">="&'Faturado mensal'!S$2,#REF!, "<"&EOMONTH('Faturado mensal'!S$2,0)) -> 9852.32 | T32: =SUMIFS(#REF!,#REF!, $A32,#REF!, ">="&'Faturado mensal'!T$2,#REF!, "<"&EOMONTH('Faturado mensal'!T$2,0)) -> 952.6 | ... X32: =SUMIFS(#REF!,#REF!, $A32,#REF!, ">="&'Faturado mensal'!X$2,#REF!, "<"&EOMONTH('Faturado mensal'!X$2,0)) -> 0 | Y32: =SUMIFS(#REF!,#REF!, $A32,#REF!, ">="&'Faturado mensal'!M$2,#REF!, "<"&EOMONTH('Faturado mensal'!M$2,12)) -> 35384.78 | Z32: =SUMIFS(#REF!,#REF!, $A32,#REF!, ">="&'Faturado mensal'!Z$2,#REF!, "<"&EOMONTH('Faturado mensal'!Z$2,0)) -> 0 | AA32: =SUMIFS(#REF!,#REF!, $A32,#REF!, ">="&'Faturado mensal'!AA$2,#REF!, "<"&EOMONTH('Faturado mensal'!AA$2,0)) -> 0 | AB32: =SUMIFS(#REF!,#REF!, $A32,#REF!, ">="&'Faturado mensal'!AB$2,#REF!, "<"&EOMONTH('Faturado mensal'!AB$2,0)) -> 0 | AC32: =SUMIFS(#REF!,#REF!, $A32,#REF!, ">="&'Faturado mensal'!AC$2,#REF!, "<"&EOMONTH('Faturado mensal'!AC$2,0)) -> 0 | AD32: =SUMIFS(#REF!,#REF!, $A32,#REF!, ">="&'Faturado mensal'!AD$2,#REF!, "<"&EOMONTH('Faturado mensal'!AD$2,0)) -> 0 | AE32: =SUMIFS(#REF!,#REF!, $A32,#REF!, ">="&'Faturado mensal'!AE$2,#REF!, "<"&EOMONTH('Faturado mensal'!AE$2,0)) -> 1025.04 | AF32: =SUMIFS(#REF!,#REF!, $A32,#REF!, ">="&'Faturado mensal'!AF$2,#REF!, "<"&EOMONTH('Faturado mensal'!AF$2,0)) -> 0 | AG32: =SUMIFS(#REF!,#REF!, $A32,#REF!, ">="&'Faturado mensal'!AG$2,#REF!, "<"&EOMONTH('Faturado mensal'!AG$2,0)) -> 0 | ... AK32: =SUMIFS(#REF!,#REF!, $A32,#REF!, ">="&'Faturado mensal'!AK$2,#REF!, "<"&EOMONTH('Faturado mensal'!AK$2,0)) -> 0 | AL32: =SUMIFS(#REF!,#REF!, $A32,#REF!, ">="&Z$2,#REF!, "<"&EOMONTH(AK$2,0)) -> 1025.04
A33: CS0000721 | B33: 070089987 | C33: N.V.COM.DISTR.DE GAS LTDA-ME | D33: Concluído | G33: INDUSTRIAL CO | H33: C | I33: N.V.COM.DISTR.DE GAS LTDA-ME | J33: 30 DIAS | K33: COFAB | L33: PRGM . COMPRAS - CO - FABRICA | M33: =SUMIFS(#REF!,#REF!, $A33,#REF!, ">="&'Faturado mensal'!M$2,#REF!, "<"&EOMONTH('Faturado mensal'!M$2,0)) -> 0 | N33: =SUMIFS(#REF!,#REF!, $A33,#REF!, ">="&'Faturado mensal'!N$2,#REF!, "<"&EOMONTH('Faturado mensal'!N$2,0)) -> 0 | O33: =SUMIFS(#REF!,#REF!, $A33,#REF!, ">="&'Faturado mensal'!O$2,#REF!, "<"&EOMONTH('Faturado mensal'!O$2,0)) -> 0 | P33: =SUMIFS(#REF!,#REF!, $A33,#REF!, ">="&'Faturado mensal'!P$2,#REF!, "<"&EOMONTH('Faturado mensal'!P$2,0)) -> 0 | Q33: =SUMIFS(#REF!,#REF!, $A33,#REF!, ">="&'Faturado mensal'!Q$2,#REF!, "<"&EOMONTH('Faturado mensal'!Q$2,0)) -> 0 | R33: =SUMIFS(#REF!,#REF!, $A33,#REF!, ">="&'Faturado mensal'!R$2,#REF!, "<"&EOMONTH('Faturado mensal'!R$2,0)) -> 0 | S33: =SUMIFS(#REF!,#REF!, $A33,#REF!, ">="&'Faturado mensal'!S$2,#REF!, "<"&EOMONTH('Faturado mensal'!S$2,0)) -> 0 | T33: =SUMIFS(#REF!,#REF!, $A33,#REF!, ">="&'Faturado mensal'!T$2,#REF!, "<"&EOMONTH('Faturado mensal'!T$2,0)) -> 0 | ... X33: =SUMIFS(#REF!,#REF!, $A33,#REF!, ">="&'Faturado mensal'!X$2,#REF!, "<"&EOMONTH('Faturado mensal'!X$2,0)) -> 0 | Y33: =SUMIFS(#REF!,#REF!, $A33,#REF!, ">="&'Faturado mensal'!M$2,#REF!, "<"&EOMONTH('Faturado mensal'!M$2,12)) -> 0 | Z33: =SUMIFS(#REF!,#REF!, $A33,#REF!, ">="&'Faturado mensal'!Z$2,#REF!, "<"&EOMONTH('Faturado mensal'!Z$2,0)) -> 0 | AA33: =SUMIFS(#REF!,#REF!, $A33,#REF!, ">="&'Faturado mensal'!AA$2,#REF!, "<"&EOMONTH('Faturado mensal'!AA$2,0)) -> 0 | AB33: =SUMIFS(#REF!,#REF!, $A33,#REF!, ">="&'Faturado mensal'!AB$2,#REF!, "<"&EOMONTH('Faturado mensal'!AB$2,0)) -> 0 | AC33: =SUMIFS(#REF!,#REF!, $A33,#REF!, ">="&'Faturado mensal'!AC$2,#REF!, "<"&EOMONTH('Faturado mensal'!AC$2,0)) -> 0 | AD33: =SUMIFS(#REF!,#REF!, $A33,#REF!, ">="&'Faturado mensal'!AD$2,#REF!, "<"&EOMONTH('Faturado mensal'!AD$2,0)) -> 0 | AE33: =SUMIFS(#REF!,#REF!, $A33,#REF!, ">="&'Faturado mensal'!AE$2,#REF!, "<"&EOMONTH('Faturado mensal'!AE$2,0)) -> 0 | AF33: =SUMIFS(#REF!,#REF!, $A33,#REF!, ">="&'Faturado mensal'!AF$2,#REF!, "<"&EOMONTH('Faturado mensal'!AF$2,0)) -> 0 | AG33: =SUMIFS(#REF!,#REF!, $A33,#REF!, ">="&'Faturado mensal'!AG$2,#REF!, "<"&EOMONTH('Faturado mensal'!AG$2,0)) -> 0 | ... AK33: =SUMIFS(#REF!,#REF!, $A33,#REF!, ">="&'Faturado mensal'!AK$2,#REF!, "<"&EOMONTH('Faturado mensal'!AK$2,0)) -> 0 | AL33: =SUMIFS(#REF!,#REF!, $A33,#REF!, ">="&Z$2,#REF!, "<"&EOMONTH(AK$2,0)) -> 0
A34: CS0000725 | B34: 070001589 | C34: MARCOS AUGUSTO DO AMARAL | D34: Concluído | I34: MARCOS AUGUSTO DO AMARAL | J34: 30 DIAS | K34: SRSPDT | L34: COMPRAS - SRS - OC (IM)PRODUT | M34: =SUMIFS(#REF!,#REF!, $A34,#REF!, ">="&'Faturado mensal'!M$2,#REF!, "<"&EOMONTH('Faturado mensal'!M$2,0)) -> 0 | N34: =SUMIFS(#REF!,#REF!, $A34,#REF!, ">="&'Faturado mensal'!N$2,#REF!, "<"&EOMONTH('Faturado mensal'!N$2,0)) -> 0 | O34: =SUMIFS(#REF!,#REF!, $A34,#REF!, ">="&'Faturado mensal'!O$2,#REF!, "<"&EOMONTH('Faturado mensal'!O$2,0)) -> 0 | P34: =SUMIFS(#REF!,#REF!, $A34,#REF!, ">="&'Faturado mensal'!P$2,#REF!, "<"&EOMONTH('Faturado mensal'!P$2,0)) -> 0 | Q34: =SUMIFS(#REF!,#REF!, $A34,#REF!, ">="&'Faturado mensal'!Q$2,#REF!, "<"&EOMONTH('Faturado mensal'!Q$2,0)) -> 0 | R34: =SUMIFS(#REF!,#REF!, $A34,#REF!, ">="&'Faturado mensal'!R$2,#REF!, "<"&EOMONTH('Faturado mensal'!R$2,0)) -> 0 | S34: =SUMIFS(#REF!,#REF!, $A34,#REF!, ">="&'Faturado mensal'!S$2,#REF!, "<"&EOMONTH('Faturado mensal'!S$2,0)) -> 0 | T34: =SUMIFS(#REF!,#REF!, $A34,#REF!, ">="&'Faturado mensal'!T$2,#REF!, "<"&EOMONTH('Faturado mensal'!T$2,0)) -> 0 | ... X34: =SUMIFS(#REF!,#REF!, $A34,#REF!, ">="&'Faturado mensal'!X$2,#REF!, "<"&EOMONTH('Faturado mensal'!X$2,0)) -> 0 | Y34: =SUMIFS(#REF!,#REF!, $A34,#REF!, ">="&'Faturado mensal'!M$2,#REF!, "<"&EOMONTH('Faturado mensal'!M$2,12)) -> 0 | Z34: =SUMIFS(#REF!,#REF!, $A34,#REF!, ">="&'Faturado mensal'!Z$2,#REF!, "<"&EOMONTH('Faturado mensal'!Z$2,0)) -> 0 | AA34: =SUMIFS(#REF!,#REF!, $A34,#REF!, ">="&'Faturado mensal'!AA$2,#REF!, "<"&EOMONTH('Faturado mensal'!AA$2,0)) -> 0 | AB34: =SUMIFS(#REF!,#REF!, $A34,#REF!, ">="&'Faturado mensal'!AB$2,#REF!, "<"&EOMONTH('Faturado mensal'!AB$2,0)) -> 0 | AC34: =SUMIFS(#REF!,#REF!, $A34,#REF!, ">="&'Faturado mensal'!AC$2,#REF!, "<"&EOMONTH('Faturado mensal'!AC$2,0)) -> 0 | AD34: =SUMIFS(#REF!,#REF!, $A34,#REF!, ">="&'Faturado mensal'!AD$2,#REF!, "<"&EOMONTH('Faturado mensal'!AD$2,0)) -> 0 | AE34: =SUMIFS(#REF!,#REF!, $A34,#REF!, ">="&'Faturado mensal'!AE$2,#REF!, "<"&EOMONTH('Faturado mensal'!AE$2,0)) -> 0 | AF34: =SUMIFS(#REF!,#REF!, $A34,#REF!, ">="&'Faturado mensal'!AF$2,#REF!, "<"&EOMONTH('Faturado mensal'!AF$2,0)) -> 0 | AG34: =SUMIFS(#REF!,#REF!, $A34,#REF!, ">="&'Faturado mensal'!AG$2,#REF!, "<"&EOMONTH('Faturado mensal'!AG$2,0)) -> 0 | ... AK34: =SUMIFS(#REF!,#REF!, $A34,#REF!, ">="&'Faturado mensal'!AK$2,#REF!, "<"&EOMONTH('Faturado mensal'!AK$2,0)) -> 0 | AL34: =SUMIFS(#REF!,#REF!, $A34,#REF!, ">="&Z$2,#REF!, "<"&EOMONTH(AK$2,0)) -> 0
A35: CS0000727 | B35: 070076216 | C35: PREMIER SISTEMA GEST.AMB.LTDA | D35: Concluído | G35: INDUSTRIAL SRS | H35: B | I35: PREMIER SISTEMA GEST.AMB.LTDA | J35: 30 DIAS | K35: SRSFAB | L35: PRGM . COMPRAS - SRS - FABRICA | M35: =SUMIFS(#REF!,#REF!, $A35,#REF!, ">="&'Faturado mensal'!M$2,#REF!, "<"&EOMONTH('Faturado mensal'!M$2,0)) -> 0 | N35: =SUMIFS(#REF!,#REF!, $A35,#REF!, ">="&'Faturado mensal'!N$2,#REF!, "<"&EOMONTH('Faturado mensal'!N$2,0)) -> 0 | O35: =SUMIFS(#REF!,#REF!, $A35,#REF!, ">="&'Faturado mensal'!O$2,#REF!, "<"&EOMONTH('Faturado mensal'!O$2,0)) -> 0 | P35: =SUMIFS(#REF!,#REF!, $A35,#REF!, ">="&'Faturado mensal'!P$2,#REF!, "<"&EOMONTH('Faturado mensal'!P$2,0)) -> 0 | Q35: =SUMIFS(#REF!,#REF!, $A35,#REF!, ">="&'Faturado mensal'!Q$2,#REF!, "<"&EOMONTH('Faturado mensal'!Q$2,0)) -> 0 | R35: =SUMIFS(#REF!,#REF!, $A35,#REF!, ">="&'Faturado mensal'!R$2,#REF!, "<"&EOMONTH('Faturado mensal'!R$2,0)) -> 0 | S35: =SUMIFS(#REF!,#REF!, $A35,#REF!, ">="&'Faturado mensal'!S$2,#REF!, "<"&EOMONTH('Faturado mensal'!S$2,0)) -> 0 | T35: =SUMIFS(#REF!,#REF!, $A35,#REF!, ">="&'Faturado mensal'!T$2,#REF!, "<"&EOMONTH('Faturado mensal'!T$2,0)) -> 0 | ... X35: =SUMIFS(#REF!,#REF!, $A35,#REF!, ">="&'Faturado mensal'!X$2,#REF!, "<"&EOMONTH('Faturado mensal'!X$2,0)) -> 0 | Y35: =SUMIFS(#REF!,#REF!, $A35,#REF!, ">="&'Faturado mensal'!M$2,#REF!, "<"&EOMONTH('Faturado mensal'!M$2,12)) -> 0 | Z35: =SUMIFS(#REF!,#REF!, $A35,#REF!, ">="&'Faturado mensal'!Z$2,#REF!, "<"&EOMONTH('Faturado mensal'!Z$2,0)) -> 0 | AA35: =SUMIFS(#REF!,#REF!, $A35,#REF!, ">="&'Faturado mensal'!AA$2,#REF!, "<"&EOMONTH('Faturado mensal'!AA$2,0)) -> 0 | AB35: =SUMIFS(#REF!,#REF!, $A35,#REF!, ">="&'Faturado mensal'!AB$2,#REF!, "<"&EOMONTH('Faturado mensal'!AB$2,0)) -> 0 | AC35: =SUMIFS(#REF!,#REF!, $A35,#REF!, ">="&'Faturado mensal'!AC$2,#REF!, "<"&EOMONTH('Faturado mensal'!AC$2,0)) -> 0 | AD35: =SUMIFS(#REF!,#REF!, $A35,#REF!, ">="&'Faturado mensal'!AD$2,#REF!, "<"&EOMONTH('Faturado mensal'!AD$2,0)) -> 0 | AE35: =SUMIFS(#REF!,#REF!, $A35,#REF!, ">="&'Faturado mensal'!AE$2,#REF!, "<"&EOMONTH('Faturado mensal'!AE$2,0)) -> 0 | AF35: =SUMIFS(#REF!,#REF!, $A35,#REF!, ">="&'Faturado mensal'!AF$2,#REF!, "<"&EOMONTH('Faturado mensal'!AF$2,0)) -> 0 | AG35: =SUMIFS(#REF!,#REF!, $A35,#REF!, ">="&'Faturado mensal'!AG$2,#REF!, "<"&EOMONTH('Faturado mensal'!AG$2,0)) -> 0 | ... AK35: =SUMIFS(#REF!,#REF!, $A35,#REF!, ">="&'Faturado mensal'!AK$2,#REF!, "<"&EOMONTH('Faturado mensal'!AK$2,0)) -> 0 | AL35: =SUMIFS(#REF!,#REF!, $A35,#REF!, ">="&Z$2,#REF!, "<"&EOMONTH(AK$2,0)) -> 0
A36: CS0000728 | B36: 070000629 | C36: EXCEL SERV. EM METROLOGIA LTDA | D36: Ativo | E36: QSMA | F36: SERVIÇOS PRESTADOS | G36: INDUSTRIAL SRS | H36: C | I36: EXCEL SERV. EM METROLOGIA LTDA | J36: 30 DIAS | K36: SRSFAB | L36: PRGM . COMPRAS - SRS - FABRICA | M36: =SUMIFS(#REF!,#REF!, $A36,#REF!, ">="&'Faturado mensal'!M$2,#REF!, "<"&EOMONTH('Faturado mensal'!M$2,0)) -> 0 | N36: =SUMIFS(#REF!,#REF!, $A36,#REF!, ">="&'Faturado mensal'!N$2,#REF!, "<"&EOMONTH('Faturado mensal'!N$2,0)) -> 0 | O36: =SUMIFS(#REF!,#REF!, $A36,#REF!, ">="&'Faturado mensal'!O$2,#REF!, "<"&EOMONTH('Faturado mensal'!O$2,0)) -> 13847.93 | P36: =SUMIFS(#REF!,#REF!, $A36,#REF!, ">="&'Faturado mensal'!P$2,#REF!, "<"&EOMONTH('Faturado mensal'!P$2,0)) -> 12326.81 | Q36: =SUMIFS(#REF!,#REF!, $A36,#REF!, ">="&'Faturado mensal'!Q$2,#REF!, "<"&EOMONTH('Faturado mensal'!Q$2,0)) -> 0 | R36: =SUMIFS(#REF!,#REF!, $A36,#REF!, ">="&'Faturado mensal'!R$2,#REF!, "<"&EOMONTH('Faturado mensal'!R$2,0)) -> 4783.17 | S36: =SUMIFS(#REF!,#REF!, $A36,#REF!, ">="&'Faturado mensal'!S$2,#REF!, "<"&EOMONTH('Faturado mensal'!S$2,0)) -> 5720.6 | T36: =SUMIFS(#REF!,#REF!, $A36,#REF!, ">="&'Faturado mensal'!T$2,#REF!, "<"&EOMONTH('Faturado mensal'!T$2,0)) -> 0 | ... X36: =SUMIFS(#REF!,#REF!, $A36,#REF!, ">="&'Faturado mensal'!X$2,#REF!, "<"&EOMONTH('Faturado mensal'!X$2,0)) -> 20549.64 | Y36: =SUMIFS(#REF!,#REF!, $A36,#REF!, ">="&'Faturado mensal'!M$2,#REF!, "<"&EOMONTH('Faturado mensal'!M$2,12)) -> 75462.98 | Z36: =SUMIFS(#REF!,#REF!, $A36,#REF!, ">="&'Faturado mensal'!Z$2,#REF!, "<"&EOMONTH('Faturado mensal'!Z$2,0)) -> 5858.29 | AA36: =SUMIFS(#REF!,#REF!, $A36,#REF!, ">="&'Faturado mensal'!AA$2,#REF!, "<"&EOMONTH('Faturado mensal'!AA$2,0)) -> 0 | AB36: =SUMIFS(#REF!,#REF!, $A36,#REF!, ">="&'Faturado mensal'!AB$2,#REF!, "<"&EOMONTH('Faturado mensal'!AB$2,0)) -> 0 | AC36: =SUMIFS(#REF!,#REF!, $A36,#REF!, ">="&'Faturado mensal'!AC$2,#REF!, "<"&EOMONTH('Faturado mensal'!AC$2,0)) -> 1535.62 | AD36: =SUMIFS(#REF!,#REF!, $A36,#REF!, ">="&'Faturado mensal'!AD$2,#REF!, "<"&EOMONTH('Faturado mensal'!AD$2,0)) -> 0 | AE36: =SUMIFS(#REF!,#REF!, $A36,#REF!, ">="&'Faturado mensal'!AE$2,#REF!, "<"&EOMONTH('Faturado mensal'!AE$2,0)) -> 22653.18 | AF36: =SUMIFS(#REF!,#REF!, $A36,#REF!, ">="&'Faturado mensal'!AF$2,#REF!, "<"&EOMONTH('Faturado mensal'!AF$2,0)) -> 0 | AG36: =SUMIFS(#REF!,#REF!, $A36,#REF!, ">="&'Faturado mensal'!AG$2,#REF!, "<"&EOMONTH('Faturado mensal'!AG$2,0)) -> 0 | ... AK36: =SUMIFS(#REF!,#REF!, $A36,#REF!, ">="&'Faturado mensal'!AK$2,#REF!, "<"&EOMONTH('Faturado mensal'!AK$2,0)) -> 0 | AL36: =SUMIFS(#REF!,#REF!, $A36,#REF!, ">="&Z$2,#REF!, "<"&EOMONTH(AK$2,0)) -> 30047.09
A37: CS0000731 | B37: 070000748 | C37: ALSCO TOALHEIRO BRASIL LTDA | D37: Ativo | E37: MANUFATURA VIES | F37: LOCAÇÕES EQUIPAMENTOS / VEÍCULOS | G37: INDUSTRIAL VIES | H37: B | I37: ALSCO TOALHEIRO BRASIL LTDA | J37: 30 DIAS | K37: VIESFB | L37: PRGM .COMPRAS - VIES - FABRICA | M37: =SUMIFS(#REF!,#REF!, $A37,#REF!, ">="&'Faturado mensal'!M$2,#REF!, "<"&EOMONTH('Faturado mensal'!M$2,0)) -> 488.4 | N37: =SUMIFS(#REF!,#REF!, $A37,#REF!, ">="&'Faturado mensal'!N$2,#REF!, "<"&EOMONTH('Faturado mensal'!N$2,0)) -> 488.4 | O37: =SUMIFS(#REF!,#REF!, $A37,#REF!, ">="&'Faturado mensal'!O$2,#REF!, "<"&EOMONTH('Faturado mensal'!O$2,0)) -> 488.4 | P37: =SUMIFS(#REF!,#REF!, $A37,#REF!, ">="&'Faturado mensal'!P$2,#REF!, "<"&EOMONTH('Faturado mensal'!P$2,0)) -> 488.4 | Q37: =SUMIFS(#REF!,#REF!, $A37,#REF!, ">="&'Faturado mensal'!Q$2,#REF!, "<"&EOMONTH('Faturado mensal'!Q$2,0)) -> 488.4 | R37: =SUMIFS(#REF!,#REF!, $A37,#REF!, ">="&'Faturado mensal'!R$2,#REF!, "<"&EOMONTH('Faturado mensal'!R$2,0)) -> 488.4 | S37: =SUMIFS(#REF!,#REF!, $A37,#REF!, ">="&'Faturado mensal'!S$2,#REF!, "<"&EOMONTH('Faturado mensal'!S$2,0)) -> 488.4 | T37: =SUMIFS(#REF!,#REF!, $A37,#REF!, ">="&'Faturado mensal'!T$2,#REF!, "<"&EOMONTH('Faturado mensal'!T$2,0)) -> 488.4 | ... X37: =SUMIFS(#REF!,#REF!, $A37,#REF!, ">="&'Faturado mensal'!X$2,#REF!, "<"&EOMONTH('Faturado mensal'!X$2,0)) -> 573.72 | Y37: =SUMIFS(#REF!,#REF!, $A37,#REF!, ">="&'Faturado mensal'!M$2,#REF!, "<"&EOMONTH('Faturado mensal'!M$2,12)) -> 6775.8 | Z37: =SUMIFS(#REF!,#REF!, $A37,#REF!, ">="&'Faturado mensal'!Z$2,#REF!, "<"&EOMONTH('Faturado mensal'!Z$2,0)) -> 573.72 | AA37: =SUMIFS(#REF!,#REF!, $A37,#REF!, ">="&'Faturado mensal'!AA$2,#REF!, "<"&EOMONTH('Faturado mensal'!AA$2,0)) -> 573.72 | AB37: =SUMIFS(#REF!,#REF!, $A37,#REF!, ">="&'Faturado mensal'!AB$2,#REF!, "<"&EOMONTH('Faturado mensal'!AB$2,0)) -> 573.72 | AC37: =SUMIFS(#REF!,#REF!, $A37,#REF!, ">="&'Faturado mensal'!AC$2,#REF!, "<"&EOMONTH('Faturado mensal'!AC$2,0)) -> 573.72 | AD37: =SUMIFS(#REF!,#REF!, $A37,#REF!, ">="&'Faturado mensal'!AD$2,#REF!, "<"&EOMONTH('Faturado mensal'!AD$2,0)) -> 573.72 | AE37: =SUMIFS(#REF!,#REF!, $A37,#REF!, ">="&'Faturado mensal'!AE$2,#REF!, "<"&EOMONTH('Faturado mensal'!AE$2,0)) -> 573.72 | AF37: =SUMIFS(#REF!,#REF!, $A37,#REF!, ">="&'Faturado mensal'!AF$2,#REF!, "<"&EOMONTH('Faturado mensal'!AF$2,0)) -> 0 | AG37: =SUMIFS(#REF!,#REF!, $A37,#REF!, ">="&'Faturado mensal'!AG$2,#REF!, "<"&EOMONTH('Faturado mensal'!AG$2,0)) -> 0 | ... AK37: =SUMIFS(#REF!,#REF!, $A37,#REF!, ">="&'Faturado mensal'!AK$2,#REF!, "<"&EOMONTH('Faturado mensal'!AK$2,0)) -> 0 | AL37: =SUMIFS(#REF!,#REF!, $A37,#REF!, ">="&Z$2,#REF!, "<"&EOMONTH(AK$2,0)) -> 3442.32
A38: CS0000735 | B38: 090003569 | C38: ELEVADORES OTIS LTDA | D38: Ativo | E38: MANUFATURA VIES | F38: MANUTENÇÃO EDIFÍCIOS / INSTALAÇÕES | G38: INDUSTRIAL VIES | H38: C | I38: ELEVADORES OTIS LTDA | J38: 15 DIAS | K38: VIESFB | L38: PRGM .COMPRAS - VIES - FABRICA | M38: =SUMIFS(#REF!,#REF!, $A38,#REF!, ">="&'Faturado mensal'!M$2,#REF!, "<"&EOMONTH('Faturado mensal'!M$2,0)) -> 591.63 | N38: =SUMIFS(#REF!,#REF!, $A38,#REF!, ">="&'Faturado mensal'!N$2,#REF!, "<"&EOMONTH('Faturado mensal'!N$2,0)) -> 591.63 | O38: =SUMIFS(#REF!,#REF!, $A38,#REF!, ">="&'Faturado mensal'!O$2,#REF!, "<"&EOMONTH('Faturado mensal'!O$2,0)) -> 643.59 | P38: =SUMIFS(#REF!,#REF!, $A38,#REF!, ">="&'Faturado mensal'!P$2,#REF!, "<"&EOMONTH('Faturado mensal'!P$2,0)) -> 643.59 | Q38: =SUMIFS(#REF!,#REF!, $A38,#REF!, ">="&'Faturado mensal'!Q$2,#REF!, "<"&EOMONTH('Faturado mensal'!Q$2,0)) -> 643.59 | R38: =SUMIFS(#REF!,#REF!, $A38,#REF!, ">="&'Faturado mensal'!R$2,#REF!, "<"&EOMONTH('Faturado mensal'!R$2,0)) -> 643.59 | S38: =SUMIFS(#REF!,#REF!, $A38,#REF!, ">="&'Faturado mensal'!S$2,#REF!, "<"&EOMONTH('Faturado mensal'!S$2,0)) -> 643.59 | T38: =SUMIFS(#REF!,#REF!, $A38,#REF!, ">="&'Faturado mensal'!T$2,#REF!, "<"&EOMONTH('Faturado mensal'!T$2,0)) -> 643.59 | ... X38: =SUMIFS(#REF!,#REF!, $A38,#REF!, ">="&'Faturado mensal'!X$2,#REF!, "<"&EOMONTH('Faturado mensal'!X$2,0)) -> 643.59 | Y38: =SUMIFS(#REF!,#REF!, $A38,#REF!, ">="&'Faturado mensal'!M$2,#REF!, "<"&EOMONTH('Faturado mensal'!M$2,12)) -> 8262.75 | Z38: =SUMIFS(#REF!,#REF!, $A38,#REF!, ">="&'Faturado mensal'!Z$2,#REF!, "<"&EOMONTH('Faturado mensal'!Z$2,0)) -> 643.59 | AA38: =SUMIFS(#REF!,#REF!, $A38,#REF!, ">="&'Faturado mensal'!AA$2,#REF!, "<"&EOMONTH('Faturado mensal'!AA$2,0)) -> 643.59 | AB38: =SUMIFS(#REF!,#REF!, $A38,#REF!, ">="&'Faturado mensal'!AB$2,#REF!, "<"&EOMONTH('Faturado mensal'!AB$2,0)) -> 0 | AC38: =SUMIFS(#REF!,#REF!, $A38,#REF!, ">="&'Faturado mensal'!AC$2,#REF!, "<"&EOMONTH('Faturado mensal'!AC$2,0)) -> 1287.18 | AD38: =SUMIFS(#REF!,#REF!, $A38,#REF!, ">="&'Faturado mensal'!AD$2,#REF!, "<"&EOMONTH('Faturado mensal'!AD$2,0)) -> 643.59 | AE38: =SUMIFS(#REF!,#REF!, $A38,#REF!, ">="&'Faturado mensal'!AE$2,#REF!, "<"&EOMONTH('Faturado mensal'!AE$2,0)) -> 643.59 | AF38: =SUMIFS(#REF!,#REF!, $A38,#REF!, ">="&'Faturado mensal'!AF$2,#REF!, "<"&EOMONTH('Faturado mensal'!AF$2,0)) -> 0 | AG38: =SUMIFS(#REF!,#REF!, $A38,#REF!, ">="&'Faturado mensal'!AG$2,#REF!, "<"&EOMONTH('Faturado mensal'!AG$2,0)) -> 0 | ... AK38: =SUMIFS(#REF!,#REF!, $A38,#REF!, ">="&'Faturado mensal'!AK$2,#REF!, "<"&EOMONTH('Faturado mensal'!AK$2,0)) -> 0 | AL38: =SUMIFS(#REF!,#REF!, $A38,#REF!, ">="&Z$2,#REF!, "<"&EOMONTH(AK$2,0)) -> 3861.54
A39: CS0000740 | B39: 070076409 | C39: UNIT SERVIOS ESP.SEGURANA LTDA | D39: Ativo | E39: SEGURANÇA PATRIMONIAL | F39: VIGILANCIA/PORTARIA | G39: SUPPLY | H39: B | I39: UNIT SERVIOS ESP.SEGURANA LTDA | J39: 15 DIAS | K39: VIESAD | L39: COMPRAS - VIES - ADMINISTRAÇAO | M39: =SUMIFS(#REF!,#REF!, $A39,#REF!, ">="&'Faturado mensal'!M$2,#REF!, "<"&EOMONTH('Faturado mensal'!M$2,0)) -> 18900 | N39: =SUMIFS(#REF!,#REF!, $A39,#REF!, ">="&'Faturado mensal'!N$2,#REF!, "<"&EOMONTH('Faturado mensal'!N$2,0)) -> 18900 | O39: =SUMIFS(#REF!,#REF!, $A39,#REF!, ">="&'Faturado mensal'!O$2,#REF!, "<"&EOMONTH('Faturado mensal'!O$2,0)) -> 18900 | P39: =SUMIFS(#REF!,#REF!, $A39,#REF!, ">="&'Faturado mensal'!P$2,#REF!, "<"&EOMONTH('Faturado mensal'!P$2,0)) -> 18900 | Q39: =SUMIFS(#REF!,#REF!, $A39,#REF!, ">="&'Faturado mensal'!Q$2,#REF!, "<"&EOMONTH('Faturado mensal'!Q$2,0)) -> 18900 | R39: =SUMIFS(#REF!,#REF!, $A39,#REF!, ">="&'Faturado mensal'!R$2,#REF!, "<"&EOMONTH('Faturado mensal'!R$2,0)) -> 18900 | S39: =SUMIFS(#REF!,#REF!, $A39,#REF!, ">="&'Faturado mensal'!S$2,#REF!, "<"&EOMONTH('Faturado mensal'!S$2,0)) -> 18900 | T39: =SUMIFS(#REF!,#REF!, $A39,#REF!, ">="&'Faturado mensal'!T$2,#REF!, "<"&EOMONTH('Faturado mensal'!T$2,0)) -> 18900 | ... X39: =SUMIFS(#REF!,#REF!, $A39,#REF!, ">="&'Faturado mensal'!X$2,#REF!, "<"&EOMONTH('Faturado mensal'!X$2,0)) -> 18900 | Y39: =SUMIFS(#REF!,#REF!, $A39,#REF!, ">="&'Faturado mensal'!M$2,#REF!, "<"&EOMONTH('Faturado mensal'!M$2,12)) -> 245700 | Z39: =SUMIFS(#REF!,#REF!, $A39,#REF!, ">="&'Faturado mensal'!Z$2,#REF!, "<"&EOMONTH('Faturado mensal'!Z$2,0)) -> 18900 | AA39: =SUMIFS(#REF!,#REF!, $A39,#REF!, ">="&'Faturado mensal'!AA$2,#REF!, "<"&EOMONTH('Faturado mensal'!AA$2,0)) -> 20790 | AB39: =SUMIFS(#REF!,#REF!, $A39,#REF!, ">="&'Faturado mensal'!AB$2,#REF!, "<"&EOMONTH('Faturado mensal'!AB$2,0)) -> 20790 | AC39: =SUMIFS(#REF!,#REF!, $A39,#REF!, ">="&'Faturado mensal'!AC$2,#REF!, "<"&EOMONTH('Faturado mensal'!AC$2,0)) -> 20790 | AD39: =SUMIFS(#REF!,#REF!, $A39,#REF!, ">="&'Faturado mensal'!AD$2,#REF!, "<"&EOMONTH('Faturado mensal'!AD$2,0)) -> 20790 | AE39: =SUMIFS(#REF!,#REF!, $A39,#REF!, ">="&'Faturado mensal'!AE$2,#REF!, "<"&EOMONTH('Faturado mensal'!AE$2,0)) -> 20790 | AF39: =SUMIFS(#REF!,#REF!, $A39,#REF!, ">="&'Faturado mensal'!AF$2,#REF!, "<"&EOMONTH('Faturado mensal'!AF$2,0)) -> 0 | AG39: =SUMIFS(#REF!,#REF!, $A39,#REF!, ">="&'Faturado mensal'!AG$2,#REF!, "<"&EOMONTH('Faturado mensal'!AG$2,0)) -> 0 | ... AK39: =SUMIFS(#REF!,#REF!, $A39,#REF!, ">="&'Faturado mensal'!AK$2,#REF!, "<"&EOMONTH('Faturado mensal'!AK$2,0)) -> 0 | AL39: =SUMIFS(#REF!,#REF!, $A39,#REF!, ">="&Z$2,#REF!, "<"&EOMONTH(AK$2,0)) -> 122850
A40: CS0000741 | B40: 070076352 | C40: R&S MARKETING DIGITAL LTDA -ME | D40: Concluído | I40: R&S MARKETING DIGITAL LTDA -ME | J40: 30 DIAS | K40: VIESFB | L40: PRGM .COMPRAS - VIES - FABRICA | M40: =SUMIFS(#REF!,#REF!, $A40,#REF!, ">="&'Faturado mensal'!M$2,#REF!, "<"&EOMONTH('Faturado mensal'!M$2,0)) -> 0 | N40: =SUMIFS(#REF!,#REF!, $A40,#REF!, ">="&'Faturado mensal'!N$2,#REF!, "<"&EOMONTH('Faturado mensal'!N$2,0)) -> 0 | O40: =SUMIFS(#REF!,#REF!, $A40,#REF!, ">="&'Faturado mensal'!O$2,#REF!, "<"&EOMONTH('Faturado mensal'!O$2,0)) -> 0 | P40: =SUMIFS(#REF!,#REF!, $A40,#REF!, ">="&'Faturado mensal'!P$2,#REF!, "<"&EOMONTH('Faturado mensal'!P$2,0)) -> 0 | Q40: =SUMIFS(#REF!,#REF!, $A40,#REF!, ">="&'Faturado mensal'!Q$2,#REF!, "<"&EOMONTH('Faturado mensal'!Q$2,0)) -> 0 | R40: =SUMIFS(#REF!,#REF!, $A40,#REF!, ">="&'Faturado mensal'!R$2,#REF!, "<"&EOMONTH('Faturado mensal'!R$2,0)) -> 0 | S40: =SUMIFS(#REF!,#REF!, $A40,#REF!, ">="&'Faturado mensal'!S$2,#REF!, "<"&EOMONTH('Faturado mensal'!S$2,0)) -> 0 | T40: =SUMIFS(#REF!,#REF!, $A40,#REF!, ">="&'Faturado mensal'!T$2,#REF!, "<"&EOMONTH('Faturado mensal'!T$2,0)) -> 0 | ... X40: =SUMIFS(#REF!,#REF!, $A40,#REF!, ">="&'Faturado mensal'!X$2,#REF!, "<"&EOMONTH('Faturado mensal'!X$2,0)) -> 0 | Y40: =SUMIFS(#REF!,#REF!, $A40,#REF!, ">="&'Faturado mensal'!M$2,#REF!, "<"&EOMONTH('Faturado mensal'!M$2,12)) -> 0 | Z40: =SUMIFS(#REF!,#REF!, $A40,#REF!, ">="&'Faturado mensal'!Z$2,#REF!, "<"&EOMONTH('Faturado mensal'!Z$2,0)) -> 0 | AA40: =SUMIFS(#REF!,#REF!, $A40,#REF!, ">="&'Faturado mensal'!AA$2,#REF!, "<"&EOMONTH('Faturado mensal'!AA$2,0)) -> 0 | AB40: =SUMIFS(#REF!,#REF!, $A40,#REF!, ">="&'Faturado mensal'!AB$2,#REF!, "<"&EOMONTH('Faturado mensal'!AB$2,0)) -> 0 | AC40: =SUMIFS(#REF!,#REF!, $A40,#REF!, ">="&'Faturado mensal'!AC$2,#REF!, "<"&EOMONTH('Faturado mensal'!AC$2,0)) -> 0 | AD40: =SUMIFS(#REF!,#REF!, $A40,#REF!, ">="&'Faturado mensal'!AD$2,#REF!, "<"&EOMONTH('Faturado mensal'!AD$2,0)) -> 0 | AE40: =SUMIFS(#REF!,#REF!, $A40,#REF!, ">="&'Faturado mensal'!AE$2,#REF!, "<"&EOMONTH('Faturado mensal'!AE$2,0)) -> 0 | AF40: =SUMIFS(#REF!,#REF!, $A40,#REF!, ">="&'Faturado mensal'!AF$2,#REF!, "<"&EOMONTH('Faturado mensal'!AF$2,0)) -> 0 | AG40: =SUMIFS(#REF!,#REF!, $A40,#REF!, ">="&'Faturado mensal'!AG$2,#REF!, "<"&EOMONTH('Faturado mensal'!AG$2,0)) -> 0 | ... AK40: =SUMIFS(#REF!,#REF!, $A40,#REF!, ">="&'Faturado mensal'!AK$2,#REF!, "<"&EOMONTH('Faturado mensal'!AK$2,0)) -> 0 | AL40: =SUMIFS(#REF!,#REF!, $A40,#REF!, ">="&Z$2,#REF!, "<"&EOMONTH(AK$2,0)) -> 0
A41: CS0000744 | B41: 090020157 | C41: SERVICO SOCIAL DA INDUSTRIA | D41: Concluído | G41: INDUSTRIAL CO | H41: C | I41: SERVICO SOCIAL DA INDUSTRIA | J41: 30 DIAS | K41: COADM | L41: COMPRAS - CO - ADMINISTRAÇÃO | M41: =SUMIFS(#REF!,#REF!, $A41,#REF!, ">="&'Faturado mensal'!M$2,#REF!, "<"&EOMONTH('Faturado mensal'!M$2,0)) -> 0 | N41: =SUMIFS(#REF!,#REF!, $A41,#REF!, ">="&'Faturado mensal'!N$2,#REF!, "<"&EOMONTH('Faturado mensal'!N$2,0)) -> 0 | O41: =SUMIFS(#REF!,#REF!, $A41,#REF!, ">="&'Faturado mensal'!O$2,#REF!, "<"&EOMONTH('Faturado mensal'!O$2,0)) -> 0 | P41: =SUMIFS(#REF!,#REF!, $A41,#REF!, ">="&'Faturado mensal'!P$2,#REF!, "<"&EOMONTH('Faturado mensal'!P$2,0)) -> 0 | Q41: =SUMIFS(#REF!,#REF!, $A41,#REF!, ">="&'Faturado mensal'!Q$2,#REF!, "<"&EOMONTH('Faturado mensal'!Q$2,0)) -> 0 | R41: =SUMIFS(#REF!,#REF!, $A41,#REF!, ">="&'Faturado mensal'!R$2,#REF!, "<"&EOMONTH('Faturado mensal'!R$2,0)) -> 0 | S41: =SUMIFS(#REF!,#REF!, $A41,#REF!, ">="&'Faturado mensal'!S$2,#REF!, "<"&EOMONTH('Faturado mensal'!S$2,0)) -> 0 | T41: =SUMIFS(#REF!,#REF!, $A41,#REF!, ">="&'Faturado mensal'!T$2,#REF!, "<"&EOMONTH('Faturado mensal'!T$2,0)) -> 0 | ... X41: =SUMIFS(#REF!,#REF!, $A41,#REF!, ">="&'Faturado mensal'!X$2,#REF!, "<"&EOMONTH('Faturado mensal'!X$2,0)) -> 0 | Y41: =SUMIFS(#REF!,#REF!, $A41,#REF!, ">="&'Faturado mensal'!M$2,#REF!, "<"&EOMONTH('Faturado mensal'!M$2,12)) -> 0 | Z41: =SUMIFS(#REF!,#REF!, $A41,#REF!, ">="&'Faturado mensal'!Z$2,#REF!, "<"&EOMONTH('Faturado mensal'!Z$2,0)) -> 0 | AA41: =SUMIFS(#REF!,#REF!, $A41,#REF!, ">="&'Faturado mensal'!AA$2,#REF!, "<"&EOMONTH('Faturado mensal'!AA$2,0)) -> 0 | AB41: =SUMIFS(#REF!,#REF!, $A41,#REF!, ">="&'Faturado mensal'!AB$2,#REF!, "<"&EOMONTH('Faturado mensal'!AB$2,0)) -> 0 | AC41: =SUMIFS(#REF!,#REF!, $A41,#REF!, ">="&'Faturado mensal'!AC$2,#REF!, "<"&EOMONTH('Faturado mensal'!AC$2,0)) -> 0 | AD41: =SUMIFS(#REF!,#REF!, $A41,#REF!, ">="&'Faturado mensal'!AD$2,#REF!, "<"&EOMONTH('Faturado mensal'!AD$2,0)) -> 0 | AE41: =SUMIFS(#REF!,#REF!, $A41,#REF!, ">="&'Faturado mensal'!AE$2,#REF!, "<"&EOMONTH('Faturado mensal'!AE$2,0)) -> 0 | AF41: =SUMIFS(#REF!,#REF!, $A41,#REF!, ">="&'Faturado mensal'!AF$2,#REF!, "<"&EOMONTH('Faturado mensal'!AF$2,0)) -> 0 | AG41: =SUMIFS(#REF!,#REF!, $A41,#REF!, ">="&'Faturado mensal'!AG$2,#REF!, "<"&EOMONTH('Faturado mensal'!AG$2,0)) -> 0 | ... AK41: =SUMIFS(#REF!,#REF!, $A41,#REF!, ">="&'Faturado mensal'!AK$2,#REF!, "<"&EOMONTH('Faturado mensal'!AK$2,0)) -> 0 | AL41: =SUMIFS(#REF!,#REF!, $A41,#REF!, ">="&Z$2,#REF!, "<"&EOMONTH(AK$2,0)) -> 0
A42: CS0000745 | B42: 090020157 | C42: SERVICO SOCIAL DA INDUSTRIA | D42: Concluído | G42: INDUSTRIAL CO | H42: C | I42: SERVICO SOCIAL DA INDUSTRIA | J42: 30 DIAS | K42: COADM | L42: COMPRAS - CO - ADMINISTRAÇÃO | M42: =SUMIFS(#REF!,#REF!, $A42,#REF!, ">="&'Faturado mensal'!M$2,#REF!, "<"&EOMONTH('Faturado mensal'!M$2,0)) -> 0 | N42: =SUMIFS(#REF!,#REF!, $A42,#REF!, ">="&'Faturado mensal'!N$2,#REF!, "<"&EOMONTH('Faturado mensal'!N$2,0)) -> 0 | O42: =SUMIFS(#REF!,#REF!, $A42,#REF!, ">="&'Faturado mensal'!O$2,#REF!, "<"&EOMONTH('Faturado mensal'!O$2,0)) -> 0 | P42: =SUMIFS(#REF!,#REF!, $A42,#REF!, ">="&'Faturado mensal'!P$2,#REF!, "<"&EOMONTH('Faturado mensal'!P$2,0)) -> 0 | Q42: =SUMIFS(#REF!,#REF!, $A42,#REF!, ">="&'Faturado mensal'!Q$2,#REF!, "<"&EOMONTH('Faturado mensal'!Q$2,0)) -> 0 | R42: =SUMIFS(#REF!,#REF!, $A42,#REF!, ">="&'Faturado mensal'!R$2,#REF!, "<"&EOMONTH('Faturado mensal'!R$2,0)) -> 0 | S42: =SUMIFS(#REF!,#REF!, $A42,#REF!, ">="&'Faturado mensal'!S$2,#REF!, "<"&EOMONTH('Faturado mensal'!S$2,0)) -> 0 | T42: =SUMIFS(#REF!,#REF!, $A42,#REF!, ">="&'Faturado mensal'!T$2,#REF!, "<"&EOMONTH('Faturado mensal'!T$2,0)) -> 0 | ... X42: =SUMIFS(#REF!,#REF!, $A42,#REF!, ">="&'Faturado mensal'!X$2,#REF!, "<"&EOMONTH('Faturado mensal'!X$2,0)) -> 0 | Y42: =SUMIFS(#REF!,#REF!, $A42,#REF!, ">="&'Faturado mensal'!M$2,#REF!, "<"&EOMONTH('Faturado mensal'!M$2,12)) -> 0 | Z42: =SUMIFS(#REF!,#REF!, $A42,#REF!, ">="&'Faturado mensal'!Z$2,#REF!, "<"&EOMONTH('Faturado mensal'!Z$2,0)) -> 0 | AA42: =SUMIFS(#REF!,#REF!, $A42,#REF!, ">="&'Faturado mensal'!AA$2,#REF!, "<"&EOMONTH('Faturado mensal'!AA$2,0)) -> 0 | AB42: =SUMIFS(#REF!,#REF!, $A42,#REF!, ">="&'Faturado mensal'!AB$2,#REF!, "<"&EOMONTH('Faturado mensal'!AB$2,0)) -> 0 | AC42: =SUMIFS(#REF!,#REF!, $A42,#REF!, ">="&'Faturado mensal'!AC$2,#REF!, "<"&EOMONTH('Faturado mensal'!AC$2,0)) -> 0 | AD42: =SUMIFS(#REF!,#REF!, $A42,#REF!, ">="&'Faturado mensal'!AD$2,#REF!, "<"&EOMONTH('Faturado mensal'!AD$2,0)) -> 0 | AE42: =SUMIFS(#REF!,#REF!, $A42,#REF!, ">="&'Faturado mensal'!AE$2,#REF!, "<"&EOMONTH('Faturado mensal'!AE$2,0)) -> 0 | AF42: =SUMIFS(#REF!,#REF!, $A42,#REF!, ">="&'Faturado mensal'!AF$2,#REF!, "<"&EOMONTH('Faturado mensal'!AF$2,0)) -> 0 | AG42: =SUMIFS(#REF!,#REF!, $A42,#REF!, ">="&'Faturado mensal'!AG$2,#REF!, "<"&EOMONTH('Faturado mensal'!AG$2,0)) -> 0 | ... AK42: =SUMIFS(#REF!,#REF!, $A42,#REF!, ">="&'Faturado mensal'!AK$2,#REF!, "<"&EOMONTH('Faturado mensal'!AK$2,0)) -> 0 | AL42: =SUMIFS(#REF!,#REF!, $A42,#REF!, ">="&Z$2,#REF!, "<"&EOMONTH(AK$2,0)) -> 0
A43: CS0000748 | B43: 090090329 | C43: SCG ENG. CONSULTORIA LTDA | D43: Concluído | I43: SCG ENG. CONSULTORIA LTDA | J43: 30 DIAS | K43: SRSFAB | L43: PRGM . COMPRAS - SRS - FABRICA | M43: =SUMIFS(#REF!,#REF!, $A43,#REF!, ">="&'Faturado mensal'!M$2,#REF!, "<"&EOMONTH('Faturado mensal'!M$2,0)) -> 0 | N43: =SUMIFS(#REF!,#REF!, $A43,#REF!, ">="&'Faturado mensal'!N$2,#REF!, "<"&EOMONTH('Faturado mensal'!N$2,0)) -> 0 | O43: =SUMIFS(#REF!,#REF!, $A43,#REF!, ">="&'Faturado mensal'!O$2,#REF!, "<"&EOMONTH('Faturado mensal'!O$2,0)) -> 0 | P43: =SUMIFS(#REF!,#REF!, $A43,#REF!, ">="&'Faturado mensal'!P$2,#REF!, "<"&EOMONTH('Faturado mensal'!P$2,0)) -> 0 | Q43: =SUMIFS(#REF!,#REF!, $A43,#REF!, ">="&'Faturado mensal'!Q$2,#REF!, "<"&EOMONTH('Faturado mensal'!Q$2,0)) -> 0 | R43: =SUMIFS(#REF!,#REF!, $A43,#REF!, ">="&'Faturado mensal'!R$2,#REF!, "<"&EOMONTH('Faturado mensal'!R$2,0)) -> 0 | S43: =SUMIFS(#REF!,#REF!, $A43,#REF!, ">="&'Faturado mensal'!S$2,#REF!, "<"&EOMONTH('Faturado mensal'!S$2,0)) -> 0 | T43: =SUMIFS(#REF!,#REF!, $A43,#REF!, ">="&'Faturado mensal'!T$2,#REF!, "<"&EOMONTH('Faturado mensal'!T$2,0)) -> 0 | ... X43: =SUMIFS(#REF!,#REF!, $A43,#REF!, ">="&'Faturado mensal'!X$2,#REF!, "<"&EOMONTH('Faturado mensal'!X$2,0)) -> 0 | Y43: =SUMIFS(#REF!,#REF!, $A43,#REF!, ">="&'Faturado mensal'!M$2,#REF!, "<"&EOMONTH('Faturado mensal'!M$2,12)) -> 0 | Z43: =SUMIFS(#REF!,#REF!, $A43,#REF!, ">="&'Faturado mensal'!Z$2,#REF!, "<"&EOMONTH('Faturado mensal'!Z$2,0)) -> 0 | AA43: =SUMIFS(#REF!,#REF!, $A43,#REF!, ">="&'Faturado mensal'!AA$2,#REF!, "<"&EOMONTH('Faturado mensal'!AA$2,0)) -> 0 | AB43: =SUMIFS(#REF!,#REF!, $A43,#REF!, ">="&'Faturado mensal'!AB$2,#REF!, "<"&EOMONTH('Faturado mensal'!AB$2,0)) -> 0 | AC43: =SUMIFS(#REF!,#REF!, $A43,#REF!, ">="&'Faturado mensal'!AC$2,#REF!, "<"&EOMONTH('Faturado mensal'!AC$2,0)) -> 0 | AD43: =SUMIFS(#REF!,#REF!, $A43,#REF!, ">="&'Faturado mensal'!AD$2,#REF!, "<"&EOMONTH('Faturado mensal'!AD$2,0)) -> 0 | AE43: =SUMIFS(#REF!,#REF!, $A43,#REF!, ">="&'Faturado mensal'!AE$2,#REF!, "<"&EOMONTH('Faturado mensal'!AE$2,0)) -> 0 | AF43: =SUMIFS(#REF!,#REF!, $A43,#REF!, ">="&'Faturado mensal'!AF$2,#REF!, "<"&EOMONTH('Faturado mensal'!AF$2,0)) -> 0 | AG43: =SUMIFS(#REF!,#REF!, $A43,#REF!, ">="&'Faturado mensal'!AG$2,#REF!, "<"&EOMONTH('Faturado mensal'!AG$2,0)) -> 0 | ... AK43: =SUMIFS(#REF!,#REF!, $A43,#REF!, ">="&'Faturado mensal'!AK$2,#REF!, "<"&EOMONTH('Faturado mensal'!AK$2,0)) -> 0 | AL43: =SUMIFS(#REF!,#REF!, $A43,#REF!, ">="&Z$2,#REF!, "<"&EOMONTH(AK$2,0)) -> 0
A44: CS0000749 | B44: 090010238 | C44: RIVITTI E DIAS SOCIAD DE ADVOG | D44: Ativo | E44: JURIDICO | F44: SERVIÇOS JURIDICOS | G44: INDUSTRIAL SRS | H44: C | I44: RIVITTI E DIAS SOCIAD DE ADVOG | J44: 30 DIAS | K44: SRSFAB | L44: PRGM . COMPRAS - SRS - FABRICA | M44: =SUMIFS(#REF!,#REF!, $A44,#REF!, ">="&'Faturado mensal'!M$2,#REF!, "<"&EOMONTH('Faturado mensal'!M$2,0)) -> 0 | N44: =SUMIFS(#REF!,#REF!, $A44,#REF!, ">="&'Faturado mensal'!N$2,#REF!, "<"&EOMONTH('Faturado mensal'!N$2,0)) -> 0 | O44: =SUMIFS(#REF!,#REF!, $A44,#REF!, ">="&'Faturado mensal'!O$2,#REF!, "<"&EOMONTH('Faturado mensal'!O$2,0)) -> 0 | P44: =SUMIFS(#REF!,#REF!, $A44,#REF!, ">="&'Faturado mensal'!P$2,#REF!, "<"&EOMONTH('Faturado mensal'!P$2,0)) -> 0 | Q44: =SUMIFS(#REF!,#REF!, $A44,#REF!, ">="&'Faturado mensal'!Q$2,#REF!, "<"&EOMONTH('Faturado mensal'!Q$2,0)) -> 0 | R44: =SUMIFS(#REF!,#REF!, $A44,#REF!, ">="&'Faturado mensal'!R$2,#REF!, "<"&EOMONTH('Faturado mensal'!R$2,0)) -> 0 | S44: =SUMIFS(#REF!,#REF!, $A44,#REF!, ">="&'Faturado mensal'!S$2,#REF!, "<"&EOMONTH('Faturado mensal'!S$2,0)) -> 0 | T44: =SUMIFS(#REF!,#REF!, $A44,#REF!, ">="&'Faturado mensal'!T$2,#REF!, "<"&EOMONTH('Faturado mensal'!T$2,0)) -> 0 | ... X44: =SUMIFS(#REF!,#REF!, $A44,#REF!, ">="&'Faturado mensal'!X$2,#REF!, "<"&EOMONTH('Faturado mensal'!X$2,0)) -> 0 | Y44: =SUMIFS(#REF!,#REF!, $A44,#REF!, ">="&'Faturado mensal'!M$2,#REF!, "<"&EOMONTH('Faturado mensal'!M$2,12)) -> 0 | Z44: =SUMIFS(#REF!,#REF!, $A44,#REF!, ">="&'Faturado mensal'!Z$2,#REF!, "<"&EOMONTH('Faturado mensal'!Z$2,0)) -> 0 | AA44: =SUMIFS(#REF!,#REF!, $A44,#REF!, ">="&'Faturado mensal'!AA$2,#REF!, "<"&EOMONTH('Faturado mensal'!AA$2,0)) -> 0 | AB44: =SUMIFS(#REF!,#REF!, $A44,#REF!, ">="&'Faturado mensal'!AB$2,#REF!, "<"&EOMONTH('Faturado mensal'!AB$2,0)) -> 0 | AC44: =SUMIFS(#REF!,#REF!, $A44,#REF!, ">="&'Faturado mensal'!AC$2,#REF!, "<"&EOMONTH('Faturado mensal'!AC$2,0)) -> 0 | AD44: =SUMIFS(#REF!,#REF!, $A44,#REF!, ">="&'Faturado mensal'!AD$2,#REF!, "<"&EOMONTH('Faturado mensal'!AD$2,0)) -> 0 | AE44: =SUMIFS(#REF!,#REF!, $A44,#REF!, ">="&'Faturado mensal'!AE$2,#REF!, "<"&EOMONTH('Faturado mensal'!AE$2,0)) -> 0 | AF44: =SUMIFS(#REF!,#REF!, $A44,#REF!, ">="&'Faturado mensal'!AF$2,#REF!, "<"&EOMONTH('Faturado mensal'!AF$2,0)) -> 0 | AG44: =SUMIFS(#REF!,#REF!, $A44,#REF!, ">="&'Faturado mensal'!AG$2,#REF!, "<"&EOMONTH('Faturado mensal'!AG$2,0)) -> 0 | ... AK44: =SUMIFS(#REF!,#REF!, $A44,#REF!, ">="&'Faturado mensal'!AK$2,#REF!, "<"&EOMONTH('Faturado mensal'!AK$2,0)) -> 0 | AL44: =SUMIFS(#REF!,#REF!, $A44,#REF!, ">="&Z$2,#REF!, "<"&EOMONTH(AK$2,0)) -> 0
A45: CS0000750 | B45: 070076328 | C45: EFIX LTDA | D45: Concluído | I45: EFIX LTDA | J45: 30 DIAS | K45: SRSFAB | L45: PRGM . COMPRAS - SRS - FABRICA | M45: =SUMIFS(#REF!,#REF!, $A45,#REF!, ">="&'Faturado mensal'!M$2,#REF!, "<"&EOMONTH('Faturado mensal'!M$2,0)) -> 0 | N45: =SUMIFS(#REF!,#REF!, $A45,#REF!, ">="&'Faturado mensal'!N$2,#REF!, "<"&EOMONTH('Faturado mensal'!N$2,0)) -> 0 | O45: =SUMIFS(#REF!,#REF!, $A45,#REF!, ">="&'Faturado mensal'!O$2,#REF!, "<"&EOMONTH('Faturado mensal'!O$2,0)) -> 0 | P45: =SUMIFS(#REF!,#REF!, $A45,#REF!, ">="&'Faturado mensal'!P$2,#REF!, "<"&EOMONTH('Faturado mensal'!P$2,0)) -> 0 | Q45: =SUMIFS(#REF!,#REF!, $A45,#REF!, ">="&'Faturado mensal'!Q$2,#REF!, "<"&EOMONTH('Faturado mensal'!Q$2,0)) -> 0 | R45: =SUMIFS(#REF!,#REF!, $A45,#REF!, ">="&'Faturado mensal'!R$2,#REF!, "<"&EOMONTH('Faturado mensal'!R$2,0)) -> 0 | S45: =SUMIFS(#REF!,#REF!, $A45,#REF!, ">="&'Faturado mensal'!S$2,#REF!, "<"&EOMONTH('Faturado mensal'!S$2,0)) -> 0 | T45: =SUMIFS(#REF!,#REF!, $A45,#REF!, ">="&'Faturado mensal'!T$2,#REF!, "<"&EOMONTH('Faturado mensal'!T$2,0)) -> 0 | ... X45: =SUMIFS(#REF!,#REF!, $A45,#REF!, ">="&'Faturado mensal'!X$2,#REF!, "<"&EOMONTH('Faturado mensal'!X$2,0)) -> 0 | Y45: =SUMIFS(#REF!,#REF!, $A45,#REF!, ">="&'Faturado mensal'!M$2,#REF!, "<"&EOMONTH('Faturado mensal'!M$2,12)) -> 0 | Z45: =SUMIFS(#REF!,#REF!, $A45,#REF!, ">="&'Faturado mensal'!Z$2,#REF!, "<"&EOMONTH('Faturado mensal'!Z$2,0)) -> 0 | AA45: =SUMIFS(#REF!,#REF!, $A45,#REF!, ">="&'Faturado mensal'!AA$2,#REF!, "<"&EOMONTH('Faturado mensal'!AA$2,0)) -> 0 | AB45: =SUMIFS(#REF!,#REF!, $A45,#REF!, ">="&'Faturado mensal'!AB$2,#REF!, "<"&EOMONTH('Faturado mensal'!AB$2,0)) -> 0 | AC45: =SUMIFS(#REF!,#REF!, $A45,#REF!, ">="&'Faturado mensal'!AC$2,#REF!, "<"&EOMONTH('Faturado mensal'!AC$2,0)) -> 0 | AD45: =SUMIFS(#REF!,#REF!, $A45,#REF!, ">="&'Faturado mensal'!AD$2,#REF!, "<"&EOMONTH('Faturado mensal'!AD$2,0)) -> 0 | AE45: =SUMIFS(#REF!,#REF!, $A45,#REF!, ">="&'Faturado mensal'!AE$2,#REF!, "<"&EOMONTH('Faturado mensal'!AE$2,0)) -> 0 | AF45: =SUMIFS(#REF!,#REF!, $A45,#REF!, ">="&'Faturado mensal'!AF$2,#REF!, "<"&EOMONTH('Faturado mensal'!AF$2,0)) -> 0 | AG45: =SUMIFS(#REF!,#REF!, $A45,#REF!, ">="&'Faturado mensal'!AG$2,#REF!, "<"&EOMONTH('Faturado mensal'!AG$2,0)) -> 0 | ... AK45: =SUMIFS(#REF!,#REF!, $A45,#REF!, ">="&'Faturado mensal'!AK$2,#REF!, "<"&EOMONTH('Faturado mensal'!AK$2,0)) -> 0 | AL45: =SUMIFS(#REF!,#REF!, $A45,#REF!, ">="&Z$2,#REF!, "<"&EOMONTH(AK$2,0)) -> 0
A46: CS0000754 | B46: 070020105 | C46: AGIT SOLUCOES AMBIENTAIS LTDA | D46: Concluído | G46: INDUSTRIAL CO | H46: B | I46: AGIT SOLUCOES AMBIENTAIS LTDA | J46: 30 DIAS | K46: SRSFAB | L46: PRGM . COMPRAS - SRS - FABRICA | M46: =SUMIFS(#REF!,#REF!, $A46,#REF!, ">="&'Faturado mensal'!M$2,#REF!, "<"&EOMONTH('Faturado mensal'!M$2,0)) -> 0 | N46: =SUMIFS(#REF!,#REF!, $A46,#REF!, ">="&'Faturado mensal'!N$2,#REF!, "<"&EOMONTH('Faturado mensal'!N$2,0)) -> 141.74 | O46: =SUMIFS(#REF!,#REF!, $A46,#REF!, ">="&'Faturado mensal'!O$2,#REF!, "<"&EOMONTH('Faturado mensal'!O$2,0)) -> 0 | P46: =SUMIFS(#REF!,#REF!, $A46,#REF!, ">="&'Faturado mensal'!P$2,#REF!, "<"&EOMONTH('Faturado mensal'!P$2,0)) -> 0 | Q46: =SUMIFS(#REF!,#REF!, $A46,#REF!, ">="&'Faturado mensal'!Q$2,#REF!, "<"&EOMONTH('Faturado mensal'!Q$2,0)) -> 0 | R46: =SUMIFS(#REF!,#REF!, $A46,#REF!, ">="&'Faturado mensal'!R$2,#REF!, "<"&EOMONTH('Faturado mensal'!R$2,0)) -> 0 | S46: =SUMIFS(#REF!,#REF!, $A46,#REF!, ">="&'Faturado mensal'!S$2,#REF!, "<"&EOMONTH('Faturado mensal'!S$2,0)) -> 0 | T46: =SUMIFS(#REF!,#REF!, $A46,#REF!, ">="&'Faturado mensal'!T$2,#REF!, "<"&EOMONTH('Faturado mensal'!T$2,0)) -> 0 | ... X46: =SUMIFS(#REF!,#REF!, $A46,#REF!, ">="&'Faturado mensal'!X$2,#REF!, "<"&EOMONTH('Faturado mensal'!X$2,0)) -> 0 | Y46: =SUMIFS(#REF!,#REF!, $A46,#REF!, ">="&'Faturado mensal'!M$2,#REF!, "<"&EOMONTH('Faturado mensal'!M$2,12)) -> 141.74 | Z46: =SUMIFS(#REF!,#REF!, $A46,#REF!, ">="&'Faturado mensal'!Z$2,#REF!, "<"&EOMONTH('Faturado mensal'!Z$2,0)) -> 0 | AA46: =SUMIFS(#REF!,#REF!, $A46,#REF!, ">="&'Faturado mensal'!AA$2,#REF!, "<"&EOMONTH('Faturado mensal'!AA$2,0)) -> 0 | AB46: =SUMIFS(#REF!,#REF!, $A46,#REF!, ">="&'Faturado mensal'!AB$2,#REF!, "<"&EOMONTH('Faturado mensal'!AB$2,0)) -> 0 | AC46: =SUMIFS(#REF!,#REF!, $A46,#REF!, ">="&'Faturado mensal'!AC$2,#REF!, "<"&EOMONTH('Faturado mensal'!AC$2,0)) -> 0 | AD46: =SUMIFS(#REF!,#REF!, $A46,#REF!, ">="&'Faturado mensal'!AD$2,#REF!, "<"&EOMONTH('Faturado mensal'!AD$2,0)) -> 0 | AE46: =SUMIFS(#REF!,#REF!, $A46,#REF!, ">="&'Faturado mensal'!AE$2,#REF!, "<"&EOMONTH('Faturado mensal'!AE$2,0)) -> 0 | AF46: =SUMIFS(#REF!,#REF!, $A46,#REF!, ">="&'Faturado mensal'!AF$2,#REF!, "<"&EOMONTH('Faturado mensal'!AF$2,0)) -> 0 | AG46: =SUMIFS(#REF!,#REF!, $A46,#REF!, ">="&'Faturado mensal'!AG$2,#REF!, "<"&EOMONTH('Faturado mensal'!AG$2,0)) -> 0 | ... AK46: =SUMIFS(#REF!,#REF!, $A46,#REF!, ">="&'Faturado mensal'!AK$2,#REF!, "<"&EOMONTH('Faturado mensal'!AK$2,0)) -> 0 | AL46: =SUMIFS(#REF!,#REF!, $A46,#REF!, ">="&Z$2,#REF!, "<"&EOMONTH(AK$2,0)) -> 0
A47: CS0000755 | B47: 070076285 | C47: RD GESTAO E SISTEMAS S.A. | D47: Ativo | E47: MARKETING | F47: SERVIÇOS PRESTADOS | G47: COMERCIAL | H47: B | I47: RD GESTAO E SISTEMAS S.A. | J47: 30 DIAS | K47: VIESAD | L47: COMPRAS - VIES - ADMINISTRAÇAO | M47: =SUMIFS(#REF!,#REF!, $A47,#REF!, ">="&'Faturado mensal'!M$2,#REF!, "<"&EOMONTH('Faturado mensal'!M$2,0)) -> 0 | N47: =SUMIFS(#REF!,#REF!, $A47,#REF!, ">="&'Faturado mensal'!N$2,#REF!, "<"&EOMONTH('Faturado mensal'!N$2,0)) -> 0 | O47: =SUMIFS(#REF!,#REF!, $A47,#REF!, ">="&'Faturado mensal'!O$2,#REF!, "<"&EOMONTH('Faturado mensal'!O$2,0)) -> 0 | P47: =SUMIFS(#REF!,#REF!, $A47,#REF!, ">="&'Faturado mensal'!P$2,#REF!, "<"&EOMONTH('Faturado mensal'!P$2,0)) -> 0 | Q47: =SUMIFS(#REF!,#REF!, $A47,#REF!, ">="&'Faturado mensal'!Q$2,#REF!, "<"&EOMONTH('Faturado mensal'!Q$2,0)) -> 0 | R47: =SUMIFS(#REF!,#REF!, $A47,#REF!, ">="&'Faturado mensal'!R$2,#REF!, "<"&EOMONTH('Faturado mensal'!R$2,0)) -> 0 | S47: =SUMIFS(#REF!,#REF!, $A47,#REF!, ">="&'Faturado mensal'!S$2,#REF!, "<"&EOMONTH('Faturado mensal'!S$2,0)) -> 0 | T47: =SUMIFS(#REF!,#REF!, $A47,#REF!, ">="&'Faturado mensal'!T$2,#REF!, "<"&EOMONTH('Faturado mensal'!T$2,0)) -> 0 | ... X47: =SUMIFS(#REF!,#REF!, $A47,#REF!, ">="&'Faturado mensal'!X$2,#REF!, "<"&EOMONTH('Faturado mensal'!X$2,0)) -> 16140 | Y47: =SUMIFS(#REF!,#REF!, $A47,#REF!, ">="&'Faturado mensal'!M$2,#REF!, "<"&EOMONTH('Faturado mensal'!M$2,12)) -> 16140 | Z47: =SUMIFS(#REF!,#REF!, $A47,#REF!, ">="&'Faturado mensal'!Z$2,#REF!, "<"&EOMONTH('Faturado mensal'!Z$2,0)) -> 0 | AA47: =SUMIFS(#REF!,#REF!, $A47,#REF!, ">="&'Faturado mensal'!AA$2,#REF!, "<"&EOMONTH('Faturado mensal'!AA$2,0)) -> 0 | AB47: =SUMIFS(#REF!,#REF!, $A47,#REF!, ">="&'Faturado mensal'!AB$2,#REF!, "<"&EOMONTH('Faturado mensal'!AB$2,0)) -> 0 | AC47: =SUMIFS(#REF!,#REF!, $A47,#REF!, ">="&'Faturado mensal'!AC$2,#REF!, "<"&EOMONTH('Faturado mensal'!AC$2,0)) -> 0 | AD47: =SUMIFS(#REF!,#REF!, $A47,#REF!, ">="&'Faturado mensal'!AD$2,#REF!, "<"&EOMONTH('Faturado mensal'!AD$2,0)) -> 0 | AE47: =SUMIFS(#REF!,#REF!, $A47,#REF!, ">="&'Faturado mensal'!AE$2,#REF!, "<"&EOMONTH('Faturado mensal'!AE$2,0)) -> 0 | AF47: =SUMIFS(#REF!,#REF!, $A47,#REF!, ">="&'Faturado mensal'!AF$2,#REF!, "<"&EOMONTH('Faturado mensal'!AF$2,0)) -> 0 | AG47: =SUMIFS(#REF!,#REF!, $A47,#REF!, ">="&'Faturado mensal'!AG$2,#REF!, "<"&EOMONTH('Faturado mensal'!AG$2,0)) -> 0 | ... AK47: =SUMIFS(#REF!,#REF!, $A47,#REF!, ">="&'Faturado mensal'!AK$2,#REF!, "<"&EOMONTH('Faturado mensal'!AK$2,0)) -> 0 | AL47: =SUMIFS(#REF!,#REF!, $A47,#REF!, ">="&Z$2,#REF!, "<"&EOMONTH(AK$2,0)) -> 0
A48: CS0000758 | B48: 070001594 | C48: N & N CONSTRUCOES LTDA | D48: Ativo | E48: MANUFATURA VIES | F48: TERCEIROS | G48: INDUSTRIAL VIES | H48: C | I48: N & N CONSTRUCOES LTDA | J48: 30 DIAS | K48: VIESFB | L48: PRGM .COMPRAS - VIES - FABRICA | M48: =SUMIFS(#REF!,#REF!, $A48,#REF!, ">="&'Faturado mensal'!M$2,#REF!, "<"&EOMONTH('Faturado mensal'!M$2,0)) -> 39804 | N48: =SUMIFS(#REF!,#REF!, $A48,#REF!, ">="&'Faturado mensal'!N$2,#REF!, "<"&EOMONTH('Faturado mensal'!N$2,0)) -> 47094 | O48: =SUMIFS(#REF!,#REF!, $A48,#REF!, ">="&'Faturado mensal'!O$2,#REF!, "<"&EOMONTH('Faturado mensal'!O$2,0)) -> 30394 | P48: =SUMIFS(#REF!,#REF!, $A48,#REF!, ">="&'Faturado mensal'!P$2,#REF!, "<"&EOMONTH('Faturado mensal'!P$2,0)) -> 28390 | Q48: =SUMIFS(#REF!,#REF!, $A48,#REF!, ">="&'Faturado mensal'!Q$2,#REF!, "<"&EOMONTH('Faturado mensal'!Q$2,0)) -> 28695.12 | R48: =SUMIFS(#REF!,#REF!, $A48,#REF!, ">="&'Faturado mensal'!R$2,#REF!, "<"&EOMONTH('Faturado mensal'!R$2,0)) -> 31930.4 | S48: =SUMIFS(#REF!,#REF!, $A48,#REF!, ">="&'Faturado mensal'!S$2,#REF!, "<"&EOMONTH('Faturado mensal'!S$2,0)) -> 29691.56 | T48: =SUMIFS(#REF!,#REF!, $A48,#REF!, ">="&'Faturado mensal'!T$2,#REF!, "<"&EOMONTH('Faturado mensal'!T$2,0)) -> 0 | ... X48: =SUMIFS(#REF!,#REF!, $A48,#REF!, ">="&'Faturado mensal'!X$2,#REF!, "<"&EOMONTH('Faturado mensal'!X$2,0)) -> 13404.88 | Y48: =SUMIFS(#REF!,#REF!, $A48,#REF!, ">="&'Faturado mensal'!M$2,#REF!, "<"&EOMONTH('Faturado mensal'!M$2,12)) -> 372324.31 | Z48: =SUMIFS(#REF!,#REF!, $A48,#REF!, ">="&'Faturado mensal'!Z$2,#REF!, "<"&EOMONTH('Faturado mensal'!Z$2,0)) -> 14121.24 | AA48: =SUMIFS(#REF!,#REF!, $A48,#REF!, ">="&'Faturado mensal'!AA$2,#REF!, "<"&EOMONTH('Faturado mensal'!AA$2,0)) -> 0 | AB48: =SUMIFS(#REF!,#REF!, $A48,#REF!, ">="&'Faturado mensal'!AB$2,#REF!, "<"&EOMONTH('Faturado mensal'!AB$2,0)) -> 40813.92 | AC48: =SUMIFS(#REF!,#REF!, $A48,#REF!, ">="&'Faturado mensal'!AC$2,#REF!, "<"&EOMONTH('Faturado mensal'!AC$2,0)) -> 23127.89 | AD48: =SUMIFS(#REF!,#REF!, $A48,#REF!, ">="&'Faturado mensal'!AD$2,#REF!, "<"&EOMONTH('Faturado mensal'!AD$2,0)) -> 18593.01 | AE48: =SUMIFS(#REF!,#REF!, $A48,#REF!, ">="&'Faturado mensal'!AE$2,#REF!, "<"&EOMONTH('Faturado mensal'!AE$2,0)) -> 18139.52 | AF48: =SUMIFS(#REF!,#REF!, $A48,#REF!, ">="&'Faturado mensal'!AF$2,#REF!, "<"&EOMONTH('Faturado mensal'!AF$2,0)) -> 0 | AG48: =SUMIFS(#REF!,#REF!, $A48,#REF!, ">="&'Faturado mensal'!AG$2,#REF!, "<"&EOMONTH('Faturado mensal'!AG$2,0)) -> 0 | ... AK48: =SUMIFS(#REF!,#REF!, $A48,#REF!, ">="&'Faturado mensal'!AK$2,#REF!, "<"&EOMONTH('Faturado mensal'!AK$2,0)) -> 0 | AL48: =SUMIFS(#REF!,#REF!, $A48,#REF!, ">="&Z$2,#REF!, "<"&EOMONTH(AK$2,0)) -> 114795.58
A49: CS0000762 | B49: 090095564 | C49: SMARTPLM SOL.SERV.T.I.LTDA | D49: Concluído | F49: SERVIÇOS PRESTADOS | G49: INDUSTRIAL VIES | H49: B | I49: SMARTPLM SOL.SERV.T.I.LTDA | J49: 30 DIAS | K49: VIESFB | L49: PRGM .COMPRAS - VIES - FABRICA | M49: =SUMIFS(#REF!,#REF!, $A49,#REF!, ">="&'Faturado mensal'!M$2,#REF!, "<"&EOMONTH('Faturado mensal'!M$2,0)) -> 0 | N49: =SUMIFS(#REF!,#REF!, $A49,#REF!, ">="&'Faturado mensal'!N$2,#REF!, "<"&EOMONTH('Faturado mensal'!N$2,0)) -> 0 | O49: =SUMIFS(#REF!,#REF!, $A49,#REF!, ">="&'Faturado mensal'!O$2,#REF!, "<"&EOMONTH('Faturado mensal'!O$2,0)) -> 10222.89 | P49: =SUMIFS(#REF!,#REF!, $A49,#REF!, ">="&'Faturado mensal'!P$2,#REF!, "<"&EOMONTH('Faturado mensal'!P$2,0)) -> 0 | Q49: =SUMIFS(#REF!,#REF!, $A49,#REF!, ">="&'Faturado mensal'!Q$2,#REF!, "<"&EOMONTH('Faturado mensal'!Q$2,0)) -> 0 | R49: =SUMIFS(#REF!,#REF!, $A49,#REF!, ">="&'Faturado mensal'!R$2,#REF!, "<"&EOMONTH('Faturado mensal'!R$2,0)) -> 0 | S49: =SUMIFS(#REF!,#REF!, $A49,#REF!, ">="&'Faturado mensal'!S$2,#REF!, "<"&EOMONTH('Faturado mensal'!S$2,0)) -> 0 | T49: =SUMIFS(#REF!,#REF!, $A49,#REF!, ">="&'Faturado mensal'!T$2,#REF!, "<"&EOMONTH('Faturado mensal'!T$2,0)) -> 0 | ... X49: =SUMIFS(#REF!,#REF!, $A49,#REF!, ">="&'Faturado mensal'!X$2,#REF!, "<"&EOMONTH('Faturado mensal'!X$2,0)) -> 0 | Y49: =SUMIFS(#REF!,#REF!, $A49,#REF!, ">="&'Faturado mensal'!M$2,#REF!, "<"&EOMONTH('Faturado mensal'!M$2,12)) -> 10222.89 | Z49: =SUMIFS(#REF!,#REF!, $A49,#REF!, ">="&'Faturado mensal'!Z$2,#REF!, "<"&EOMONTH('Faturado mensal'!Z$2,0)) -> 0 | AA49: =SUMIFS(#REF!,#REF!, $A49,#REF!, ">="&'Faturado mensal'!AA$2,#REF!, "<"&EOMONTH('Faturado mensal'!AA$2,0)) -> 0 | AB49: =SUMIFS(#REF!,#REF!, $A49,#REF!, ">="&'Faturado mensal'!AB$2,#REF!, "<"&EOMONTH('Faturado mensal'!AB$2,0)) -> 0 | AC49: =SUMIFS(#REF!,#REF!, $A49,#REF!, ">="&'Faturado mensal'!AC$2,#REF!, "<"&EOMONTH('Faturado mensal'!AC$2,0)) -> 0 | AD49: =SUMIFS(#REF!,#REF!, $A49,#REF!, ">="&'Faturado mensal'!AD$2,#REF!, "<"&EOMONTH('Faturado mensal'!AD$2,0)) -> 0 | AE49: =SUMIFS(#REF!,#REF!, $A49,#REF!, ">="&'Faturado mensal'!AE$2,#REF!, "<"&EOMONTH('Faturado mensal'!AE$2,0)) -> 0 | AF49: =SUMIFS(#REF!,#REF!, $A49,#REF!, ">="&'Faturado mensal'!AF$2,#REF!, "<"&EOMONTH('Faturado mensal'!AF$2,0)) -> 0 | AG49: =SUMIFS(#REF!,#REF!, $A49,#REF!, ">="&'Faturado mensal'!AG$2,#REF!, "<"&EOMONTH('Faturado mensal'!AG$2,0)) -> 0 | ... AK49: =SUMIFS(#REF!,#REF!, $A49,#REF!, ">="&'Faturado mensal'!AK$2,#REF!, "<"&EOMONTH('Faturado mensal'!AK$2,0)) -> 0 | AL49: =SUMIFS(#REF!,#REF!, $A49,#REF!, ">="&Z$2,#REF!, "<"&EOMONTH(AK$2,0)) -> 0
A50: CS0000763 | B50: 090095564 | C50: SMARTPLM SOL.SERV.T.I.LTDA | D50: Concluído | F50: SERVIÇOS PRESTADOS | G50: INDUSTRIAL VIES | H50: B | I50: SMARTPLM SOL.SERV.T.I.LTDA | J50: 30 DIAS | K50: VIESFB | L50: PRGM .COMPRAS - VIES - FABRICA | M50: =SUMIFS(#REF!,#REF!, $A50,#REF!, ">="&'Faturado mensal'!M$2,#REF!, "<"&EOMONTH('Faturado mensal'!M$2,0)) -> 0 | N50: =SUMIFS(#REF!,#REF!, $A50,#REF!, ">="&'Faturado mensal'!N$2,#REF!, "<"&EOMONTH('Faturado mensal'!N$2,0)) -> 0 | O50: =SUMIFS(#REF!,#REF!, $A50,#REF!, ">="&'Faturado mensal'!O$2,#REF!, "<"&EOMONTH('Faturado mensal'!O$2,0)) -> 0 | P50: =SUMIFS(#REF!,#REF!, $A50,#REF!, ">="&'Faturado mensal'!P$2,#REF!, "<"&EOMONTH('Faturado mensal'!P$2,0)) -> 0 | Q50: =SUMIFS(#REF!,#REF!, $A50,#REF!, ">="&'Faturado mensal'!Q$2,#REF!, "<"&EOMONTH('Faturado mensal'!Q$2,0)) -> 0 | R50: =SUMIFS(#REF!,#REF!, $A50,#REF!, ">="&'Faturado mensal'!R$2,#REF!, "<"&EOMONTH('Faturado mensal'!R$2,0)) -> 0 | S50: =SUMIFS(#REF!,#REF!, $A50,#REF!, ">="&'Faturado mensal'!S$2,#REF!, "<"&EOMONTH('Faturado mensal'!S$2,0)) -> 0 | T50: =SUMIFS(#REF!,#REF!, $A50,#REF!, ">="&'Faturado mensal'!T$2,#REF!, "<"&EOMONTH('Faturado mensal'!T$2,0)) -> 0 | ... X50: =SUMIFS(#REF!,#REF!, $A50,#REF!, ">="&'Faturado mensal'!X$2,#REF!, "<"&EOMONTH('Faturado mensal'!X$2,0)) -> 0 | Y50: =SUMIFS(#REF!,#REF!, $A50,#REF!, ">="&'Faturado mensal'!M$2,#REF!, "<"&EOMONTH('Faturado mensal'!M$2,12)) -> 0 | Z50: =SUMIFS(#REF!,#REF!, $A50,#REF!, ">="&'Faturado mensal'!Z$2,#REF!, "<"&EOMONTH('Faturado mensal'!Z$2,0)) -> 0 | AA50: =SUMIFS(#REF!,#REF!, $A50,#REF!, ">="&'Faturado mensal'!AA$2,#REF!, "<"&EOMONTH('Faturado mensal'!AA$2,0)) -> 0 | AB50: =SUMIFS(#REF!,#REF!, $A50,#REF!, ">="&'Faturado mensal'!AB$2,#REF!, "<"&EOMONTH('Faturado mensal'!AB$2,0)) -> 0 | AC50: =SUMIFS(#REF!,#REF!, $A50,#REF!, ">="&'Faturado mensal'!AC$2,#REF!, "<"&EOMONTH('Faturado mensal'!AC$2,0)) -> 0 | AD50: =SUMIFS(#REF!,#REF!, $A50,#REF!, ">="&'Faturado mensal'!AD$2,#REF!, "<"&EOMONTH('Faturado mensal'!AD$2,0)) -> 0 | AE50: =SUMIFS(#REF!,#REF!, $A50,#REF!, ">="&'Faturado mensal'!AE$2,#REF!, "<"&EOMONTH('Faturado mensal'!AE$2,0)) -> 0 | AF50: =SUMIFS(#REF!,#REF!, $A50,#REF!, ">="&'Faturado mensal'!AF$2,#REF!, "<"&EOMONTH('Faturado mensal'!AF$2,0)) -> 0 | AG50: =SUMIFS(#REF!,#REF!, $A50,#REF!, ">="&'Faturado mensal'!AG$2,#REF!, "<"&EOMONTH('Faturado mensal'!AG$2,0)) -> 0 | ... AK50: =SUMIFS(#REF!,#REF!, $A50,#REF!, ">="&'Faturado mensal'!AK$2,#REF!, "<"&EOMONTH('Faturado mensal'!AK$2,0)) -> 0 | AL50: =SUMIFS(#REF!,#REF!, $A50,#REF!, ">="&Z$2,#REF!, "<"&EOMONTH(AK$2,0)) -> 0
A51: CS0000765 | B51: 070006685 | C51: SERPRAM SERV PREST A M H LTDA | D51: Concluído | I51: SERPRAM SERV PREST A M H LTDA | J51: 30 DIAS | K51: COFAB | L51: PRGM . COMPRAS - CO - FABRICA | M51: =SUMIFS(#REF!,#REF!, $A51,#REF!, ">="&'Faturado mensal'!M$2,#REF!, "<"&EOMONTH('Faturado mensal'!M$2,0)) -> 0 | N51: =SUMIFS(#REF!,#REF!, $A51,#REF!, ">="&'Faturado mensal'!N$2,#REF!, "<"&EOMONTH('Faturado mensal'!N$2,0)) -> 0 | O51: =SUMIFS(#REF!,#REF!, $A51,#REF!, ">="&'Faturado mensal'!O$2,#REF!, "<"&EOMONTH('Faturado mensal'!O$2,0)) -> 0 | P51: =SUMIFS(#REF!,#REF!, $A51,#REF!, ">="&'Faturado mensal'!P$2,#REF!, "<"&EOMONTH('Faturado mensal'!P$2,0)) -> 0 | Q51: =SUMIFS(#REF!,#REF!, $A51,#REF!, ">="&'Faturado mensal'!Q$2,#REF!, "<"&EOMONTH('Faturado mensal'!Q$2,0)) -> 0 | R51: =SUMIFS(#REF!,#REF!, $A51,#REF!, ">="&'Faturado mensal'!R$2,#REF!, "<"&EOMONTH('Faturado mensal'!R$2,0)) -> 0 | S51: =SUMIFS(#REF!,#REF!, $A51,#REF!, ">="&'Faturado mensal'!S$2,#REF!, "<"&EOMONTH('Faturado mensal'!S$2,0)) -> 0 | T51: =SUMIFS(#REF!,#REF!, $A51,#REF!, ">="&'Faturado mensal'!T$2,#REF!, "<"&EOMONTH('Faturado mensal'!T$2,0)) -> 0 | ... X51: =SUMIFS(#REF!,#REF!, $A51,#REF!, ">="&'Faturado mensal'!X$2,#REF!, "<"&EOMONTH('Faturado mensal'!X$2,0)) -> 0 | Y51: =SUMIFS(#REF!,#REF!, $A51,#REF!, ">="&'Faturado mensal'!M$2,#REF!, "<"&EOMONTH('Faturado mensal'!M$2,12)) -> 0 | Z51: =SUMIFS(#REF!,#REF!, $A51,#REF!, ">="&'Faturado mensal'!Z$2,#REF!, "<"&EOMONTH('Faturado mensal'!Z$2,0)) -> 0 | AA51: =SUMIFS(#REF!,#REF!, $A51,#REF!, ">="&'Faturado mensal'!AA$2,#REF!, "<"&EOMONTH('Faturado mensal'!AA$2,0)) -> 0 | AB51: =SUMIFS(#REF!,#REF!, $A51,#REF!, ">="&'Faturado mensal'!AB$2,#REF!, "<"&EOMONTH('Faturado mensal'!AB$2,0)) -> 0 | AC51: =SUMIFS(#REF!,#REF!, $A51,#REF!, ">="&'Faturado mensal'!AC$2,#REF!, "<"&EOMONTH('Faturado mensal'!AC$2,0)) -> 0 | AD51: =SUMIFS(#REF!,#REF!, $A51,#REF!, ">="&'Faturado mensal'!AD$2,#REF!, "<"&EOMONTH('Faturado mensal'!AD$2,0)) -> 0 | AE51: =SUMIFS(#REF!,#REF!, $A51,#REF!, ">="&'Faturado mensal'!AE$2,#REF!, "<"&EOMONTH('Faturado mensal'!AE$2,0)) -> 0 | AF51: =SUMIFS(#REF!,#REF!, $A51,#REF!, ">="&'Faturado mensal'!AF$2,#REF!, "<"&EOMONTH('Faturado mensal'!AF$2,0)) -> 0 | AG51: =SUMIFS(#REF!,#REF!, $A51,#REF!, ">="&'Faturado mensal'!AG$2,#REF!, "<"&EOMONTH('Faturado mensal'!AG$2,0)) -> 0 | ... AK51: =SUMIFS(#REF!,#REF!, $A51,#REF!, ">="&'Faturado mensal'!AK$2,#REF!, "<"&EOMONTH('Faturado mensal'!AK$2,0)) -> 0 | AL51: =SUMIFS(#REF!,#REF!, $A51,#REF!, ">="&Z$2,#REF!, "<"&EOMONTH(AK$2,0)) -> 0
A52: CS0000767 | B52: 090095419 | C52: TOP SERVICE SERVICOS SIST LTDA | D52: Concluído | I52: TOP SERVICE SERVICOS SIST LTDA | J52: 30 DIAS | K52: COFAB | L52: PRGM . COMPRAS - CO - FABRICA | M52: =SUMIFS(#REF!,#REF!, $A52,#REF!, ">="&'Faturado mensal'!M$2,#REF!, "<"&EOMONTH('Faturado mensal'!M$2,0)) -> 0 | N52: =SUMIFS(#REF!,#REF!, $A52,#REF!, ">="&'Faturado mensal'!N$2,#REF!, "<"&EOMONTH('Faturado mensal'!N$2,0)) -> 0 | O52: =SUMIFS(#REF!,#REF!, $A52,#REF!, ">="&'Faturado mensal'!O$2,#REF!, "<"&EOMONTH('Faturado mensal'!O$2,0)) -> 0 | P52: =SUMIFS(#REF!,#REF!, $A52,#REF!, ">="&'Faturado mensal'!P$2,#REF!, "<"&EOMONTH('Faturado mensal'!P$2,0)) -> 0 | Q52: =SUMIFS(#REF!,#REF!, $A52,#REF!, ">="&'Faturado mensal'!Q$2,#REF!, "<"&EOMONTH('Faturado mensal'!Q$2,0)) -> 0 | R52: =SUMIFS(#REF!,#REF!, $A52,#REF!, ">="&'Faturado mensal'!R$2,#REF!, "<"&EOMONTH('Faturado mensal'!R$2,0)) -> 0 | S52: =SUMIFS(#REF!,#REF!, $A52,#REF!, ">="&'Faturado mensal'!S$2,#REF!, "<"&EOMONTH('Faturado mensal'!S$2,0)) -> 0 | T52: =SUMIFS(#REF!,#REF!, $A52,#REF!, ">="&'Faturado mensal'!T$2,#REF!, "<"&EOMONTH('Faturado mensal'!T$2,0)) -> 0 | ... X52: =SUMIFS(#REF!,#REF!, $A52,#REF!, ">="&'Faturado mensal'!X$2,#REF!, "<"&EOMONTH('Faturado mensal'!X$2,0)) -> 0 | Y52: =SUMIFS(#REF!,#REF!, $A52,#REF!, ">="&'Faturado mensal'!M$2,#REF!, "<"&EOMONTH('Faturado mensal'!M$2,12)) -> 0 | Z52: =SUMIFS(#REF!,#REF!, $A52,#REF!, ">="&'Faturado mensal'!Z$2,#REF!, "<"&EOMONTH('Faturado mensal'!Z$2,0)) -> 0 | AA52: =SUMIFS(#REF!,#REF!, $A52,#REF!, ">="&'Faturado mensal'!AA$2,#REF!, "<"&EOMONTH('Faturado mensal'!AA$2,0)) -> 0 | AB52: =SUMIFS(#REF!,#REF!, $A52,#REF!, ">="&'Faturado mensal'!AB$2,#REF!, "<"&EOMONTH('Faturado mensal'!AB$2,0)) -> 0 | AC52: =SUMIFS(#REF!,#REF!, $A52,#REF!, ">="&'Faturado mensal'!AC$2,#REF!, "<"&EOMONTH('Faturado mensal'!AC$2,0)) -> 0 | AD52: =SUMIFS(#REF!,#REF!, $A52,#REF!, ">="&'Faturado mensal'!AD$2,#REF!, "<"&EOMONTH('Faturado mensal'!AD$2,0)) -> 0 | AE52: =SUMIFS(#REF!,#REF!, $A52,#REF!, ">="&'Faturado mensal'!AE$2,#REF!, "<"&EOMONTH('Faturado mensal'!AE$2,0)) -> 0 | AF52: =SUMIFS(#REF!,#REF!, $A52,#REF!, ">="&'Faturado mensal'!AF$2,#REF!, "<"&EOMONTH('Faturado mensal'!AF$2,0)) -> 0 | AG52: =SUMIFS(#REF!,#REF!, $A52,#REF!, ">="&'Faturado mensal'!AG$2,#REF!, "<"&EOMONTH('Faturado mensal'!AG$2,0)) -> 0 | ... AK52: =SUMIFS(#REF!,#REF!, $A52,#REF!, ">="&'Faturado mensal'!AK$2,#REF!, "<"&EOMONTH('Faturado mensal'!AK$2,0)) -> 0 | AL52: =SUMIFS(#REF!,#REF!, $A52,#REF!, ">="&Z$2,#REF!, "<"&EOMONTH(AK$2,0)) -> 0
A53: CS0000773 | B53: 070076083 | C53: VENETUR TURISMO LTDA | D53: Ativo | E53: RECURSOS HUMANOS | F53: TRANSPORTE FUNCIONÁRIOS | G53: ADMINISTRATIVO | H53: A | I53: VENETUR TURISMO LTDA | J53: 30 DIAS | K53: SRSADM | L53: COMPRAS - SRS - ADMINISTRAÇÃO | M53: =SUMIFS(#REF!,#REF!, $A53,#REF!, ">="&'Faturado mensal'!M$2,#REF!, "<"&EOMONTH('Faturado mensal'!M$2,0)) -> 164844.68 | N53: =SUMIFS(#REF!,#REF!, $A53,#REF!, ">="&'Faturado mensal'!N$2,#REF!, "<"&EOMONTH('Faturado mensal'!N$2,0)) -> 169135.37 | O53: =SUMIFS(#REF!,#REF!, $A53,#REF!, ">="&'Faturado mensal'!O$2,#REF!, "<"&EOMONTH('Faturado mensal'!O$2,0)) -> 169401.04 | P53: =SUMIFS(#REF!,#REF!, $A53,#REF!, ">="&'Faturado mensal'!P$2,#REF!, "<"&EOMONTH('Faturado mensal'!P$2,0)) -> 173043.58 | Q53: =SUMIFS(#REF!,#REF!, $A53,#REF!, ">="&'Faturado mensal'!Q$2,#REF!, "<"&EOMONTH('Faturado mensal'!Q$2,0)) -> 172266.15 | R53: =SUMIFS(#REF!,#REF!, $A53,#REF!, ">="&'Faturado mensal'!R$2,#REF!, "<"&EOMONTH('Faturado mensal'!R$2,0)) -> 187286.84 | S53: =SUMIFS(#REF!,#REF!, $A53,#REF!, ">="&'Faturado mensal'!S$2,#REF!, "<"&EOMONTH('Faturado mensal'!S$2,0)) -> 190964.1 | T53: =SUMIFS(#REF!,#REF!, $A53,#REF!, ">="&'Faturado mensal'!T$2,#REF!, "<"&EOMONTH('Faturado mensal'!T$2,0)) -> 197654.96 | ... X53: =SUMIFS(#REF!,#REF!, $A53,#REF!, ">="&'Faturado mensal'!X$2,#REF!, "<"&EOMONTH('Faturado mensal'!X$2,0)) -> 165808.12 | Y53: =SUMIFS(#REF!,#REF!, $A53,#REF!, ">="&'Faturado mensal'!M$2,#REF!, "<"&EOMONTH('Faturado mensal'!M$2,12)) -> 2315927.6 | Z53: =SUMIFS(#REF!,#REF!, $A53,#REF!, ">="&'Faturado mensal'!Z$2,#REF!, "<"&EOMONTH('Faturado mensal'!Z$2,0)) -> 143908.86 | AA53: =SUMIFS(#REF!,#REF!, $A53,#REF!, ">="&'Faturado mensal'!AA$2,#REF!, "<"&EOMONTH('Faturado mensal'!AA$2,0)) -> 169714.2 | AB53: =SUMIFS(#REF!,#REF!, $A53,#REF!, ">="&'Faturado mensal'!AB$2,#REF!, "<"&EOMONTH('Faturado mensal'!AB$2,0)) -> 167509.27 | AC53: =SUMIFS(#REF!,#REF!, $A53,#REF!, ">="&'Faturado mensal'!AC$2,#REF!, "<"&EOMONTH('Faturado mensal'!AC$2,0)) -> 0 | AD53: =SUMIFS(#REF!,#REF!, $A53,#REF!, ">="&'Faturado mensal'!AD$2,#REF!, "<"&EOMONTH('Faturado mensal'!AD$2,0)) -> 191315.57 | AE53: =SUMIFS(#REF!,#REF!, $A53,#REF!, ">="&'Faturado mensal'!AE$2,#REF!, "<"&EOMONTH('Faturado mensal'!AE$2,0)) -> 1737.2 | AF53: =SUMIFS(#REF!,#REF!, $A53,#REF!, ">="&'Faturado mensal'!AF$2,#REF!, "<"&EOMONTH('Faturado mensal'!AF$2,0)) -> 0 | AG53: =SUMIFS(#REF!,#REF!, $A53,#REF!, ">="&'Faturado mensal'!AG$2,#REF!, "<"&EOMONTH('Faturado mensal'!AG$2,0)) -> 0 | ... AK53: =SUMIFS(#REF!,#REF!, $A53,#REF!, ">="&'Faturado mensal'!AK$2,#REF!, "<"&EOMONTH('Faturado mensal'!AK$2,0)) -> 0 | AL53: =SUMIFS(#REF!,#REF!, $A53,#REF!, ">="&Z$2,#REF!, "<"&EOMONTH(AK$2,0)) -> 871527.16
A54: CS0000776 | B54: 090010398 | C54: WHIRLPOOL S.A | D54: Ativo | E54: MANUFATURA VIES | F54: LOCAÇÕES EQUIPAMENTOS / VEÍCULOS | G54: ADMINISTRATIVO | H54: C | I54: WHIRLPOOL S.A | J54: 30 DIAS | K54: VIESFB | L54: PRGM .COMPRAS - VIES - FABRICA | M54: =SUMIFS(#REF!,#REF!, $A54,#REF!, ">="&'Faturado mensal'!M$2,#REF!, "<"&EOMONTH('Faturado mensal'!M$2,0)) -> 932.3 | N54: =SUMIFS(#REF!,#REF!, $A54,#REF!, ">="&'Faturado mensal'!N$2,#REF!, "<"&EOMONTH('Faturado mensal'!N$2,0)) -> 720.12 | O54: =SUMIFS(#REF!,#REF!, $A54,#REF!, ">="&'Faturado mensal'!O$2,#REF!, "<"&EOMONTH('Faturado mensal'!O$2,0)) -> 822.4 | P54: =SUMIFS(#REF!,#REF!, $A54,#REF!, ">="&'Faturado mensal'!P$2,#REF!, "<"&EOMONTH('Faturado mensal'!P$2,0)) -> 822.4 | Q54: =SUMIFS(#REF!,#REF!, $A54,#REF!, ">="&'Faturado mensal'!Q$2,#REF!, "<"&EOMONTH('Faturado mensal'!Q$2,0)) -> 822.4 | R54: =SUMIFS(#REF!,#REF!, $A54,#REF!, ">="&'Faturado mensal'!R$2,#REF!, "<"&EOMONTH('Faturado mensal'!R$2,0)) -> 712.5 | S54: =SUMIFS(#REF!,#REF!, $A54,#REF!, ">="&'Faturado mensal'!S$2,#REF!, "<"&EOMONTH('Faturado mensal'!S$2,0)) -> 822.4 | T54: =SUMIFS(#REF!,#REF!, $A54,#REF!, ">="&'Faturado mensal'!T$2,#REF!, "<"&EOMONTH('Faturado mensal'!T$2,0)) -> 822.4 | ... X54: =SUMIFS(#REF!,#REF!, $A54,#REF!, ">="&'Faturado mensal'!X$2,#REF!, "<"&EOMONTH('Faturado mensal'!X$2,0)) -> 785.88 | Y54: =SUMIFS(#REF!,#REF!, $A54,#REF!, ">="&'Faturado mensal'!M$2,#REF!, "<"&EOMONTH('Faturado mensal'!M$2,12)) -> 9913.28 | Z54: =SUMIFS(#REF!,#REF!, $A54,#REF!, ">="&'Faturado mensal'!Z$2,#REF!, "<"&EOMONTH('Faturado mensal'!Z$2,0)) -> 0 | AA54: =SUMIFS(#REF!,#REF!, $A54,#REF!, ">="&'Faturado mensal'!AA$2,#REF!, "<"&EOMONTH('Faturado mensal'!AA$2,0)) -> 785.88 | AB54: =SUMIFS(#REF!,#REF!, $A54,#REF!, ">="&'Faturado mensal'!AB$2,#REF!, "<"&EOMONTH('Faturado mensal'!AB$2,0)) -> 0 | AC54: =SUMIFS(#REF!,#REF!, $A54,#REF!, ">="&'Faturado mensal'!AC$2,#REF!, "<"&EOMONTH('Faturado mensal'!AC$2,0)) -> 1484.44 | AD54: =SUMIFS(#REF!,#REF!, $A54,#REF!, ">="&'Faturado mensal'!AD$2,#REF!, "<"&EOMONTH('Faturado mensal'!AD$2,0)) -> 0 | AE54: =SUMIFS(#REF!,#REF!, $A54,#REF!, ">="&'Faturado mensal'!AE$2,#REF!, "<"&EOMONTH('Faturado mensal'!AE$2,0)) -> 0 | AF54: =SUMIFS(#REF!,#REF!, $A54,#REF!, ">="&'Faturado mensal'!AF$2,#REF!, "<"&EOMONTH('Faturado mensal'!AF$2,0)) -> 0 | AG54: =SUMIFS(#REF!,#REF!, $A54,#REF!, ">="&'Faturado mensal'!AG$2,#REF!, "<"&EOMONTH('Faturado mensal'!AG$2,0)) -> 0 | ... AK54: =SUMIFS(#REF!,#REF!, $A54,#REF!, ">="&'Faturado mensal'!AK$2,#REF!, "<"&EOMONTH('Faturado mensal'!AK$2,0)) -> 0 | AL54: =SUMIFS(#REF!,#REF!, $A54,#REF!, ">="&Z$2,#REF!, "<"&EOMONTH(AK$2,0)) -> 2270.32
A55: CS0000777 | B55: 090096485 | C55: HIDRO T TEC.S.ENERGIA E AGUA | D55: Concluído | I55: HIDRO T TEC.S.ENERGIA E AGUA | J55: 30 DIAS | K55: VIESFB | L55: PRGM .COMPRAS - VIES - FABRICA | M55: =SUMIFS(#REF!,#REF!, $A55,#REF!, ">="&'Faturado mensal'!M$2,#REF!, "<"&EOMONTH('Faturado mensal'!M$2,0)) -> 0 | N55: =SUMIFS(#REF!,#REF!, $A55,#REF!, ">="&'Faturado mensal'!N$2,#REF!, "<"&EOMONTH('Faturado mensal'!N$2,0)) -> 0 | O55: =SUMIFS(#REF!,#REF!, $A55,#REF!, ">="&'Faturado mensal'!O$2,#REF!, "<"&EOMONTH('Faturado mensal'!O$2,0)) -> 0 | P55: =SUMIFS(#REF!,#REF!, $A55,#REF!, ">="&'Faturado mensal'!P$2,#REF!, "<"&EOMONTH('Faturado mensal'!P$2,0)) -> 0 | Q55: =SUMIFS(#REF!,#REF!, $A55,#REF!, ">="&'Faturado mensal'!Q$2,#REF!, "<"&EOMONTH('Faturado mensal'!Q$2,0)) -> 0 | R55: =SUMIFS(#REF!,#REF!, $A55,#REF!, ">="&'Faturado mensal'!R$2,#REF!, "<"&EOMONTH('Faturado mensal'!R$2,0)) -> 0 | S55: =SUMIFS(#REF!,#REF!, $A55,#REF!, ">="&'Faturado mensal'!S$2,#REF!, "<"&EOMONTH('Faturado mensal'!S$2,0)) -> 0 | T55: =SUMIFS(#REF!,#REF!, $A55,#REF!, ">="&'Faturado mensal'!T$2,#REF!, "<"&EOMONTH('Faturado mensal'!T$2,0)) -> 0 | ... X55: =SUMIFS(#REF!,#REF!, $A55,#REF!, ">="&'Faturado mensal'!X$2,#REF!, "<"&EOMONTH('Faturado mensal'!X$2,0)) -> 0 | Y55: =SUMIFS(#REF!,#REF!, $A55,#REF!, ">="&'Faturado mensal'!M$2,#REF!, "<"&EOMONTH('Faturado mensal'!M$2,12)) -> 0 | Z55: =SUMIFS(#REF!,#REF!, $A55,#REF!, ">="&'Faturado mensal'!Z$2,#REF!, "<"&EOMONTH('Faturado mensal'!Z$2,0)) -> 0 | AA55: =SUMIFS(#REF!,#REF!, $A55,#REF!, ">="&'Faturado mensal'!AA$2,#REF!, "<"&EOMONTH('Faturado mensal'!AA$2,0)) -> 0 | AB55: =SUMIFS(#REF!,#REF!, $A55,#REF!, ">="&'Faturado mensal'!AB$2,#REF!, "<"&EOMONTH('Faturado mensal'!AB$2,0)) -> 0 | AC55: =SUMIFS(#REF!,#REF!, $A55,#REF!, ">="&'Faturado mensal'!AC$2,#REF!, "<"&EOMONTH('Faturado mensal'!AC$2,0)) -> 0 | AD55: =SUMIFS(#REF!,#REF!, $A55,#REF!, ">="&'Faturado mensal'!AD$2,#REF!, "<"&EOMONTH('Faturado mensal'!AD$2,0)) -> 0 | AE55: =SUMIFS(#REF!,#REF!, $A55,#REF!, ">="&'Faturado mensal'!AE$2,#REF!, "<"&EOMONTH('Faturado mensal'!AE$2,0)) -> 0 | AF55: =SUMIFS(#REF!,#REF!, $A55,#REF!, ">="&'Faturado mensal'!AF$2,#REF!, "<"&EOMONTH('Faturado mensal'!AF$2,0)) -> 0 | AG55: =SUMIFS(#REF!,#REF!, $A55,#REF!, ">="&'Faturado mensal'!AG$2,#REF!, "<"&EOMONTH('Faturado mensal'!AG$2,0)) -> 0 | ... AK55: =SUMIFS(#REF!,#REF!, $A55,#REF!, ">="&'Faturado mensal'!AK$2,#REF!, "<"&EOMONTH('Faturado mensal'!AK$2,0)) -> 0 | AL55: =SUMIFS(#REF!,#REF!, $A55,#REF!, ">="&Z$2,#REF!, "<"&EOMONTH(AK$2,0)) -> 0
A56: CS0000781 | B56: 070000629 | C56: EXCEL SERV. EM METROLOGIA LTDA | D56: Ativo | E56: QSMA | F56: SERVIÇOS PRESTADOS | G56: INDUSTRIAL VIES | H56: C | I56: EXCEL SERV. EM METROLOGIA LTDA | J56: 30 DIAS | K56: VIESFB | L56: PRGM .COMPRAS - VIES - FABRICA | M56: =SUMIFS(#REF!,#REF!, $A56,#REF!, ">="&'Faturado mensal'!M$2,#REF!, "<"&EOMONTH('Faturado mensal'!M$2,0)) -> 0 | N56: =SUMIFS(#REF!,#REF!, $A56,#REF!, ">="&'Faturado mensal'!N$2,#REF!, "<"&EOMONTH('Faturado mensal'!N$2,0)) -> 0 | O56: =SUMIFS(#REF!,#REF!, $A56,#REF!, ">="&'Faturado mensal'!O$2,#REF!, "<"&EOMONTH('Faturado mensal'!O$2,0)) -> 0 | P56: =SUMIFS(#REF!,#REF!, $A56,#REF!, ">="&'Faturado mensal'!P$2,#REF!, "<"&EOMONTH('Faturado mensal'!P$2,0)) -> 0 | Q56: =SUMIFS(#REF!,#REF!, $A56,#REF!, ">="&'Faturado mensal'!Q$2,#REF!, "<"&EOMONTH('Faturado mensal'!Q$2,0)) -> 0 | R56: =SUMIFS(#REF!,#REF!, $A56,#REF!, ">="&'Faturado mensal'!R$2,#REF!, "<"&EOMONTH('Faturado mensal'!R$2,0)) -> 0 | S56: =SUMIFS(#REF!,#REF!, $A56,#REF!, ">="&'Faturado mensal'!S$2,#REF!, "<"&EOMONTH('Faturado mensal'!S$2,0)) -> 0 | T56: =SUMIFS(#REF!,#REF!, $A56,#REF!, ">="&'Faturado mensal'!T$2,#REF!, "<"&EOMONTH('Faturado mensal'!T$2,0)) -> 0 | ... X56: =SUMIFS(#REF!,#REF!, $A56,#REF!, ">="&'Faturado mensal'!X$2,#REF!, "<"&EOMONTH('Faturado mensal'!X$2,0)) -> 0 | Y56: =SUMIFS(#REF!,#REF!, $A56,#REF!, ">="&'Faturado mensal'!M$2,#REF!, "<"&EOMONTH('Faturado mensal'!M$2,12)) -> 29855.75 | Z56: =SUMIFS(#REF!,#REF!, $A56,#REF!, ">="&'Faturado mensal'!Z$2,#REF!, "<"&EOMONTH('Faturado mensal'!Z$2,0)) -> 0 | AA56: =SUMIFS(#REF!,#REF!, $A56,#REF!, ">="&'Faturado mensal'!AA$2,#REF!, "<"&EOMONTH('Faturado mensal'!AA$2,0)) -> 0 | AB56: =SUMIFS(#REF!,#REF!, $A56,#REF!, ">="&'Faturado mensal'!AB$2,#REF!, "<"&EOMONTH('Faturado mensal'!AB$2,0)) -> 0 | AC56: =SUMIFS(#REF!,#REF!, $A56,#REF!, ">="&'Faturado mensal'!AC$2,#REF!, "<"&EOMONTH('Faturado mensal'!AC$2,0)) -> 0 | AD56: =SUMIFS(#REF!,#REF!, $A56,#REF!, ">="&'Faturado mensal'!AD$2,#REF!, "<"&EOMONTH('Faturado mensal'!AD$2,0)) -> 0 | AE56: =SUMIFS(#REF!,#REF!, $A56,#REF!, ">="&'Faturado mensal'!AE$2,#REF!, "<"&EOMONTH('Faturado mensal'!AE$2,0)) -> 0 | AF56: =SUMIFS(#REF!,#REF!, $A56,#REF!, ">="&'Faturado mensal'!AF$2,#REF!, "<"&EOMONTH('Faturado mensal'!AF$2,0)) -> 0 | AG56: =SUMIFS(#REF!,#REF!, $A56,#REF!, ">="&'Faturado mensal'!AG$2,#REF!, "<"&EOMONTH('Faturado mensal'!AG$2,0)) -> 0 | ... AK56: =SUMIFS(#REF!,#REF!, $A56,#REF!, ">="&'Faturado mensal'!AK$2,#REF!, "<"&EOMONTH('Faturado mensal'!AK$2,0)) -> 0 | AL56: =SUMIFS(#REF!,#REF!, $A56,#REF!, ">="&Z$2,#REF!, "<"&EOMONTH(AK$2,0)) -> 0
A57: CS0000783 | B57: 090001789 | C57: INST. DA QUALIDADE AUTOMOT.IQA | D57: Concluído | E57: QSMA | F57: SERVIÇOS PRESTADOS | G57: INDUSTRIAL SRS | H57: B | I57: INST. DA QUALIDADE AUTOMOT.IQA | J57: 30 DIAS | K57: COFAB | L57: PRGM . COMPRAS - CO - FABRICA | M57: =SUMIFS(#REF!,#REF!, $A57,#REF!, ">="&'Faturado mensal'!M$2,#REF!, "<"&EOMONTH('Faturado mensal'!M$2,0)) -> 0 | N57: =SUMIFS(#REF!,#REF!, $A57,#REF!, ">="&'Faturado mensal'!N$2,#REF!, "<"&EOMONTH('Faturado mensal'!N$2,0)) -> 0 | O57: =SUMIFS(#REF!,#REF!, $A57,#REF!, ">="&'Faturado mensal'!O$2,#REF!, "<"&EOMONTH('Faturado mensal'!O$2,0)) -> 0 | P57: =SUMIFS(#REF!,#REF!, $A57,#REF!, ">="&'Faturado mensal'!P$2,#REF!, "<"&EOMONTH('Faturado mensal'!P$2,0)) -> 0 | Q57: =SUMIFS(#REF!,#REF!, $A57,#REF!, ">="&'Faturado mensal'!Q$2,#REF!, "<"&EOMONTH('Faturado mensal'!Q$2,0)) -> 0 | R57: =SUMIFS(#REF!,#REF!, $A57,#REF!, ">="&'Faturado mensal'!R$2,#REF!, "<"&EOMONTH('Faturado mensal'!R$2,0)) -> 0 | S57: =SUMIFS(#REF!,#REF!, $A57,#REF!, ">="&'Faturado mensal'!S$2,#REF!, "<"&EOMONTH('Faturado mensal'!S$2,0)) -> 0 | T57: =SUMIFS(#REF!,#REF!, $A57,#REF!, ">="&'Faturado mensal'!T$2,#REF!, "<"&EOMONTH('Faturado mensal'!T$2,0)) -> 0 | ... X57: =SUMIFS(#REF!,#REF!, $A57,#REF!, ">="&'Faturado mensal'!X$2,#REF!, "<"&EOMONTH('Faturado mensal'!X$2,0)) -> 0 | Y57: =SUMIFS(#REF!,#REF!, $A57,#REF!, ">="&'Faturado mensal'!M$2,#REF!, "<"&EOMONTH('Faturado mensal'!M$2,12)) -> 0 | Z57: =SUMIFS(#REF!,#REF!, $A57,#REF!, ">="&'Faturado mensal'!Z$2,#REF!, "<"&EOMONTH('Faturado mensal'!Z$2,0)) -> 0 | AA57: =SUMIFS(#REF!,#REF!, $A57,#REF!, ">="&'Faturado mensal'!AA$2,#REF!, "<"&EOMONTH('Faturado mensal'!AA$2,0)) -> 0 | AB57: =SUMIFS(#REF!,#REF!, $A57,#REF!, ">="&'Faturado mensal'!AB$2,#REF!, "<"&EOMONTH('Faturado mensal'!AB$2,0)) -> 0 | AC57: =SUMIFS(#REF!,#REF!, $A57,#REF!, ">="&'Faturado mensal'!AC$2,#REF!, "<"&EOMONTH('Faturado mensal'!AC$2,0)) -> 0 | AD57: =SUMIFS(#REF!,#REF!, $A57,#REF!, ">="&'Faturado mensal'!AD$2,#REF!, "<"&EOMONTH('Faturado mensal'!AD$2,0)) -> 0 | AE57: =SUMIFS(#REF!,#REF!, $A57,#REF!, ">="&'Faturado mensal'!AE$2,#REF!, "<"&EOMONTH('Faturado mensal'!AE$2,0)) -> 0 | AF57: =SUMIFS(#REF!,#REF!, $A57,#REF!, ">="&'Faturado mensal'!AF$2,#REF!, "<"&EOMONTH('Faturado mensal'!AF$2,0)) -> 0 | AG57: =SUMIFS(#REF!,#REF!, $A57,#REF!, ">="&'Faturado mensal'!AG$2,#REF!, "<"&EOMONTH('Faturado mensal'!AG$2,0)) -> 0 | ... AK57: =SUMIFS(#REF!,#REF!, $A57,#REF!, ">="&'Faturado mensal'!AK$2,#REF!, "<"&EOMONTH('Faturado mensal'!AK$2,0)) -> 0 | AL57: =SUMIFS(#REF!,#REF!, $A57,#REF!, ">="&Z$2,#REF!, "<"&EOMONTH(AK$2,0)) -> 0
A58: CS0000786 | B58: 070065548 | C58: TUV SUD SFDK LABORATORIO DE ANALISE | D58: Ativo | E58: QSMA | F58: SERVIÇOS PRESTADOS | G58: INDUSTRIAL CO | H58: B | I58: TUV SUD SFDK LABORATORIO DE AN | J58: 30 DIAS | K58: COFAB | L58: PRGM . COMPRAS - CO - FABRICA | M58: =SUMIFS(#REF!,#REF!, $A58,#REF!, ">="&'Faturado mensal'!M$2,#REF!, "<"&EOMONTH('Faturado mensal'!M$2,0)) -> 0 | N58: =SUMIFS(#REF!,#REF!, $A58,#REF!, ">="&'Faturado mensal'!N$2,#REF!, "<"&EOMONTH('Faturado mensal'!N$2,0)) -> 0 | O58: =SUMIFS(#REF!,#REF!, $A58,#REF!, ">="&'Faturado mensal'!O$2,#REF!, "<"&EOMONTH('Faturado mensal'!O$2,0)) -> 0 | P58: =SUMIFS(#REF!,#REF!, $A58,#REF!, ">="&'Faturado mensal'!P$2,#REF!, "<"&EOMONTH('Faturado mensal'!P$2,0)) -> 0 | Q58: =SUMIFS(#REF!,#REF!, $A58,#REF!, ">="&'Faturado mensal'!Q$2,#REF!, "<"&EOMONTH('Faturado mensal'!Q$2,0)) -> 0 | R58: =SUMIFS(#REF!,#REF!, $A58,#REF!, ">="&'Faturado mensal'!R$2,#REF!, "<"&EOMONTH('Faturado mensal'!R$2,0)) -> 0 | S58: =SUMIFS(#REF!,#REF!, $A58,#REF!, ">="&'Faturado mensal'!S$2,#REF!, "<"&EOMONTH('Faturado mensal'!S$2,0)) -> 0 | T58: =SUMIFS(#REF!,#REF!, $A58,#REF!, ">="&'Faturado mensal'!T$2,#REF!, "<"&EOMONTH('Faturado mensal'!T$2,0)) -> 0 | ... X58: =SUMIFS(#REF!,#REF!, $A58,#REF!, ">="&'Faturado mensal'!X$2,#REF!, "<"&EOMONTH('Faturado mensal'!X$2,0)) -> 0 | Y58: =SUMIFS(#REF!,#REF!, $A58,#REF!, ">="&'Faturado mensal'!M$2,#REF!, "<"&EOMONTH('Faturado mensal'!M$2,12)) -> 14371.29 | Z58: =SUMIFS(#REF!,#REF!, $A58,#REF!, ">="&'Faturado mensal'!Z$2,#REF!, "<"&EOMONTH('Faturado mensal'!Z$2,0)) -> 0 | AA58: =SUMIFS(#REF!,#REF!, $A58,#REF!, ">="&'Faturado mensal'!AA$2,#REF!, "<"&EOMONTH('Faturado mensal'!AA$2,0)) -> 0 | AB58: =SUMIFS(#REF!,#REF!, $A58,#REF!, ">="&'Faturado mensal'!AB$2,#REF!, "<"&EOMONTH('Faturado mensal'!AB$2,0)) -> 0 | AC58: =SUMIFS(#REF!,#REF!, $A58,#REF!, ">="&'Faturado mensal'!AC$2,#REF!, "<"&EOMONTH('Faturado mensal'!AC$2,0)) -> 0 | AD58: =SUMIFS(#REF!,#REF!, $A58,#REF!, ">="&'Faturado mensal'!AD$2,#REF!, "<"&EOMONTH('Faturado mensal'!AD$2,0)) -> 0 | AE58: =SUMIFS(#REF!,#REF!, $A58,#REF!, ">="&'Faturado mensal'!AE$2,#REF!, "<"&EOMONTH('Faturado mensal'!AE$2,0)) -> 0 | AF58: =SUMIFS(#REF!,#REF!, $A58,#REF!, ">="&'Faturado mensal'!AF$2,#REF!, "<"&EOMONTH('Faturado mensal'!AF$2,0)) -> 0 | AG58: =SUMIFS(#REF!,#REF!, $A58,#REF!, ">="&'Faturado mensal'!AG$2,#REF!, "<"&EOMONTH('Faturado mensal'!AG$2,0)) -> 0 | ... AK58: =SUMIFS(#REF!,#REF!, $A58,#REF!, ">="&'Faturado mensal'!AK$2,#REF!, "<"&EOMONTH('Faturado mensal'!AK$2,0)) -> 0 | AL58: =SUMIFS(#REF!,#REF!, $A58,#REF!, ">="&Z$2,#REF!, "<"&EOMONTH(AK$2,0)) -> 0
A59: CS0000791 | B59: 070000685 | C59: AMPRO LABOR. E ENGa. S/C LTDA | D59: Ativo | E59: QSMA | F59: SERVIÇOS PRESTADOS | G59: INDUSTRIAL CO | H59: B | I59: AMPRO LABOR. E ENGa. S/C LTDA | J59: 30 DIAS | K59: COFAB | L59: PRGM . COMPRAS - CO - FABRICA | M59: =SUMIFS(#REF!,#REF!, $A59,#REF!, ">="&'Faturado mensal'!M$2,#REF!, "<"&EOMONTH('Faturado mensal'!M$2,0)) -> 0 | N59: =SUMIFS(#REF!,#REF!, $A59,#REF!, ">="&'Faturado mensal'!N$2,#REF!, "<"&EOMONTH('Faturado mensal'!N$2,0)) -> 0 | O59: =SUMIFS(#REF!,#REF!, $A59,#REF!, ">="&'Faturado mensal'!O$2,#REF!, "<"&EOMONTH('Faturado mensal'!O$2,0)) -> 1261 | P59: =SUMIFS(#REF!,#REF!, $A59,#REF!, ">="&'Faturado mensal'!P$2,#REF!, "<"&EOMONTH('Faturado mensal'!P$2,0)) -> 0 | Q59: =SUMIFS(#REF!,#REF!, $A59,#REF!, ">="&'Faturado mensal'!Q$2,#REF!, "<"&EOMONTH('Faturado mensal'!Q$2,0)) -> 0 | R59: =SUMIFS(#REF!,#REF!, $A59,#REF!, ">="&'Faturado mensal'!R$2,#REF!, "<"&EOMONTH('Faturado mensal'!R$2,0)) -> 1261 | S59: =SUMIFS(#REF!,#REF!, $A59,#REF!, ">="&'Faturado mensal'!S$2,#REF!, "<"&EOMONTH('Faturado mensal'!S$2,0)) -> 0 | T59: =SUMIFS(#REF!,#REF!, $A59,#REF!, ">="&'Faturado mensal'!T$2,#REF!, "<"&EOMONTH('Faturado mensal'!T$2,0)) -> 0 | ... X59: =SUMIFS(#REF!,#REF!, $A59,#REF!, ">="&'Faturado mensal'!X$2,#REF!, "<"&EOMONTH('Faturado mensal'!X$2,0)) -> 1305 | Y59: =SUMIFS(#REF!,#REF!, $A59,#REF!, ">="&'Faturado mensal'!M$2,#REF!, "<"&EOMONTH('Faturado mensal'!M$2,12)) -> 5132 | Z59: =SUMIFS(#REF!,#REF!, $A59,#REF!, ">="&'Faturado mensal'!Z$2,#REF!, "<"&EOMONTH('Faturado mensal'!Z$2,0)) -> 0 | AA59: =SUMIFS(#REF!,#REF!, $A59,#REF!, ">="&'Faturado mensal'!AA$2,#REF!, "<"&EOMONTH('Faturado mensal'!AA$2,0)) -> 0 | AB59: =SUMIFS(#REF!,#REF!, $A59,#REF!, ">="&'Faturado mensal'!AB$2,#REF!, "<"&EOMONTH('Faturado mensal'!AB$2,0)) -> 1305 | AC59: =SUMIFS(#REF!,#REF!, $A59,#REF!, ">="&'Faturado mensal'!AC$2,#REF!, "<"&EOMONTH('Faturado mensal'!AC$2,0)) -> 0 | AD59: =SUMIFS(#REF!,#REF!, $A59,#REF!, ">="&'Faturado mensal'!AD$2,#REF!, "<"&EOMONTH('Faturado mensal'!AD$2,0)) -> 2215 | AE59: =SUMIFS(#REF!,#REF!, $A59,#REF!, ">="&'Faturado mensal'!AE$2,#REF!, "<"&EOMONTH('Faturado mensal'!AE$2,0)) -> 0 | AF59: =SUMIFS(#REF!,#REF!, $A59,#REF!, ">="&'Faturado mensal'!AF$2,#REF!, "<"&EOMONTH('Faturado mensal'!AF$2,0)) -> 0 | AG59: =SUMIFS(#REF!,#REF!, $A59,#REF!, ">="&'Faturado mensal'!AG$2,#REF!, "<"&EOMONTH('Faturado mensal'!AG$2,0)) -> 0 | ... AK59: =SUMIFS(#REF!,#REF!, $A59,#REF!, ">="&'Faturado mensal'!AK$2,#REF!, "<"&EOMONTH('Faturado mensal'!AK$2,0)) -> 0 | AL59: =SUMIFS(#REF!,#REF!, $A59,#REF!, ">="&Z$2,#REF!, "<"&EOMONTH(AK$2,0)) -> 3520
A60: CS0000795 | B60: 090020157 | C60: SERVICO SOCIAL DA INDUSTRIA | D60: Concluído | G60: INDUSTRIAL CO | H60: C | I60: SERVICO SOCIAL DA INDUSTRIA | J60: 30 DIAS | K60: SRSADM | L60: COMPRAS - SRS - ADMINISTRAÇÃO | M60: =SUMIFS(#REF!,#REF!, $A60,#REF!, ">="&'Faturado mensal'!M$2,#REF!, "<"&EOMONTH('Faturado mensal'!M$2,0)) -> 0 | N60: =SUMIFS(#REF!,#REF!, $A60,#REF!, ">="&'Faturado mensal'!N$2,#REF!, "<"&EOMONTH('Faturado mensal'!N$2,0)) -> 0 | O60: =SUMIFS(#REF!,#REF!, $A60,#REF!, ">="&'Faturado mensal'!O$2,#REF!, "<"&EOMONTH('Faturado mensal'!O$2,0)) -> 0 | P60: =SUMIFS(#REF!,#REF!, $A60,#REF!, ">="&'Faturado mensal'!P$2,#REF!, "<"&EOMONTH('Faturado mensal'!P$2,0)) -> 0 | Q60: =SUMIFS(#REF!,#REF!, $A60,#REF!, ">="&'Faturado mensal'!Q$2,#REF!, "<"&EOMONTH('Faturado mensal'!Q$2,0)) -> 0 | R60: =SUMIFS(#REF!,#REF!, $A60,#REF!, ">="&'Faturado mensal'!R$2,#REF!, "<"&EOMONTH('Faturado mensal'!R$2,0)) -> 0 | S60: =SUMIFS(#REF!,#REF!, $A60,#REF!, ">="&'Faturado mensal'!S$2,#REF!, "<"&EOMONTH('Faturado mensal'!S$2,0)) -> 0 | T60: =SUMIFS(#REF!,#REF!, $A60,#REF!, ">="&'Faturado mensal'!T$2,#REF!, "<"&EOMONTH('Faturado mensal'!T$2,0)) -> 0 | ... X60: =SUMIFS(#REF!,#REF!, $A60,#REF!, ">="&'Faturado mensal'!X$2,#REF!, "<"&EOMONTH('Faturado mensal'!X$2,0)) -> 0 | Y60: =SUMIFS(#REF!,#REF!, $A60,#REF!, ">="&'Faturado mensal'!M$2,#REF!, "<"&EOMONTH('Faturado mensal'!M$2,12)) -> 0 | Z60: =SUMIFS(#REF!,#REF!, $A60,#REF!, ">="&'Faturado mensal'!Z$2,#REF!, "<"&EOMONTH('Faturado mensal'!Z$2,0)) -> 0 | AA60: =SUMIFS(#REF!,#REF!, $A60,#REF!, ">="&'Faturado mensal'!AA$2,#REF!, "<"&EOMONTH('Faturado mensal'!AA$2,0)) -> 0 | AB60: =SUMIFS(#REF!,#REF!, $A60,#REF!, ">="&'Faturado mensal'!AB$2,#REF!, "<"&EOMONTH('Faturado mensal'!AB$2,0)) -> 0 | AC60: =SUMIFS(#REF!,#REF!, $A60,#REF!, ">="&'Faturado mensal'!AC$2,#REF!, "<"&EOMONTH('Faturado mensal'!AC$2,0)) -> 0 | AD60: =SUMIFS(#REF!,#REF!, $A60,#REF!, ">="&'Faturado mensal'!AD$2,#REF!, "<"&EOMONTH('Faturado mensal'!AD$2,0)) -> 0 | AE60: =SUMIFS(#REF!,#REF!, $A60,#REF!, ">="&'Faturado mensal'!AE$2,#REF!, "<"&EOMONTH('Faturado mensal'!AE$2,0)) -> 0 | AF60: =SUMIFS(#REF!,#REF!, $A60,#REF!, ">="&'Faturado mensal'!AF$2,#REF!, "<"&EOMONTH('Faturado mensal'!AF$2,0)) -> 0 | AG60: =SUMIFS(#REF!,#REF!, $A60,#REF!, ">="&'Faturado mensal'!AG$2,#REF!, "<"&EOMONTH('Faturado mensal'!AG$2,0)) -> 0 | ... AK60: =SUMIFS(#REF!,#REF!, $A60,#REF!, ">="&'Faturado mensal'!AK$2,#REF!, "<"&EOMONTH('Faturado mensal'!AK$2,0)) -> 0 | AL60: =SUMIFS(#REF!,#REF!, $A60,#REF!, ">="&Z$2,#REF!, "<"&EOMONTH(AK$2,0)) -> 0
A61: CS0000796 | B61: 090020157 | C61: SERVICO SOCIAL DA INDUSTRIA | D61: Concluído | G61: INDUSTRIAL CO | H61: C | I61: SERVICO SOCIAL DA INDUSTRIA | J61: 30 DIAS | K61: SRSADM | L61: COMPRAS - SRS - ADMINISTRAÇÃO | M61: =SUMIFS(#REF!,#REF!, $A61,#REF!, ">="&'Faturado mensal'!M$2,#REF!, "<"&EOMONTH('Faturado mensal'!M$2,0)) -> 0 | N61: =SUMIFS(#REF!,#REF!, $A61,#REF!, ">="&'Faturado mensal'!N$2,#REF!, "<"&EOMONTH('Faturado mensal'!N$2,0)) -> 0 | O61: =SUMIFS(#REF!,#REF!, $A61,#REF!, ">="&'Faturado mensal'!O$2,#REF!, "<"&EOMONTH('Faturado mensal'!O$2,0)) -> 0 | P61: =SUMIFS(#REF!,#REF!, $A61,#REF!, ">="&'Faturado mensal'!P$2,#REF!, "<"&EOMONTH('Faturado mensal'!P$2,0)) -> 0 | Q61: =SUMIFS(#REF!,#REF!, $A61,#REF!, ">="&'Faturado mensal'!Q$2,#REF!, "<"&EOMONTH('Faturado mensal'!Q$2,0)) -> 0 | R61: =SUMIFS(#REF!,#REF!, $A61,#REF!, ">="&'Faturado mensal'!R$2,#REF!, "<"&EOMONTH('Faturado mensal'!R$2,0)) -> 0 | S61: =SUMIFS(#REF!,#REF!, $A61,#REF!, ">="&'Faturado mensal'!S$2,#REF!, "<"&EOMONTH('Faturado mensal'!S$2,0)) -> 0 | T61: =SUMIFS(#REF!,#REF!, $A61,#REF!, ">="&'Faturado mensal'!T$2,#REF!, "<"&EOMONTH('Faturado mensal'!T$2,0)) -> 0 | ... X61: =SUMIFS(#REF!,#REF!, $A61,#REF!, ">="&'Faturado mensal'!X$2,#REF!, "<"&EOMONTH('Faturado mensal'!X$2,0)) -> 0 | Y61: =SUMIFS(#REF!,#REF!, $A61,#REF!, ">="&'Faturado mensal'!M$2,#REF!, "<"&EOMONTH('Faturado mensal'!M$2,12)) -> 0 | Z61: =SUMIFS(#REF!,#REF!, $A61,#REF!, ">="&'Faturado mensal'!Z$2,#REF!, "<"&EOMONTH('Faturado mensal'!Z$2,0)) -> 0 | AA61: =SUMIFS(#REF!,#REF!, $A61,#REF!, ">="&'Faturado mensal'!AA$2,#REF!, "<"&EOMONTH('Faturado mensal'!AA$2,0)) -> 0 | AB61: =SUMIFS(#REF!,#REF!, $A61,#REF!, ">="&'Faturado mensal'!AB$2,#REF!, "<"&EOMONTH('Faturado mensal'!AB$2,0)) -> 0 | AC61: =SUMIFS(#REF!,#REF!, $A61,#REF!, ">="&'Faturado mensal'!AC$2,#REF!, "<"&EOMONTH('Faturado mensal'!AC$2,0)) -> 0 | AD61: =SUMIFS(#REF!,#REF!, $A61,#REF!, ">="&'Faturado mensal'!AD$2,#REF!, "<"&EOMONTH('Faturado mensal'!AD$2,0)) -> 0 | AE61: =SUMIFS(#REF!,#REF!, $A61,#REF!, ">="&'Faturado mensal'!AE$2,#REF!, "<"&EOMONTH('Faturado mensal'!AE$2,0)) -> 0 | AF61: =SUMIFS(#REF!,#REF!, $A61,#REF!, ">="&'Faturado mensal'!AF$2,#REF!, "<"&EOMONTH('Faturado mensal'!AF$2,0)) -> 0 | AG61: =SUMIFS(#REF!,#REF!, $A61,#REF!, ">="&'Faturado mensal'!AG$2,#REF!, "<"&EOMONTH('Faturado mensal'!AG$2,0)) -> 0 | ... AK61: =SUMIFS(#REF!,#REF!, $A61,#REF!, ">="&'Faturado mensal'!AK$2,#REF!, "<"&EOMONTH('Faturado mensal'!AK$2,0)) -> 0 | AL61: =SUMIFS(#REF!,#REF!, $A61,#REF!, ">="&Z$2,#REF!, "<"&EOMONTH(AK$2,0)) -> 0
A62: CS0000798 | B62: 070075686 | C62: IDIADA TECNOLOGIA AUTOM. LTDA | D62: Concluído | G62: INDUSTRIAL SRS | H62: B | I62: IDIADA TECNOLOGIA AUTOM. LTDA | J62: 30 DIAS | K62: SRSFAB | L62: PRGM . COMPRAS - SRS - FABRICA | M62: =SUMIFS(#REF!,#REF!, $A62,#REF!, ">="&'Faturado mensal'!M$2,#REF!, "<"&EOMONTH('Faturado mensal'!M$2,0)) -> 0 | N62: =SUMIFS(#REF!,#REF!, $A62,#REF!, ">="&'Faturado mensal'!N$2,#REF!, "<"&EOMONTH('Faturado mensal'!N$2,0)) -> 0 | O62: =SUMIFS(#REF!,#REF!, $A62,#REF!, ">="&'Faturado mensal'!O$2,#REF!, "<"&EOMONTH('Faturado mensal'!O$2,0)) -> 0 | P62: =SUMIFS(#REF!,#REF!, $A62,#REF!, ">="&'Faturado mensal'!P$2,#REF!, "<"&EOMONTH('Faturado mensal'!P$2,0)) -> 0 | Q62: =SUMIFS(#REF!,#REF!, $A62,#REF!, ">="&'Faturado mensal'!Q$2,#REF!, "<"&EOMONTH('Faturado mensal'!Q$2,0)) -> 0 | R62: =SUMIFS(#REF!,#REF!, $A62,#REF!, ">="&'Faturado mensal'!R$2,#REF!, "<"&EOMONTH('Faturado mensal'!R$2,0)) -> 0 | S62: =SUMIFS(#REF!,#REF!, $A62,#REF!, ">="&'Faturado mensal'!S$2,#REF!, "<"&EOMONTH('Faturado mensal'!S$2,0)) -> 0 | T62: =SUMIFS(#REF!,#REF!, $A62,#REF!, ">="&'Faturado mensal'!T$2,#REF!, "<"&EOMONTH('Faturado mensal'!T$2,0)) -> 0 | ... X62: =SUMIFS(#REF!,#REF!, $A62,#REF!, ">="&'Faturado mensal'!X$2,#REF!, "<"&EOMONTH('Faturado mensal'!X$2,0)) -> 0 | Y62: =SUMIFS(#REF!,#REF!, $A62,#REF!, ">="&'Faturado mensal'!M$2,#REF!, "<"&EOMONTH('Faturado mensal'!M$2,12)) -> 0 | Z62: =SUMIFS(#REF!,#REF!, $A62,#REF!, ">="&'Faturado mensal'!Z$2,#REF!, "<"&EOMONTH('Faturado mensal'!Z$2,0)) -> 0 | AA62: =SUMIFS(#REF!,#REF!, $A62,#REF!, ">="&'Faturado mensal'!AA$2,#REF!, "<"&EOMONTH('Faturado mensal'!AA$2,0)) -> 0 | AB62: =SUMIFS(#REF!,#REF!, $A62,#REF!, ">="&'Faturado mensal'!AB$2,#REF!, "<"&EOMONTH('Faturado mensal'!AB$2,0)) -> 0 | AC62: =SUMIFS(#REF!,#REF!, $A62,#REF!, ">="&'Faturado mensal'!AC$2,#REF!, "<"&EOMONTH('Faturado mensal'!AC$2,0)) -> 0 | AD62: =SUMIFS(#REF!,#REF!, $A62,#REF!, ">="&'Faturado mensal'!AD$2,#REF!, "<"&EOMONTH('Faturado mensal'!AD$2,0)) -> 0 | AE62: =SUMIFS(#REF!,#REF!, $A62,#REF!, ">="&'Faturado mensal'!AE$2,#REF!, "<"&EOMONTH('Faturado mensal'!AE$2,0)) -> 0 | AF62: =SUMIFS(#REF!,#REF!, $A62,#REF!, ">="&'Faturado mensal'!AF$2,#REF!, "<"&EOMONTH('Faturado mensal'!AF$2,0)) -> 0 | AG62: =SUMIFS(#REF!,#REF!, $A62,#REF!, ">="&'Faturado mensal'!AG$2,#REF!, "<"&EOMONTH('Faturado mensal'!AG$2,0)) -> 0 | ... AK62: =SUMIFS(#REF!,#REF!, $A62,#REF!, ">="&'Faturado mensal'!AK$2,#REF!, "<"&EOMONTH('Faturado mensal'!AK$2,0)) -> 0 | AL62: =SUMIFS(#REF!,#REF!, $A62,#REF!, ">="&Z$2,#REF!, "<"&EOMONTH(AK$2,0)) -> 0
A63: CS0000799 | B63: 070001565 | C63: ADP BRASIL LTDA | D63: Ativo | E63: RECURSOS HUMANOS | F63: SERVIÇOS PRESTADOS | G63: ADMINISTRATIVO | H63: B | I63: ADP BRASIL LTDA | J63: 30 DIAS | K63: SRSADM | L63: COMPRAS - SRS - ADMINISTRAÇÃO | M63: =SUMIFS(#REF!,#REF!, $A63,#REF!, ">="&'Faturado mensal'!M$2,#REF!, "<"&EOMONTH('Faturado mensal'!M$2,0)) -> 49368.88 | N63: =SUMIFS(#REF!,#REF!, $A63,#REF!, ">="&'Faturado mensal'!N$2,#REF!, "<"&EOMONTH('Faturado mensal'!N$2,0)) -> 31199.93 | O63: =SUMIFS(#REF!,#REF!, $A63,#REF!, ">="&'Faturado mensal'!O$2,#REF!, "<"&EOMONTH('Faturado mensal'!O$2,0)) -> 31231.73 | P63: =SUMIFS(#REF!,#REF!, $A63,#REF!, ">="&'Faturado mensal'!P$2,#REF!, "<"&EOMONTH('Faturado mensal'!P$2,0)) -> 31263.54 | Q63: =SUMIFS(#REF!,#REF!, $A63,#REF!, ">="&'Faturado mensal'!Q$2,#REF!, "<"&EOMONTH('Faturado mensal'!Q$2,0)) -> 39802.58 | R63: =SUMIFS(#REF!,#REF!, $A63,#REF!, ">="&'Faturado mensal'!R$2,#REF!, "<"&EOMONTH('Faturado mensal'!R$2,0)) -> 42185.55 | S63: =SUMIFS(#REF!,#REF!, $A63,#REF!, ">="&'Faturado mensal'!S$2,#REF!, "<"&EOMONTH('Faturado mensal'!S$2,0)) -> 37586.8 | T63: =SUMIFS(#REF!,#REF!, $A63,#REF!, ">="&'Faturado mensal'!T$2,#REF!, "<"&EOMONTH('Faturado mensal'!T$2,0)) -> 37808.76 | ... X63: =SUMIFS(#REF!,#REF!, $A63,#REF!, ">="&'Faturado mensal'!X$2,#REF!, "<"&EOMONTH('Faturado mensal'!X$2,0)) -> 55056.25 | Y63: =SUMIFS(#REF!,#REF!, $A63,#REF!, ">="&'Faturado mensal'!M$2,#REF!, "<"&EOMONTH('Faturado mensal'!M$2,12)) -> 521141.27 | Z63: =SUMIFS(#REF!,#REF!, $A63,#REF!, ">="&'Faturado mensal'!Z$2,#REF!, "<"&EOMONTH('Faturado mensal'!Z$2,0)) -> 54100.45 | AA63: =SUMIFS(#REF!,#REF!, $A63,#REF!, ">="&'Faturado mensal'!AA$2,#REF!, "<"&EOMONTH('Faturado mensal'!AA$2,0)) -> 35917.59 | AB63: =SUMIFS(#REF!,#REF!, $A63,#REF!, ">="&'Faturado mensal'!AB$2,#REF!, "<"&EOMONTH('Faturado mensal'!AB$2,0)) -> 36365.62 | AC63: =SUMIFS(#REF!,#REF!, $A63,#REF!, ">="&'Faturado mensal'!AC$2,#REF!, "<"&EOMONTH('Faturado mensal'!AC$2,0)) -> 38232.45 | AD63: =SUMIFS(#REF!,#REF!, $A63,#REF!, ">="&'Faturado mensal'!AD$2,#REF!, "<"&EOMONTH('Faturado mensal'!AD$2,0)) -> 38568.47 | AE63: =SUMIFS(#REF!,#REF!, $A63,#REF!, ">="&'Faturado mensal'!AE$2,#REF!, "<"&EOMONTH('Faturado mensal'!AE$2,0)) -> 0 | AF63: =SUMIFS(#REF!,#REF!, $A63,#REF!, ">="&'Faturado mensal'!AF$2,#REF!, "<"&EOMONTH('Faturado mensal'!AF$2,0)) -> 0 | AG63: =SUMIFS(#REF!,#REF!, $A63,#REF!, ">="&'Faturado mensal'!AG$2,#REF!, "<"&EOMONTH('Faturado mensal'!AG$2,0)) -> 0 | ... AK63: =SUMIFS(#REF!,#REF!, $A63,#REF!, ">="&'Faturado mensal'!AK$2,#REF!, "<"&EOMONTH('Faturado mensal'!AK$2,0)) -> 0 | AL63: =SUMIFS(#REF!,#REF!, $A63,#REF!, ">="&Z$2,#REF!, "<"&EOMONTH(AK$2,0)) -> 203184.58
A64: CS0000801 | B64: 070076175 | C64: ANDREA CARVALHO DESP.EIRELI-ME | D64: Ativo | E64: MANUFATURA CO | F64: SERVIÇOS PRESTADOS | G64: INDUSTRIAL CO | H64: C | I64: ANDREA CARVALHO DESP.EIRELI-ME | J64: 30 DIAS | K64: COFAB | L64: PRGM . COMPRAS - CO - FABRICA | M64: =SUMIFS(#REF!,#REF!, $A64,#REF!, ">="&'Faturado mensal'!M$2,#REF!, "<"&EOMONTH('Faturado mensal'!M$2,0)) -> 0 | N64: =SUMIFS(#REF!,#REF!, $A64,#REF!, ">="&'Faturado mensal'!N$2,#REF!, "<"&EOMONTH('Faturado mensal'!N$2,0)) -> 600 | O64: =SUMIFS(#REF!,#REF!, $A64,#REF!, ">="&'Faturado mensal'!O$2,#REF!, "<"&EOMONTH('Faturado mensal'!O$2,0)) -> 0 | P64: =SUMIFS(#REF!,#REF!, $A64,#REF!, ">="&'Faturado mensal'!P$2,#REF!, "<"&EOMONTH('Faturado mensal'!P$2,0)) -> 0 | Q64: =SUMIFS(#REF!,#REF!, $A64,#REF!, ">="&'Faturado mensal'!Q$2,#REF!, "<"&EOMONTH('Faturado mensal'!Q$2,0)) -> 0 | R64: =SUMIFS(#REF!,#REF!, $A64,#REF!, ">="&'Faturado mensal'!R$2,#REF!, "<"&EOMONTH('Faturado mensal'!R$2,0)) -> 1500 | S64: =SUMIFS(#REF!,#REF!, $A64,#REF!, ">="&'Faturado mensal'!S$2,#REF!, "<"&EOMONTH('Faturado mensal'!S$2,0)) -> 0 | T64: =SUMIFS(#REF!,#REF!, $A64,#REF!, ">="&'Faturado mensal'!T$2,#REF!, "<"&EOMONTH('Faturado mensal'!T$2,0)) -> 0 | ... X64: =SUMIFS(#REF!,#REF!, $A64,#REF!, ">="&'Faturado mensal'!X$2,#REF!, "<"&EOMONTH('Faturado mensal'!X$2,0)) -> 0 | Y64: =SUMIFS(#REF!,#REF!, $A64,#REF!, ">="&'Faturado mensal'!M$2,#REF!, "<"&EOMONTH('Faturado mensal'!M$2,12)) -> 2100 | Z64: =SUMIFS(#REF!,#REF!, $A64,#REF!, ">="&'Faturado mensal'!Z$2,#REF!, "<"&EOMONTH('Faturado mensal'!Z$2,0)) -> 0 | AA64: =SUMIFS(#REF!,#REF!, $A64,#REF!, ">="&'Faturado mensal'!AA$2,#REF!, "<"&EOMONTH('Faturado mensal'!AA$2,0)) -> 600 | AB64: =SUMIFS(#REF!,#REF!, $A64,#REF!, ">="&'Faturado mensal'!AB$2,#REF!, "<"&EOMONTH('Faturado mensal'!AB$2,0)) -> 0 | AC64: =SUMIFS(#REF!,#REF!, $A64,#REF!, ">="&'Faturado mensal'!AC$2,#REF!, "<"&EOMONTH('Faturado mensal'!AC$2,0)) -> 0 | AD64: =SUMIFS(#REF!,#REF!, $A64,#REF!, ">="&'Faturado mensal'!AD$2,#REF!, "<"&EOMONTH('Faturado mensal'!AD$2,0)) -> 0 | AE64: =SUMIFS(#REF!,#REF!, $A64,#REF!, ">="&'Faturado mensal'!AE$2,#REF!, "<"&EOMONTH('Faturado mensal'!AE$2,0)) -> 0 | AF64: =SUMIFS(#REF!,#REF!, $A64,#REF!, ">="&'Faturado mensal'!AF$2,#REF!, "<"&EOMONTH('Faturado mensal'!AF$2,0)) -> 0 | AG64: =SUMIFS(#REF!,#REF!, $A64,#REF!, ">="&'Faturado mensal'!AG$2,#REF!, "<"&EOMONTH('Faturado mensal'!AG$2,0)) -> 0 | ... AK64: =SUMIFS(#REF!,#REF!, $A64,#REF!, ">="&'Faturado mensal'!AK$2,#REF!, "<"&EOMONTH('Faturado mensal'!AK$2,0)) -> 0 | AL64: =SUMIFS(#REF!,#REF!, $A64,#REF!, ">="&Z$2,#REF!, "<"&EOMONTH(AK$2,0)) -> 600
A65: CS0000802 | B65: 070076126 | C65: PAULO ROGERIO DE LIMA | D65: Concluído | E65: RECURSOS HUMANOS | F65: SERVIÇOS PRESTADOS | G65: ADMINISTRATIVO | I65: PAULO ROGERIO DE LIMA | J65: 30 DIAS | K65: VIESPD | L65: COMPRAS - VIES - OC (IM)PRODUT | M65: =SUMIFS(#REF!,#REF!, $A65,#REF!, ">="&'Faturado mensal'!M$2,#REF!, "<"&EOMONTH('Faturado mensal'!M$2,0)) -> 14826 | N65: =SUMIFS(#REF!,#REF!, $A65,#REF!, ">="&'Faturado mensal'!N$2,#REF!, "<"&EOMONTH('Faturado mensal'!N$2,0)) -> 18228 | O65: =SUMIFS(#REF!,#REF!, $A65,#REF!, ">="&'Faturado mensal'!O$2,#REF!, "<"&EOMONTH('Faturado mensal'!O$2,0)) -> 19194 | P65: =SUMIFS(#REF!,#REF!, $A65,#REF!, ">="&'Faturado mensal'!P$2,#REF!, "<"&EOMONTH('Faturado mensal'!P$2,0)) -> 0 | Q65: =SUMIFS(#REF!,#REF!, $A65,#REF!, ">="&'Faturado mensal'!Q$2,#REF!, "<"&EOMONTH('Faturado mensal'!Q$2,0)) -> 0 | R65: =SUMIFS(#REF!,#REF!, $A65,#REF!, ">="&'Faturado mensal'!R$2,#REF!, "<"&EOMONTH('Faturado mensal'!R$2,0)) -> 0 | S65: =SUMIFS(#REF!,#REF!, $A65,#REF!, ">="&'Faturado mensal'!S$2,#REF!, "<"&EOMONTH('Faturado mensal'!S$2,0)) -> 0 | T65: =SUMIFS(#REF!,#REF!, $A65,#REF!, ">="&'Faturado mensal'!T$2,#REF!, "<"&EOMONTH('Faturado mensal'!T$2,0)) -> 0 | ... X65: =SUMIFS(#REF!,#REF!, $A65,#REF!, ">="&'Faturado mensal'!X$2,#REF!, "<"&EOMONTH('Faturado mensal'!X$2,0)) -> 0 | Y65: =SUMIFS(#REF!,#REF!, $A65,#REF!, ">="&'Faturado mensal'!M$2,#REF!, "<"&EOMONTH('Faturado mensal'!M$2,12)) -> 52248 | Z65: =SUMIFS(#REF!,#REF!, $A65,#REF!, ">="&'Faturado mensal'!Z$2,#REF!, "<"&EOMONTH('Faturado mensal'!Z$2,0)) -> 0 | AA65: =SUMIFS(#REF!,#REF!, $A65,#REF!, ">="&'Faturado mensal'!AA$2,#REF!, "<"&EOMONTH('Faturado mensal'!AA$2,0)) -> 0 | AB65: =SUMIFS(#REF!,#REF!, $A65,#REF!, ">="&'Faturado mensal'!AB$2,#REF!, "<"&EOMONTH('Faturado mensal'!AB$2,0)) -> 0 | AC65: =SUMIFS(#REF!,#REF!, $A65,#REF!, ">="&'Faturado mensal'!AC$2,#REF!, "<"&EOMONTH('Faturado mensal'!AC$2,0)) -> 0 | AD65: =SUMIFS(#REF!,#REF!, $A65,#REF!, ">="&'Faturado mensal'!AD$2,#REF!, "<"&EOMONTH('Faturado mensal'!AD$2,0)) -> 0 | AE65: =SUMIFS(#REF!,#REF!, $A65,#REF!, ">="&'Faturado mensal'!AE$2,#REF!, "<"&EOMONTH('Faturado mensal'!AE$2,0)) -> 0 | AF65: =SUMIFS(#REF!,#REF!, $A65,#REF!, ">="&'Faturado mensal'!AF$2,#REF!, "<"&EOMONTH('Faturado mensal'!AF$2,0)) -> 0 | AG65: =SUMIFS(#REF!,#REF!, $A65,#REF!, ">="&'Faturado mensal'!AG$2,#REF!, "<"&EOMONTH('Faturado mensal'!AG$2,0)) -> 0 | ... AK65: =SUMIFS(#REF!,#REF!, $A65,#REF!, ">="&'Faturado mensal'!AK$2,#REF!, "<"&EOMONTH('Faturado mensal'!AK$2,0)) -> 0 | AL65: =SUMIFS(#REF!,#REF!, $A65,#REF!, ">="&Z$2,#REF!, "<"&EOMONTH(AK$2,0)) -> 0
A66: CS0000803 | B66: 070007045 | C66: ADUANEIRAS INFORMATICA LTDA | D66: Ativo | E66: SUPPLY | F66: LICENÇAS IMPORTAÇÃO | G66: SUPPLY | I66: ADUANEIRAS INFORMATICA LTDA | J66: 30 DIAS | K66: VIESAD | L66: COMPRAS - VIES - ADMINISTRAÇAO | M66: =SUMIFS(#REF!,#REF!, $A66,#REF!, ">="&'Faturado mensal'!M$2,#REF!, "<"&EOMONTH('Faturado mensal'!M$2,0)) -> 0 | N66: =SUMIFS(#REF!,#REF!, $A66,#REF!, ">="&'Faturado mensal'!N$2,#REF!, "<"&EOMONTH('Faturado mensal'!N$2,0)) -> 0 | O66: =SUMIFS(#REF!,#REF!, $A66,#REF!, ">="&'Faturado mensal'!O$2,#REF!, "<"&EOMONTH('Faturado mensal'!O$2,0)) -> 0 | P66: =SUMIFS(#REF!,#REF!, $A66,#REF!, ">="&'Faturado mensal'!P$2,#REF!, "<"&EOMONTH('Faturado mensal'!P$2,0)) -> 0 | Q66: =SUMIFS(#REF!,#REF!, $A66,#REF!, ">="&'Faturado mensal'!Q$2,#REF!, "<"&EOMONTH('Faturado mensal'!Q$2,0)) -> 0 | R66: =SUMIFS(#REF!,#REF!, $A66,#REF!, ">="&'Faturado mensal'!R$2,#REF!, "<"&EOMONTH('Faturado mensal'!R$2,0)) -> 0 | S66: =SUMIFS(#REF!,#REF!, $A66,#REF!, ">="&'Faturado mensal'!S$2,#REF!, "<"&EOMONTH('Faturado mensal'!S$2,0)) -> 0 | T66: =SUMIFS(#REF!,#REF!, $A66,#REF!, ">="&'Faturado mensal'!T$2,#REF!, "<"&EOMONTH('Faturado mensal'!T$2,0)) -> 0 | ... X66: =SUMIFS(#REF!,#REF!, $A66,#REF!, ">="&'Faturado mensal'!X$2,#REF!, "<"&EOMONTH('Faturado mensal'!X$2,0)) -> 0 | Y66: =SUMIFS(#REF!,#REF!, $A66,#REF!, ">="&'Faturado mensal'!M$2,#REF!, "<"&EOMONTH('Faturado mensal'!M$2,12)) -> 4357 | Z66: =SUMIFS(#REF!,#REF!, $A66,#REF!, ">="&'Faturado mensal'!Z$2,#REF!, "<"&EOMONTH('Faturado mensal'!Z$2,0)) -> 0 | AA66: =SUMIFS(#REF!,#REF!, $A66,#REF!, ">="&'Faturado mensal'!AA$2,#REF!, "<"&EOMONTH('Faturado mensal'!AA$2,0)) -> 0 | AB66: =SUMIFS(#REF!,#REF!, $A66,#REF!, ">="&'Faturado mensal'!AB$2,#REF!, "<"&EOMONTH('Faturado mensal'!AB$2,0)) -> 0 | AC66: =SUMIFS(#REF!,#REF!, $A66,#REF!, ">="&'Faturado mensal'!AC$2,#REF!, "<"&EOMONTH('Faturado mensal'!AC$2,0)) -> 0 | AD66: =SUMIFS(#REF!,#REF!, $A66,#REF!, ">="&'Faturado mensal'!AD$2,#REF!, "<"&EOMONTH('Faturado mensal'!AD$2,0)) -> 0 | AE66: =SUMIFS(#REF!,#REF!, $A66,#REF!, ">="&'Faturado mensal'!AE$2,#REF!, "<"&EOMONTH('Faturado mensal'!AE$2,0)) -> 0 | AF66: =SUMIFS(#REF!,#REF!, $A66,#REF!, ">="&'Faturado mensal'!AF$2,#REF!, "<"&EOMONTH('Faturado mensal'!AF$2,0)) -> 0 | AG66: =SUMIFS(#REF!,#REF!, $A66,#REF!, ">="&'Faturado mensal'!AG$2,#REF!, "<"&EOMONTH('Faturado mensal'!AG$2,0)) -> 0 | ... AK66: =SUMIFS(#REF!,#REF!, $A66,#REF!, ">="&'Faturado mensal'!AK$2,#REF!, "<"&EOMONTH('Faturado mensal'!AK$2,0)) -> 0 | AL66: =SUMIFS(#REF!,#REF!, $A66,#REF!, ">="&Z$2,#REF!, "<"&EOMONTH(AK$2,0)) -> 0
A67: CS0000805 | B67: 090010054 | C67: VERZANI E SANDRINI LTDA | D67: Concluído | E67: SEGURANÇA PATRIMONIAL | F67: VIGILANCIA/PORTARIA | G67: SUPPLY | H67: A | I67: VERZANI E SANDRINI LTDA | J67: 30 DIAS | K67: VIESFB | L67: PRGM .COMPRAS - VIES - FABRICA | M67: =SUMIFS(#REF!,#REF!, $A67,#REF!, ">="&'Faturado mensal'!M$2,#REF!, "<"&EOMONTH('Faturado mensal'!M$2,0)) -> 0 | N67: =SUMIFS(#REF!,#REF!, $A67,#REF!, ">="&'Faturado mensal'!N$2,#REF!, "<"&EOMONTH('Faturado mensal'!N$2,0)) -> 0 | O67: =SUMIFS(#REF!,#REF!, $A67,#REF!, ">="&'Faturado mensal'!O$2,#REF!, "<"&EOMONTH('Faturado mensal'!O$2,0)) -> 0 | P67: =SUMIFS(#REF!,#REF!, $A67,#REF!, ">="&'Faturado mensal'!P$2,#REF!, "<"&EOMONTH('Faturado mensal'!P$2,0)) -> 0 | Q67: =SUMIFS(#REF!,#REF!, $A67,#REF!, ">="&'Faturado mensal'!Q$2,#REF!, "<"&EOMONTH('Faturado mensal'!Q$2,0)) -> 0 | R67: =SUMIFS(#REF!,#REF!, $A67,#REF!, ">="&'Faturado mensal'!R$2,#REF!, "<"&EOMONTH('Faturado mensal'!R$2,0)) -> 0 | S67: =SUMIFS(#REF!,#REF!, $A67,#REF!, ">="&'Faturado mensal'!S$2,#REF!, "<"&EOMONTH('Faturado mensal'!S$2,0)) -> 0 | T67: =SUMIFS(#REF!,#REF!, $A67,#REF!, ">="&'Faturado mensal'!T$2,#REF!, "<"&EOMONTH('Faturado mensal'!T$2,0)) -> 0 | ... X67: =SUMIFS(#REF!,#REF!, $A67,#REF!, ">="&'Faturado mensal'!X$2,#REF!, "<"&EOMONTH('Faturado mensal'!X$2,0)) -> 0 | Y67: =SUMIFS(#REF!,#REF!, $A67,#REF!, ">="&'Faturado mensal'!M$2,#REF!, "<"&EOMONTH('Faturado mensal'!M$2,12)) -> 0 | Z67: =SUMIFS(#REF!,#REF!, $A67,#REF!, ">="&'Faturado mensal'!Z$2,#REF!, "<"&EOMONTH('Faturado mensal'!Z$2,0)) -> 0 | AA67: =SUMIFS(#REF!,#REF!, $A67,#REF!, ">="&'Faturado mensal'!AA$2,#REF!, "<"&EOMONTH('Faturado mensal'!AA$2,0)) -> 0 | AB67: =SUMIFS(#REF!,#REF!, $A67,#REF!, ">="&'Faturado mensal'!AB$2,#REF!, "<"&EOMONTH('Faturado mensal'!AB$2,0)) -> 0 | AC67: =SUMIFS(#REF!,#REF!, $A67,#REF!, ">="&'Faturado mensal'!AC$2,#REF!, "<"&EOMONTH('Faturado mensal'!AC$2,0)) -> 0 | AD67: =SUMIFS(#REF!,#REF!, $A67,#REF!, ">="&'Faturado mensal'!AD$2,#REF!, "<"&EOMONTH('Faturado mensal'!AD$2,0)) -> 0 | AE67: =SUMIFS(#REF!,#REF!, $A67,#REF!, ">="&'Faturado mensal'!AE$2,#REF!, "<"&EOMONTH('Faturado mensal'!AE$2,0)) -> 0 | AF67: =SUMIFS(#REF!,#REF!, $A67,#REF!, ">="&'Faturado mensal'!AF$2,#REF!, "<"&EOMONTH('Faturado mensal'!AF$2,0)) -> 0 | AG67: =SUMIFS(#REF!,#REF!, $A67,#REF!, ">="&'Faturado mensal'!AG$2,#REF!, "<"&EOMONTH('Faturado mensal'!AG$2,0)) -> 0 | ... AK67: =SUMIFS(#REF!,#REF!, $A67,#REF!, ">="&'Faturado mensal'!AK$2,#REF!, "<"&EOMONTH('Faturado mensal'!AK$2,0)) -> 0 | AL67: =SUMIFS(#REF!,#REF!, $A67,#REF!, ">="&Z$2,#REF!, "<"&EOMONTH(AK$2,0)) -> 0
A68: CS0000807 | B68: 070076481 | C68: SMART INTELIGENCIA EMPRESARIAL | D68: Concluído | I68: SMART INTELIGENCIA EMPRESARIAL | J68: 30 DIAS | K68: VIESFB | L68: PRGM .COMPRAS - VIES - FABRICA | M68: =SUMIFS(#REF!,#REF!, $A68,#REF!, ">="&'Faturado mensal'!M$2,#REF!, "<"&EOMONTH('Faturado mensal'!M$2,0)) -> 0 | N68: =SUMIFS(#REF!,#REF!, $A68,#REF!, ">="&'Faturado mensal'!N$2,#REF!, "<"&EOMONTH('Faturado mensal'!N$2,0)) -> 0 | O68: =SUMIFS(#REF!,#REF!, $A68,#REF!, ">="&'Faturado mensal'!O$2,#REF!, "<"&EOMONTH('Faturado mensal'!O$2,0)) -> 0 | P68: =SUMIFS(#REF!,#REF!, $A68,#REF!, ">="&'Faturado mensal'!P$2,#REF!, "<"&EOMONTH('Faturado mensal'!P$2,0)) -> 0 | Q68: =SUMIFS(#REF!,#REF!, $A68,#REF!, ">="&'Faturado mensal'!Q$2,#REF!, "<"&EOMONTH('Faturado mensal'!Q$2,0)) -> 0 | R68: =SUMIFS(#REF!,#REF!, $A68,#REF!, ">="&'Faturado mensal'!R$2,#REF!, "<"&EOMONTH('Faturado mensal'!R$2,0)) -> 0 | S68: =SUMIFS(#REF!,#REF!, $A68,#REF!, ">="&'Faturado mensal'!S$2,#REF!, "<"&EOMONTH('Faturado mensal'!S$2,0)) -> 0 | T68: =SUMIFS(#REF!,#REF!, $A68,#REF!, ">="&'Faturado mensal'!T$2,#REF!, "<"&EOMONTH('Faturado mensal'!T$2,0)) -> 0 | ... X68: =SUMIFS(#REF!,#REF!, $A68,#REF!, ">="&'Faturado mensal'!X$2,#REF!, "<"&EOMONTH('Faturado mensal'!X$2,0)) -> 0 | Y68: =SUMIFS(#REF!,#REF!, $A68,#REF!, ">="&'Faturado mensal'!M$2,#REF!, "<"&EOMONTH('Faturado mensal'!M$2,12)) -> 0 | Z68: =SUMIFS(#REF!,#REF!, $A68,#REF!, ">="&'Faturado mensal'!Z$2,#REF!, "<"&EOMONTH('Faturado mensal'!Z$2,0)) -> 0 | AA68: =SUMIFS(#REF!,#REF!, $A68,#REF!, ">="&'Faturado mensal'!AA$2,#REF!, "<"&EOMONTH('Faturado mensal'!AA$2,0)) -> 0 | AB68: =SUMIFS(#REF!,#REF!, $A68,#REF!, ">="&'Faturado mensal'!AB$2,#REF!, "<"&EOMONTH('Faturado mensal'!AB$2,0)) -> 0 | AC68: =SUMIFS(#REF!,#REF!, $A68,#REF!, ">="&'Faturado mensal'!AC$2,#REF!, "<"&EOMONTH('Faturado mensal'!AC$2,0)) -> 0 | AD68: =SUMIFS(#REF!,#REF!, $A68,#REF!, ">="&'Faturado mensal'!AD$2,#REF!, "<"&EOMONTH('Faturado mensal'!AD$2,0)) -> 0 | AE68: =SUMIFS(#REF!,#REF!, $A68,#REF!, ">="&'Faturado mensal'!AE$2,#REF!, "<"&EOMONTH('Faturado mensal'!AE$2,0)) -> 0 | AF68: =SUMIFS(#REF!,#REF!, $A68,#REF!, ">="&'Faturado mensal'!AF$2,#REF!, "<"&EOMONTH('Faturado mensal'!AF$2,0)) -> 0 | AG68: =SUMIFS(#REF!,#REF!, $A68,#REF!, ">="&'Faturado mensal'!AG$2,#REF!, "<"&EOMONTH('Faturado mensal'!AG$2,0)) -> 0 | ... AK68: =SUMIFS(#REF!,#REF!, $A68,#REF!, ">="&'Faturado mensal'!AK$2,#REF!, "<"&EOMONTH('Faturado mensal'!AK$2,0)) -> 0 | AL68: =SUMIFS(#REF!,#REF!, $A68,#REF!, ">="&Z$2,#REF!, "<"&EOMONTH(AK$2,0)) -> 0
A69: CS0000808 | B69: 090095564 | C69: SMARTPLM SOL.SERV.T.I.LTDA | D69: Concluído | F69: SERVIÇOS PRESTADOS | G69: INDUSTRIAL VIES | H69: B | I69: SMARTPLM SOL.SERV.T.I.LTDA | J69: 30 DIAS | K69: VIESFB | L69: PRGM .COMPRAS - VIES - FABRICA | M69: =SUMIFS(#REF!,#REF!, $A69,#REF!, ">="&'Faturado mensal'!M$2,#REF!, "<"&EOMONTH('Faturado mensal'!M$2,0)) -> 0 | N69: =SUMIFS(#REF!,#REF!, $A69,#REF!, ">="&'Faturado mensal'!N$2,#REF!, "<"&EOMONTH('Faturado mensal'!N$2,0)) -> 0 | O69: =SUMIFS(#REF!,#REF!, $A69,#REF!, ">="&'Faturado mensal'!O$2,#REF!, "<"&EOMONTH('Faturado mensal'!O$2,0)) -> 0 | P69: =SUMIFS(#REF!,#REF!, $A69,#REF!, ">="&'Faturado mensal'!P$2,#REF!, "<"&EOMONTH('Faturado mensal'!P$2,0)) -> 0 | Q69: =SUMIFS(#REF!,#REF!, $A69,#REF!, ">="&'Faturado mensal'!Q$2,#REF!, "<"&EOMONTH('Faturado mensal'!Q$2,0)) -> 0 | R69: =SUMIFS(#REF!,#REF!, $A69,#REF!, ">="&'Faturado mensal'!R$2,#REF!, "<"&EOMONTH('Faturado mensal'!R$2,0)) -> 0 | S69: =SUMIFS(#REF!,#REF!, $A69,#REF!, ">="&'Faturado mensal'!S$2,#REF!, "<"&EOMONTH('Faturado mensal'!S$2,0)) -> 0 | T69: =SUMIFS(#REF!,#REF!, $A69,#REF!, ">="&'Faturado mensal'!T$2,#REF!, "<"&EOMONTH('Faturado mensal'!T$2,0)) -> 0 | ... X69: =SUMIFS(#REF!,#REF!, $A69,#REF!, ">="&'Faturado mensal'!X$2,#REF!, "<"&EOMONTH('Faturado mensal'!X$2,0)) -> 0 | Y69: =SUMIFS(#REF!,#REF!, $A69,#REF!, ">="&'Faturado mensal'!M$2,#REF!, "<"&EOMONTH('Faturado mensal'!M$2,12)) -> 0 | Z69: =SUMIFS(#REF!,#REF!, $A69,#REF!, ">="&'Faturado mensal'!Z$2,#REF!, "<"&EOMONTH('Faturado mensal'!Z$2,0)) -> 0 | AA69: =SUMIFS(#REF!,#REF!, $A69,#REF!, ">="&'Faturado mensal'!AA$2,#REF!, "<"&EOMONTH('Faturado mensal'!AA$2,0)) -> 0 | AB69: =SUMIFS(#REF!,#REF!, $A69,#REF!, ">="&'Faturado mensal'!AB$2,#REF!, "<"&EOMONTH('Faturado mensal'!AB$2,0)) -> 0 | AC69: =SUMIFS(#REF!,#REF!, $A69,#REF!, ">="&'Faturado mensal'!AC$2,#REF!, "<"&EOMONTH('Faturado mensal'!AC$2,0)) -> 0 | AD69: =SUMIFS(#REF!,#REF!, $A69,#REF!, ">="&'Faturado mensal'!AD$2,#REF!, "<"&EOMONTH('Faturado mensal'!AD$2,0)) -> 0 | AE69: =SUMIFS(#REF!,#REF!, $A69,#REF!, ">="&'Faturado mensal'!AE$2,#REF!, "<"&EOMONTH('Faturado mensal'!AE$2,0)) -> 0 | AF69: =SUMIFS(#REF!,#REF!, $A69,#REF!, ">="&'Faturado mensal'!AF$2,#REF!, "<"&EOMONTH('Faturado mensal'!AF$2,0)) -> 0 | AG69: =SUMIFS(#REF!,#REF!, $A69,#REF!, ">="&'Faturado mensal'!AG$2,#REF!, "<"&EOMONTH('Faturado mensal'!AG$2,0)) -> 0 | ... AK69: =SUMIFS(#REF!,#REF!, $A69,#REF!, ">="&'Faturado mensal'!AK$2,#REF!, "<"&EOMONTH('Faturado mensal'!AK$2,0)) -> 0 | AL69: =SUMIFS(#REF!,#REF!, $A69,#REF!, ">="&Z$2,#REF!, "<"&EOMONTH(AK$2,0)) -> 0
A70: CS0000811 | B70: 090010234 | C70: ALINE DE PAULA ALMEIDA | D70: Concluído | I70: ALINE DE PAULA ALMEIDA | J70: 30 DIAS | K70: SRSFAB | L70: PRGM . COMPRAS - SRS - FABRICA | M70: =SUMIFS(#REF!,#REF!, $A70,#REF!, ">="&'Faturado mensal'!M$2,#REF!, "<"&EOMONTH('Faturado mensal'!M$2,0)) -> 0 | N70: =SUMIFS(#REF!,#REF!, $A70,#REF!, ">="&'Faturado mensal'!N$2,#REF!, "<"&EOMONTH('Faturado mensal'!N$2,0)) -> 0 | O70: =SUMIFS(#REF!,#REF!, $A70,#REF!, ">="&'Faturado mensal'!O$2,#REF!, "<"&EOMONTH('Faturado mensal'!O$2,0)) -> 0 | P70: =SUMIFS(#REF!,#REF!, $A70,#REF!, ">="&'Faturado mensal'!P$2,#REF!, "<"&EOMONTH('Faturado mensal'!P$2,0)) -> 0 | Q70: =SUMIFS(#REF!,#REF!, $A70,#REF!, ">="&'Faturado mensal'!Q$2,#REF!, "<"&EOMONTH('Faturado mensal'!Q$2,0)) -> 0 | R70: =SUMIFS(#REF!,#REF!, $A70,#REF!, ">="&'Faturado mensal'!R$2,#REF!, "<"&EOMONTH('Faturado mensal'!R$2,0)) -> 0 | S70: =SUMIFS(#REF!,#REF!, $A70,#REF!, ">="&'Faturado mensal'!S$2,#REF!, "<"&EOMONTH('Faturado mensal'!S$2,0)) -> 0 | T70: =SUMIFS(#REF!,#REF!, $A70,#REF!, ">="&'Faturado mensal'!T$2,#REF!, "<"&EOMONTH('Faturado mensal'!T$2,0)) -> 0 | ... X70: =SUMIFS(#REF!,#REF!, $A70,#REF!, ">="&'Faturado mensal'!X$2,#REF!, "<"&EOMONTH('Faturado mensal'!X$2,0)) -> 0 | Y70: =SUMIFS(#REF!,#REF!, $A70,#REF!, ">="&'Faturado mensal'!M$2,#REF!, "<"&EOMONTH('Faturado mensal'!M$2,12)) -> 0 | Z70: =SUMIFS(#REF!,#REF!, $A70,#REF!, ">="&'Faturado mensal'!Z$2,#REF!, "<"&EOMONTH('Faturado mensal'!Z$2,0)) -> 0 | AA70: =SUMIFS(#REF!,#REF!, $A70,#REF!, ">="&'Faturado mensal'!AA$2,#REF!, "<"&EOMONTH('Faturado mensal'!AA$2,0)) -> 0 | AB70: =SUMIFS(#REF!,#REF!, $A70,#REF!, ">="&'Faturado mensal'!AB$2,#REF!, "<"&EOMONTH('Faturado mensal'!AB$2,0)) -> 0 | AC70: =SUMIFS(#REF!,#REF!, $A70,#REF!, ">="&'Faturado mensal'!AC$2,#REF!, "<"&EOMONTH('Faturado mensal'!AC$2,0)) -> 0 | AD70: =SUMIFS(#REF!,#REF!, $A70,#REF!, ">="&'Faturado mensal'!AD$2,#REF!, "<"&EOMONTH('Faturado mensal'!AD$2,0)) -> 0 | AE70: =SUMIFS(#REF!,#REF!, $A70,#REF!, ">="&'Faturado mensal'!AE$2,#REF!, "<"&EOMONTH('Faturado mensal'!AE$2,0)) -> 0 | AF70: =SUMIFS(#REF!,#REF!, $A70,#REF!, ">="&'Faturado mensal'!AF$2,#REF!, "<"&EOMONTH('Faturado mensal'!AF$2,0)) -> 0 | AG70: =SUMIFS(#REF!,#REF!, $A70,#REF!, ">="&'Faturado mensal'!AG$2,#REF!, "<"&EOMONTH('Faturado mensal'!AG$2,0)) -> 0 | ... AK70: =SUMIFS(#REF!,#REF!, $A70,#REF!, ">="&'Faturado mensal'!AK$2,#REF!, "<"&EOMONTH('Faturado mensal'!AK$2,0)) -> 0 | AL70: =SUMIFS(#REF!,#REF!, $A70,#REF!, ">="&Z$2,#REF!, "<"&EOMONTH(AK$2,0)) -> 0
A71: CS0000812 | B71: 070075893 | C71: ANTONIO CESAR DE FARIA JUNIOR | D71: Concluído | E71: RECURSOS HUMANOS | F71: ALUGUÉIS DIVERSOS | G71: INDUSTRIAL SRS | H71: C | I71: ANTONIO CESAR DE FARIA JUNIOR | J71: 30 DIAS | K71: SRSFAB | L71: PRGM . COMPRAS - SRS - FABRICA | M71: =SUMIFS(#REF!,#REF!, $A71,#REF!, ">="&'Faturado mensal'!M$2,#REF!, "<"&EOMONTH('Faturado mensal'!M$2,0)) -> 2950 | N71: =SUMIFS(#REF!,#REF!, $A71,#REF!, ">="&'Faturado mensal'!N$2,#REF!, "<"&EOMONTH('Faturado mensal'!N$2,0)) -> 2950 | O71: =SUMIFS(#REF!,#REF!, $A71,#REF!, ">="&'Faturado mensal'!O$2,#REF!, "<"&EOMONTH('Faturado mensal'!O$2,0)) -> 2950 | P71: =SUMIFS(#REF!,#REF!, $A71,#REF!, ">="&'Faturado mensal'!P$2,#REF!, "<"&EOMONTH('Faturado mensal'!P$2,0)) -> 2950 | Q71: =SUMIFS(#REF!,#REF!, $A71,#REF!, ">="&'Faturado mensal'!Q$2,#REF!, "<"&EOMONTH('Faturado mensal'!Q$2,0)) -> 2950 | R71: =SUMIFS(#REF!,#REF!, $A71,#REF!, ">="&'Faturado mensal'!R$2,#REF!, "<"&EOMONTH('Faturado mensal'!R$2,0)) -> 2950 | S71: =SUMIFS(#REF!,#REF!, $A71,#REF!, ">="&'Faturado mensal'!S$2,#REF!, "<"&EOMONTH('Faturado mensal'!S$2,0)) -> 2950 | T71: =SUMIFS(#REF!,#REF!, $A71,#REF!, ">="&'Faturado mensal'!T$2,#REF!, "<"&EOMONTH('Faturado mensal'!T$2,0)) -> 2950 | ... X71: =SUMIFS(#REF!,#REF!, $A71,#REF!, ">="&'Faturado mensal'!X$2,#REF!, "<"&EOMONTH('Faturado mensal'!X$2,0)) -> 2950 | Y71: =SUMIFS(#REF!,#REF!, $A71,#REF!, ">="&'Faturado mensal'!M$2,#REF!, "<"&EOMONTH('Faturado mensal'!M$2,12)) -> 38350 | Z71: =SUMIFS(#REF!,#REF!, $A71,#REF!, ">="&'Faturado mensal'!Z$2,#REF!, "<"&EOMONTH('Faturado mensal'!Z$2,0)) -> 2950 | AA71: =SUMIFS(#REF!,#REF!, $A71,#REF!, ">="&'Faturado mensal'!AA$2,#REF!, "<"&EOMONTH('Faturado mensal'!AA$2,0)) -> 2950 | AB71: =SUMIFS(#REF!,#REF!, $A71,#REF!, ">="&'Faturado mensal'!AB$2,#REF!, "<"&EOMONTH('Faturado mensal'!AB$2,0)) -> 2950 | AC71: =SUMIFS(#REF!,#REF!, $A71,#REF!, ">="&'Faturado mensal'!AC$2,#REF!, "<"&EOMONTH('Faturado mensal'!AC$2,0)) -> 2950 | AD71: =SUMIFS(#REF!,#REF!, $A71,#REF!, ">="&'Faturado mensal'!AD$2,#REF!, "<"&EOMONTH('Faturado mensal'!AD$2,0)) -> 2950 | AE71: =SUMIFS(#REF!,#REF!, $A71,#REF!, ">="&'Faturado mensal'!AE$2,#REF!, "<"&EOMONTH('Faturado mensal'!AE$2,0)) -> 2950 | AF71: =SUMIFS(#REF!,#REF!, $A71,#REF!, ">="&'Faturado mensal'!AF$2,#REF!, "<"&EOMONTH('Faturado mensal'!AF$2,0)) -> 0 | AG71: =SUMIFS(#REF!,#REF!, $A71,#REF!, ">="&'Faturado mensal'!AG$2,#REF!, "<"&EOMONTH('Faturado mensal'!AG$2,0)) -> 0 | ... AK71: =SUMIFS(#REF!,#REF!, $A71,#REF!, ">="&'Faturado mensal'!AK$2,#REF!, "<"&EOMONTH('Faturado mensal'!AK$2,0)) -> 0 | AL71: =SUMIFS(#REF!,#REF!, $A71,#REF!, ">="&Z$2,#REF!, "<"&EOMONTH(AK$2,0)) -> 17700
A72: CS0000814 | B72: 070001506 | C72: MARCIO ADRIANO AUGUSTO 01651506612 | D72: Concluído | G72: INDUSTRIAL SRS | H72: Indef | I72: MARCIO ADRIANO AUGUSTO 0165150 | J72: 30 DIAS | K72: SRSFAB | L72: PRGM . COMPRAS - SRS - FABRICA | M72: =SUMIFS(#REF!,#REF!, $A72,#REF!, ">="&'Faturado mensal'!M$2,#REF!, "<"&EOMONTH('Faturado mensal'!M$2,0)) -> 0 | N72: =SUMIFS(#REF!,#REF!, $A72,#REF!, ">="&'Faturado mensal'!N$2,#REF!, "<"&EOMONTH('Faturado mensal'!N$2,0)) -> 0 | O72: =SUMIFS(#REF!,#REF!, $A72,#REF!, ">="&'Faturado mensal'!O$2,#REF!, "<"&EOMONTH('Faturado mensal'!O$2,0)) -> 0 | P72: =SUMIFS(#REF!,#REF!, $A72,#REF!, ">="&'Faturado mensal'!P$2,#REF!, "<"&EOMONTH('Faturado mensal'!P$2,0)) -> 0 | Q72: =SUMIFS(#REF!,#REF!, $A72,#REF!, ">="&'Faturado mensal'!Q$2,#REF!, "<"&EOMONTH('Faturado mensal'!Q$2,0)) -> 0 | R72: =SUMIFS(#REF!,#REF!, $A72,#REF!, ">="&'Faturado mensal'!R$2,#REF!, "<"&EOMONTH('Faturado mensal'!R$2,0)) -> 0 | S72: =SUMIFS(#REF!,#REF!, $A72,#REF!, ">="&'Faturado mensal'!S$2,#REF!, "<"&EOMONTH('Faturado mensal'!S$2,0)) -> 0 | T72: =SUMIFS(#REF!,#REF!, $A72,#REF!, ">="&'Faturado mensal'!T$2,#REF!, "<"&EOMONTH('Faturado mensal'!T$2,0)) -> 0 | ... X72: =SUMIFS(#REF!,#REF!, $A72,#REF!, ">="&'Faturado mensal'!X$2,#REF!, "<"&EOMONTH('Faturado mensal'!X$2,0)) -> 0 | Y72: =SUMIFS(#REF!,#REF!, $A72,#REF!, ">="&'Faturado mensal'!M$2,#REF!, "<"&EOMONTH('Faturado mensal'!M$2,12)) -> 0 | Z72: =SUMIFS(#REF!,#REF!, $A72,#REF!, ">="&'Faturado mensal'!Z$2,#REF!, "<"&EOMONTH('Faturado mensal'!Z$2,0)) -> 0 | AA72: =SUMIFS(#REF!,#REF!, $A72,#REF!, ">="&'Faturado mensal'!AA$2,#REF!, "<"&EOMONTH('Faturado mensal'!AA$2,0)) -> 0 | AB72: =SUMIFS(#REF!,#REF!, $A72,#REF!, ">="&'Faturado mensal'!AB$2,#REF!, "<"&EOMONTH('Faturado mensal'!AB$2,0)) -> 0 | AC72: =SUMIFS(#REF!,#REF!, $A72,#REF!, ">="&'Faturado mensal'!AC$2,#REF!, "<"&EOMONTH('Faturado mensal'!AC$2,0)) -> 0 | AD72: =SUMIFS(#REF!,#REF!, $A72,#REF!, ">="&'Faturado mensal'!AD$2,#REF!, "<"&EOMONTH('Faturado mensal'!AD$2,0)) -> 0 | AE72: =SUMIFS(#REF!,#REF!, $A72,#REF!, ">="&'Faturado mensal'!AE$2,#REF!, "<"&EOMONTH('Faturado mensal'!AE$2,0)) -> 0 | AF72: =SUMIFS(#REF!,#REF!, $A72,#REF!, ">="&'Faturado mensal'!AF$2,#REF!, "<"&EOMONTH('Faturado mensal'!AF$2,0)) -> 0 | AG72: =SUMIFS(#REF!,#REF!, $A72,#REF!, ">="&'Faturado mensal'!AG$2,#REF!, "<"&EOMONTH('Faturado mensal'!AG$2,0)) -> 0 | ... AK72: =SUMIFS(#REF!,#REF!, $A72,#REF!, ">="&'Faturado mensal'!AK$2,#REF!, "<"&EOMONTH('Faturado mensal'!AK$2,0)) -> 0 | AL72: =SUMIFS(#REF!,#REF!, $A72,#REF!, ">="&Z$2,#REF!, "<"&EOMONTH(AK$2,0)) -> 0
A73: CS0000816 | B73: 070001734 | C73: WAKE Commerce LTDA | D73: Concluído | G73: ADMINISTRATIVO | H73: B | I73: FBITS DESENVOLVIMENTO DE SOFTW | J73: 30 DIAS | K73: SRSCML | L73: COMPRAS - SRS - COMERCIAL | M73: =SUMIFS(#REF!,#REF!, $A73,#REF!, ">="&'Faturado mensal'!M$2,#REF!, "<"&EOMONTH('Faturado mensal'!M$2,0)) -> 0 | N73: =SUMIFS(#REF!,#REF!, $A73,#REF!, ">="&'Faturado mensal'!N$2,#REF!, "<"&EOMONTH('Faturado mensal'!N$2,0)) -> 0 | O73: =SUMIFS(#REF!,#REF!, $A73,#REF!, ">="&'Faturado mensal'!O$2,#REF!, "<"&EOMONTH('Faturado mensal'!O$2,0)) -> 0 | P73: =SUMIFS(#REF!,#REF!, $A73,#REF!, ">="&'Faturado mensal'!P$2,#REF!, "<"&EOMONTH('Faturado mensal'!P$2,0)) -> 0 | Q73: =SUMIFS(#REF!,#REF!, $A73,#REF!, ">="&'Faturado mensal'!Q$2,#REF!, "<"&EOMONTH('Faturado mensal'!Q$2,0)) -> 0 | R73: =SUMIFS(#REF!,#REF!, $A73,#REF!, ">="&'Faturado mensal'!R$2,#REF!, "<"&EOMONTH('Faturado mensal'!R$2,0)) -> 0 | S73: =SUMIFS(#REF!,#REF!, $A73,#REF!, ">="&'Faturado mensal'!S$2,#REF!, "<"&EOMONTH('Faturado mensal'!S$2,0)) -> 0 | T73: =SUMIFS(#REF!,#REF!, $A73,#REF!, ">="&'Faturado mensal'!T$2,#REF!, "<"&EOMONTH('Faturado mensal'!T$2,0)) -> 0 | ... X73: =SUMIFS(#REF!,#REF!, $A73,#REF!, ">="&'Faturado mensal'!X$2,#REF!, "<"&EOMONTH('Faturado mensal'!X$2,0)) -> 0 | Y73: =SUMIFS(#REF!,#REF!, $A73,#REF!, ">="&'Faturado mensal'!M$2,#REF!, "<"&EOMONTH('Faturado mensal'!M$2,12)) -> 0 | Z73: =SUMIFS(#REF!,#REF!, $A73,#REF!, ">="&'Faturado mensal'!Z$2,#REF!, "<"&EOMONTH('Faturado mensal'!Z$2,0)) -> 0 | AA73: =SUMIFS(#REF!,#REF!, $A73,#REF!, ">="&'Faturado mensal'!AA$2,#REF!, "<"&EOMONTH('Faturado mensal'!AA$2,0)) -> 0 | AB73: =SUMIFS(#REF!,#REF!, $A73,#REF!, ">="&'Faturado mensal'!AB$2,#REF!, "<"&EOMONTH('Faturado mensal'!AB$2,0)) -> 0 | AC73: =SUMIFS(#REF!,#REF!, $A73,#REF!, ">="&'Faturado mensal'!AC$2,#REF!, "<"&EOMONTH('Faturado mensal'!AC$2,0)) -> 0 | AD73: =SUMIFS(#REF!,#REF!, $A73,#REF!, ">="&'Faturado mensal'!AD$2,#REF!, "<"&EOMONTH('Faturado mensal'!AD$2,0)) -> 0 | AE73: =SUMIFS(#REF!,#REF!, $A73,#REF!, ">="&'Faturado mensal'!AE$2,#REF!, "<"&EOMONTH('Faturado mensal'!AE$2,0)) -> 0 | AF73: =SUMIFS(#REF!,#REF!, $A73,#REF!, ">="&'Faturado mensal'!AF$2,#REF!, "<"&EOMONTH('Faturado mensal'!AF$2,0)) -> 0 | AG73: =SUMIFS(#REF!,#REF!, $A73,#REF!, ">="&'Faturado mensal'!AG$2,#REF!, "<"&EOMONTH('Faturado mensal'!AG$2,0)) -> 0 | ... AK73: =SUMIFS(#REF!,#REF!, $A73,#REF!, ">="&'Faturado mensal'!AK$2,#REF!, "<"&EOMONTH('Faturado mensal'!AK$2,0)) -> 0 | AL73: =SUMIFS(#REF!,#REF!, $A73,#REF!, ">="&Z$2,#REF!, "<"&EOMONTH(AK$2,0)) -> 0
A74: CS0000820 | B74: 090003326 | C74: TECMES TEC.M.SERV.INF.S/C LTDA | D74: Ativo | E74: ENGENHARIA PRODUTO | F74: SOTWARE-CATIA | G74: ENGENHARIA PRODUTO | H74: B | I74: TECMES TEC.M.SERV.INF.S/C LTDA | J74: 30 DIAS | K74: VIESFB | L74: PRGM .COMPRAS - VIES - FABRICA | M74: =SUMIFS(#REF!,#REF!, $A74,#REF!, ">="&'Faturado mensal'!M$2,#REF!, "<"&EOMONTH('Faturado mensal'!M$2,0)) -> 0 | N74: =SUMIFS(#REF!,#REF!, $A74,#REF!, ">="&'Faturado mensal'!N$2,#REF!, "<"&EOMONTH('Faturado mensal'!N$2,0)) -> 0 | O74: =SUMIFS(#REF!,#REF!, $A74,#REF!, ">="&'Faturado mensal'!O$2,#REF!, "<"&EOMONTH('Faturado mensal'!O$2,0)) -> 0 | P74: =SUMIFS(#REF!,#REF!, $A74,#REF!, ">="&'Faturado mensal'!P$2,#REF!, "<"&EOMONTH('Faturado mensal'!P$2,0)) -> 0 | Q74: =SUMIFS(#REF!,#REF!, $A74,#REF!, ">="&'Faturado mensal'!Q$2,#REF!, "<"&EOMONTH('Faturado mensal'!Q$2,0)) -> 10734.03 | R74: =SUMIFS(#REF!,#REF!, $A74,#REF!, ">="&'Faturado mensal'!R$2,#REF!, "<"&EOMONTH('Faturado mensal'!R$2,0)) -> 0 | S74: =SUMIFS(#REF!,#REF!, $A74,#REF!, ">="&'Faturado mensal'!S$2,#REF!, "<"&EOMONTH('Faturado mensal'!S$2,0)) -> 0 | T74: =SUMIFS(#REF!,#REF!, $A74,#REF!, ">="&'Faturado mensal'!T$2,#REF!, "<"&EOMONTH('Faturado mensal'!T$2,0)) -> 39413.39 | ... X74: =SUMIFS(#REF!,#REF!, $A74,#REF!, ">="&'Faturado mensal'!X$2,#REF!, "<"&EOMONTH('Faturado mensal'!X$2,0)) -> 0 | Y74: =SUMIFS(#REF!,#REF!, $A74,#REF!, ">="&'Faturado mensal'!M$2,#REF!, "<"&EOMONTH('Faturado mensal'!M$2,12)) -> 60881.45 | Z74: =SUMIFS(#REF!,#REF!, $A74,#REF!, ">="&'Faturado mensal'!Z$2,#REF!, "<"&EOMONTH('Faturado mensal'!Z$2,0)) -> 0 | AA74: =SUMIFS(#REF!,#REF!, $A74,#REF!, ">="&'Faturado mensal'!AA$2,#REF!, "<"&EOMONTH('Faturado mensal'!AA$2,0)) -> 10734.03 | AB74: =SUMIFS(#REF!,#REF!, $A74,#REF!, ">="&'Faturado mensal'!AB$2,#REF!, "<"&EOMONTH('Faturado mensal'!AB$2,0)) -> 0 | AC74: =SUMIFS(#REF!,#REF!, $A74,#REF!, ">="&'Faturado mensal'!AC$2,#REF!, "<"&EOMONTH('Faturado mensal'!AC$2,0)) -> 0 | AD74: =SUMIFS(#REF!,#REF!, $A74,#REF!, ">="&'Faturado mensal'!AD$2,#REF!, "<"&EOMONTH('Faturado mensal'!AD$2,0)) -> 11658.95 | AE74: =SUMIFS(#REF!,#REF!, $A74,#REF!, ">="&'Faturado mensal'!AE$2,#REF!, "<"&EOMONTH('Faturado mensal'!AE$2,0)) -> 0 | AF74: =SUMIFS(#REF!,#REF!, $A74,#REF!, ">="&'Faturado mensal'!AF$2,#REF!, "<"&EOMONTH('Faturado mensal'!AF$2,0)) -> 0 | AG74: =SUMIFS(#REF!,#REF!, $A74,#REF!, ">="&'Faturado mensal'!AG$2,#REF!, "<"&EOMONTH('Faturado mensal'!AG$2,0)) -> 0 | ... AK74: =SUMIFS(#REF!,#REF!, $A74,#REF!, ">="&'Faturado mensal'!AK$2,#REF!, "<"&EOMONTH('Faturado mensal'!AK$2,0)) -> 0 | AL74: =SUMIFS(#REF!,#REF!, $A74,#REF!, ">="&Z$2,#REF!, "<"&EOMONTH(AK$2,0)) -> 22392.98
A75: CS0000821 | B75: 090017099 | C75: MART.NETO E G.ADV.ASSOC. S/C. | D75: Concluído | G75: ADMINISTRATIVO | H75: C | I75: MART.NETO E G.ADV.ASSOC. S/C. | J75: 30 DIAS | K75: VIESFB | L75: PRGM .COMPRAS - VIES - FABRICA | M75: =SUMIFS(#REF!,#REF!, $A75,#REF!, ">="&'Faturado mensal'!M$2,#REF!, "<"&EOMONTH('Faturado mensal'!M$2,0)) -> 0 | N75: =SUMIFS(#REF!,#REF!, $A75,#REF!, ">="&'Faturado mensal'!N$2,#REF!, "<"&EOMONTH('Faturado mensal'!N$2,0)) -> 0 | O75: =SUMIFS(#REF!,#REF!, $A75,#REF!, ">="&'Faturado mensal'!O$2,#REF!, "<"&EOMONTH('Faturado mensal'!O$2,0)) -> 0 | P75: =SUMIFS(#REF!,#REF!, $A75,#REF!, ">="&'Faturado mensal'!P$2,#REF!, "<"&EOMONTH('Faturado mensal'!P$2,0)) -> 0 | Q75: =SUMIFS(#REF!,#REF!, $A75,#REF!, ">="&'Faturado mensal'!Q$2,#REF!, "<"&EOMONTH('Faturado mensal'!Q$2,0)) -> 0 | R75: =SUMIFS(#REF!,#REF!, $A75,#REF!, ">="&'Faturado mensal'!R$2,#REF!, "<"&EOMONTH('Faturado mensal'!R$2,0)) -> 0 | S75: =SUMIFS(#REF!,#REF!, $A75,#REF!, ">="&'Faturado mensal'!S$2,#REF!, "<"&EOMONTH('Faturado mensal'!S$2,0)) -> 0 | T75: =SUMIFS(#REF!,#REF!, $A75,#REF!, ">="&'Faturado mensal'!T$2,#REF!, "<"&EOMONTH('Faturado mensal'!T$2,0)) -> 0 | ... X75: =SUMIFS(#REF!,#REF!, $A75,#REF!, ">="&'Faturado mensal'!X$2,#REF!, "<"&EOMONTH('Faturado mensal'!X$2,0)) -> 0 | Y75: =SUMIFS(#REF!,#REF!, $A75,#REF!, ">="&'Faturado mensal'!M$2,#REF!, "<"&EOMONTH('Faturado mensal'!M$2,12)) -> 0 | Z75: =SUMIFS(#REF!,#REF!, $A75,#REF!, ">="&'Faturado mensal'!Z$2,#REF!, "<"&EOMONTH('Faturado mensal'!Z$2,0)) -> 0 | AA75: =SUMIFS(#REF!,#REF!, $A75,#REF!, ">="&'Faturado mensal'!AA$2,#REF!, "<"&EOMONTH('Faturado mensal'!AA$2,0)) -> 0 | AB75: =SUMIFS(#REF!,#REF!, $A75,#REF!, ">="&'Faturado mensal'!AB$2,#REF!, "<"&EOMONTH('Faturado mensal'!AB$2,0)) -> 0 | AC75: =SUMIFS(#REF!,#REF!, $A75,#REF!, ">="&'Faturado mensal'!AC$2,#REF!, "<"&EOMONTH('Faturado mensal'!AC$2,0)) -> 0 | AD75: =SUMIFS(#REF!,#REF!, $A75,#REF!, ">="&'Faturado mensal'!AD$2,#REF!, "<"&EOMONTH('Faturado mensal'!AD$2,0)) -> 0 | AE75: =SUMIFS(#REF!,#REF!, $A75,#REF!, ">="&'Faturado mensal'!AE$2,#REF!, "<"&EOMONTH('Faturado mensal'!AE$2,0)) -> 0 | AF75: =SUMIFS(#REF!,#REF!, $A75,#REF!, ">="&'Faturado mensal'!AF$2,#REF!, "<"&EOMONTH('Faturado mensal'!AF$2,0)) -> 0 | AG75: =SUMIFS(#REF!,#REF!, $A75,#REF!, ">="&'Faturado mensal'!AG$2,#REF!, "<"&EOMONTH('Faturado mensal'!AG$2,0)) -> 0 | ... AK75: =SUMIFS(#REF!,#REF!, $A75,#REF!, ">="&'Faturado mensal'!AK$2,#REF!, "<"&EOMONTH('Faturado mensal'!AK$2,0)) -> 0 | AL75: =SUMIFS(#REF!,#REF!, $A75,#REF!, ">="&Z$2,#REF!, "<"&EOMONTH(AK$2,0)) -> 0
A76: CS0000822 | B76: 070075970 | C76: TB SERVICOS T L G R HUMANOS SA | D76: Concluído | I76: TB SERVICOS T L G R HUMANOS SA | J76: 30 DIAS | K76: VIESFB | L76: PRGM .COMPRAS - VIES - FABRICA | M76: =SUMIFS(#REF!,#REF!, $A76,#REF!, ">="&'Faturado mensal'!M$2,#REF!, "<"&EOMONTH('Faturado mensal'!M$2,0)) -> 0 | N76: =SUMIFS(#REF!,#REF!, $A76,#REF!, ">="&'Faturado mensal'!N$2,#REF!, "<"&EOMONTH('Faturado mensal'!N$2,0)) -> 0 | O76: =SUMIFS(#REF!,#REF!, $A76,#REF!, ">="&'Faturado mensal'!O$2,#REF!, "<"&EOMONTH('Faturado mensal'!O$2,0)) -> 0 | P76: =SUMIFS(#REF!,#REF!, $A76,#REF!, ">="&'Faturado mensal'!P$2,#REF!, "<"&EOMONTH('Faturado mensal'!P$2,0)) -> 0 | Q76: =SUMIFS(#REF!,#REF!, $A76,#REF!, ">="&'Faturado mensal'!Q$2,#REF!, "<"&EOMONTH('Faturado mensal'!Q$2,0)) -> 0 | R76: =SUMIFS(#REF!,#REF!, $A76,#REF!, ">="&'Faturado mensal'!R$2,#REF!, "<"&EOMONTH('Faturado mensal'!R$2,0)) -> 0 | S76: =SUMIFS(#REF!,#REF!, $A76,#REF!, ">="&'Faturado mensal'!S$2,#REF!, "<"&EOMONTH('Faturado mensal'!S$2,0)) -> 0 | T76: =SUMIFS(#REF!,#REF!, $A76,#REF!, ">="&'Faturado mensal'!T$2,#REF!, "<"&EOMONTH('Faturado mensal'!T$2,0)) -> 0 | ... X76: =SUMIFS(#REF!,#REF!, $A76,#REF!, ">="&'Faturado mensal'!X$2,#REF!, "<"&EOMONTH('Faturado mensal'!X$2,0)) -> 0 | Y76: =SUMIFS(#REF!,#REF!, $A76,#REF!, ">="&'Faturado mensal'!M$2,#REF!, "<"&EOMONTH('Faturado mensal'!M$2,12)) -> 0 | Z76: =SUMIFS(#REF!,#REF!, $A76,#REF!, ">="&'Faturado mensal'!Z$2,#REF!, "<"&EOMONTH('Faturado mensal'!Z$2,0)) -> 0 | AA76: =SUMIFS(#REF!,#REF!, $A76,#REF!, ">="&'Faturado mensal'!AA$2,#REF!, "<"&EOMONTH('Faturado mensal'!AA$2,0)) -> 0 | AB76: =SUMIFS(#REF!,#REF!, $A76,#REF!, ">="&'Faturado mensal'!AB$2,#REF!, "<"&EOMONTH('Faturado mensal'!AB$2,0)) -> 0 | AC76: =SUMIFS(#REF!,#REF!, $A76,#REF!, ">="&'Faturado mensal'!AC$2,#REF!, "<"&EOMONTH('Faturado mensal'!AC$2,0)) -> 0 | AD76: =SUMIFS(#REF!,#REF!, $A76,#REF!, ">="&'Faturado mensal'!AD$2,#REF!, "<"&EOMONTH('Faturado mensal'!AD$2,0)) -> 0 | AE76: =SUMIFS(#REF!,#REF!, $A76,#REF!, ">="&'Faturado mensal'!AE$2,#REF!, "<"&EOMONTH('Faturado mensal'!AE$2,0)) -> 0 | AF76: =SUMIFS(#REF!,#REF!, $A76,#REF!, ">="&'Faturado mensal'!AF$2,#REF!, "<"&EOMONTH('Faturado mensal'!AF$2,0)) -> 0 | AG76: =SUMIFS(#REF!,#REF!, $A76,#REF!, ">="&'Faturado mensal'!AG$2,#REF!, "<"&EOMONTH('Faturado mensal'!AG$2,0)) -> 0 | ... AK76: =SUMIFS(#REF!,#REF!, $A76,#REF!, ">="&'Faturado mensal'!AK$2,#REF!, "<"&EOMONTH('Faturado mensal'!AK$2,0)) -> 0 | AL76: =SUMIFS(#REF!,#REF!, $A76,#REF!, ">="&Z$2,#REF!, "<"&EOMONTH(AK$2,0)) -> 0
A77: CS0000823 | B77: 070075932 | C77: PURIFIKAR LOC.DIST.PRO.DO.LTDA | D77: Concluído | I77: PURIFIKAR LOC.DIST.PRO.DO.LTDA | J77: 30 DIAS | K77: VIESFB | L77: PRGM .COMPRAS - VIES - FABRICA | M77: =SUMIFS(#REF!,#REF!, $A77,#REF!, ">="&'Faturado mensal'!M$2,#REF!, "<"&EOMONTH('Faturado mensal'!M$2,0)) -> 0 | N77: =SUMIFS(#REF!,#REF!, $A77,#REF!, ">="&'Faturado mensal'!N$2,#REF!, "<"&EOMONTH('Faturado mensal'!N$2,0)) -> 0 | O77: =SUMIFS(#REF!,#REF!, $A77,#REF!, ">="&'Faturado mensal'!O$2,#REF!, "<"&EOMONTH('Faturado mensal'!O$2,0)) -> 0 | P77: =SUMIFS(#REF!,#REF!, $A77,#REF!, ">="&'Faturado mensal'!P$2,#REF!, "<"&EOMONTH('Faturado mensal'!P$2,0)) -> 0 | Q77: =SUMIFS(#REF!,#REF!, $A77,#REF!, ">="&'Faturado mensal'!Q$2,#REF!, "<"&EOMONTH('Faturado mensal'!Q$2,0)) -> 0 | R77: =SUMIFS(#REF!,#REF!, $A77,#REF!, ">="&'Faturado mensal'!R$2,#REF!, "<"&EOMONTH('Faturado mensal'!R$2,0)) -> 0 | S77: =SUMIFS(#REF!,#REF!, $A77,#REF!, ">="&'Faturado mensal'!S$2,#REF!, "<"&EOMONTH('Faturado mensal'!S$2,0)) -> 0 | T77: =SUMIFS(#REF!,#REF!, $A77,#REF!, ">="&'Faturado mensal'!T$2,#REF!, "<"&EOMONTH('Faturado mensal'!T$2,0)) -> 0 | ... X77: =SUMIFS(#REF!,#REF!, $A77,#REF!, ">="&'Faturado mensal'!X$2,#REF!, "<"&EOMONTH('Faturado mensal'!X$2,0)) -> 0 | Y77: =SUMIFS(#REF!,#REF!, $A77,#REF!, ">="&'Faturado mensal'!M$2,#REF!, "<"&EOMONTH('Faturado mensal'!M$2,12)) -> 0 | Z77: =SUMIFS(#REF!,#REF!, $A77,#REF!, ">="&'Faturado mensal'!Z$2,#REF!, "<"&EOMONTH('Faturado mensal'!Z$2,0)) -> 0 | AA77: =SUMIFS(#REF!,#REF!, $A77,#REF!, ">="&'Faturado mensal'!AA$2,#REF!, "<"&EOMONTH('Faturado mensal'!AA$2,0)) -> 0 | AB77: =SUMIFS(#REF!,#REF!, $A77,#REF!, ">="&'Faturado mensal'!AB$2,#REF!, "<"&EOMONTH('Faturado mensal'!AB$2,0)) -> 0 | AC77: =SUMIFS(#REF!,#REF!, $A77,#REF!, ">="&'Faturado mensal'!AC$2,#REF!, "<"&EOMONTH('Faturado mensal'!AC$2,0)) -> 0 | AD77: =SUMIFS(#REF!,#REF!, $A77,#REF!, ">="&'Faturado mensal'!AD$2,#REF!, "<"&EOMONTH('Faturado mensal'!AD$2,0)) -> 0 | AE77: =SUMIFS(#REF!,#REF!, $A77,#REF!, ">="&'Faturado mensal'!AE$2,#REF!, "<"&EOMONTH('Faturado mensal'!AE$2,0)) -> 0 | AF77: =SUMIFS(#REF!,#REF!, $A77,#REF!, ">="&'Faturado mensal'!AF$2,#REF!, "<"&EOMONTH('Faturado mensal'!AF$2,0)) -> 0 | AG77: =SUMIFS(#REF!,#REF!, $A77,#REF!, ">="&'Faturado mensal'!AG$2,#REF!, "<"&EOMONTH('Faturado mensal'!AG$2,0)) -> 0 | ... AK77: =SUMIFS(#REF!,#REF!, $A77,#REF!, ">="&'Faturado mensal'!AK$2,#REF!, "<"&EOMONTH('Faturado mensal'!AK$2,0)) -> 0 | AL77: =SUMIFS(#REF!,#REF!, $A77,#REF!, ">="&Z$2,#REF!, "<"&EOMONTH(AK$2,0)) -> 0
A78: CS0000824 | B78: 070075890 | C78: LABORTECHNIC TEC.LTDA - EPP | D78: Ativo | E78: QSMA | F78: SERVIÇOS PRESTADOS | G78: INDUSTRIAL VIES | H78: B | I78: LABORTECHNIC TEC.LTDA - EPP | J78: 30 DIAS | K78: VIESFB | L78: PRGM .COMPRAS - VIES - FABRICA | M78: =SUMIFS(#REF!,#REF!, $A78,#REF!, ">="&'Faturado mensal'!M$2,#REF!, "<"&EOMONTH('Faturado mensal'!M$2,0)) -> 180 | N78: =SUMIFS(#REF!,#REF!, $A78,#REF!, ">="&'Faturado mensal'!N$2,#REF!, "<"&EOMONTH('Faturado mensal'!N$2,0)) -> 180 | O78: =SUMIFS(#REF!,#REF!, $A78,#REF!, ">="&'Faturado mensal'!O$2,#REF!, "<"&EOMONTH('Faturado mensal'!O$2,0)) -> 0 | P78: =SUMIFS(#REF!,#REF!, $A78,#REF!, ">="&'Faturado mensal'!P$2,#REF!, "<"&EOMONTH('Faturado mensal'!P$2,0)) -> 180 | Q78: =SUMIFS(#REF!,#REF!, $A78,#REF!, ">="&'Faturado mensal'!Q$2,#REF!, "<"&EOMONTH('Faturado mensal'!Q$2,0)) -> 610 | R78: =SUMIFS(#REF!,#REF!, $A78,#REF!, ">="&'Faturado mensal'!R$2,#REF!, "<"&EOMONTH('Faturado mensal'!R$2,0)) -> 0 | S78: =SUMIFS(#REF!,#REF!, $A78,#REF!, ">="&'Faturado mensal'!S$2,#REF!, "<"&EOMONTH('Faturado mensal'!S$2,0)) -> 190 | T78: =SUMIFS(#REF!,#REF!, $A78,#REF!, ">="&'Faturado mensal'!T$2,#REF!, "<"&EOMONTH('Faturado mensal'!T$2,0)) -> 190 | ... X78: =SUMIFS(#REF!,#REF!, $A78,#REF!, ">="&'Faturado mensal'!X$2,#REF!, "<"&EOMONTH('Faturado mensal'!X$2,0)) -> 640 | Y78: =SUMIFS(#REF!,#REF!, $A78,#REF!, ">="&'Faturado mensal'!M$2,#REF!, "<"&EOMONTH('Faturado mensal'!M$2,12)) -> 3380 | Z78: =SUMIFS(#REF!,#REF!, $A78,#REF!, ">="&'Faturado mensal'!Z$2,#REF!, "<"&EOMONTH('Faturado mensal'!Z$2,0)) -> 190 | AA78: =SUMIFS(#REF!,#REF!, $A78,#REF!, ">="&'Faturado mensal'!AA$2,#REF!, "<"&EOMONTH('Faturado mensal'!AA$2,0)) -> 190 | AB78: =SUMIFS(#REF!,#REF!, $A78,#REF!, ">="&'Faturado mensal'!AB$2,#REF!, "<"&EOMONTH('Faturado mensal'!AB$2,0)) -> 0 | AC78: =SUMIFS(#REF!,#REF!, $A78,#REF!, ">="&'Faturado mensal'!AC$2,#REF!, "<"&EOMONTH('Faturado mensal'!AC$2,0)) -> 640 | AD78: =SUMIFS(#REF!,#REF!, $A78,#REF!, ">="&'Faturado mensal'!AD$2,#REF!, "<"&EOMONTH('Faturado mensal'!AD$2,0)) -> 0 | AE78: =SUMIFS(#REF!,#REF!, $A78,#REF!, ">="&'Faturado mensal'!AE$2,#REF!, "<"&EOMONTH('Faturado mensal'!AE$2,0)) -> 0 | AF78: =SUMIFS(#REF!,#REF!, $A78,#REF!, ">="&'Faturado mensal'!AF$2,#REF!, "<"&EOMONTH('Faturado mensal'!AF$2,0)) -> 0 | AG78: =SUMIFS(#REF!,#REF!, $A78,#REF!, ">="&'Faturado mensal'!AG$2,#REF!, "<"&EOMONTH('Faturado mensal'!AG$2,0)) -> 0 | ... AK78: =SUMIFS(#REF!,#REF!, $A78,#REF!, ">="&'Faturado mensal'!AK$2,#REF!, "<"&EOMONTH('Faturado mensal'!AK$2,0)) -> 0 | AL78: =SUMIFS(#REF!,#REF!, $A78,#REF!, ">="&Z$2,#REF!, "<"&EOMONTH(AK$2,0)) -> 1220
